Workbook

Sheet Dashboard 2023
A1: DASHBOARD - MAIN REASONS - 2023 | AP1: No
A2: Reason | B2: Total $ | C2: % | D2: CR | F2: Faturamento 2023 | G2: =252.626363992077 -> 252.62636
A3: Shipment delay | B3: 73636.32 | C3: 0.18023872 | D3: No
A4: Customer reschedule | B4: 52194.37 | C4: 0.12775552 | D4: Yes | F4: Premium Total | G4: =GETPIVOTDATA("Total $",$A$2)/1000000 -> 0.40854883
A5: Stock discrepancy | B5: 50584.37 | C5: 0.12381475 | D5: No | F5: % Premium Total/ fat | G5: =G4/G2 -> 0.0016172058
A6: Internal Strategy/ discount | B6: 44192.13 | C6: 0.10816854 | D6: No
A7: Project | B7: 44059.27 | C7: 0.10784334 | D7: Yes | F7: CR Non recoverable | G7: =(SUMIF($D$3:$D$20,$AP$1,$B$3:$B$20))/1000000 -> 0.26143235
A8: Internal problem - Manufacturing/ Ordering/ Purchasing/ IT | B8: 41301.74 | C8: 0.10109377 | D8: No | F8: % CR Non recoverable/ fat | G8: =G7/G2 -> 0.0010348577
A9: Supplier delay | B9: 33215.36 | C9: 0.081300833 | D9: Yes
A10: Lead time discrepancy between supplier/ customer | B10: 21926.49 | C10: 0.053669203 | D10: No
A11: Freight to be recovery at POV | B11: 17647.48 | C11: 0.043195522 | D11: Yes
A12: Força maior | B12: 6811.93 | C12: 0.016673478 | D12: No
A13: Cargo lost | B13: 6265.32 | C13: 0.015335548 | D13: No
A14: Lack of packaging | B14: 5926.78 | C14: 0.014506907 | D14: No
A15: P&A | B15: 4672.48 | C15: 0.011436772 | D15: No
A16: Stoled cargo | B16: 2692.61 | C16: 0.0065906687 | D16: No
A17: BOM error | B17: 2549.16 | C17: 0.0062395479 | D17: No
A18: Quality problem | B18: 873.02 | C18: 0.0021368804 | D18: No
A19: Total Geral | B19: 408548.83 | C19: 1

Sheet Details 2023
I1: =SUBTOTAL(9,I3:I920) -> 408548.83
A2: MÊS REPORTE | B2: MOTIVO | C2: PREMIUM_ID | D2: PBU_NAME | E2: CUSTOMER | F2: SHIPMENT_DATE | G2: PLANT_NAME | H2: SHIPMENT_TYPE | I2: ACTUAL_COST_IN_USD | J2: ESTIMATED_COST_IN_USD | K2: Percentual | L2: PREMIUM_REASON_CODE | M2: ORIG_PREMIUM_REASON_CODE | N2: SHIP_TO_NAME | O2: SHIP_FROM_NAME | P2: PROBLEM_DESCRIPTION | Q2: CARRIER_NAME | R2: PTA_NUMBER | S2: PART_NUMBERS_TEXT | T2: QUANTITY(In Pieces) | U2: WEIGHT | V2: COST_RECOVERY | W2: COMMODITY_TYPE | X2: SUBMITTED_BY_NAME | Y2: SUBMIT_DATE | Z2: EDIT_DATE | AA2: REGION_NAME | AB2: RECOVERY_STATUS | AC2: RECOVERED_COST_IN_USD | AD2: RECOVERED_DATE | AE2: ORIG_FREIGHT_COST_USD | AF2: LAUNCH_PERIOD | AG2: PLANT_CODE | AH2: SOURCE_SYSTEM | AI2: RECOVERED_LC | AJ2: ACTUAL_SHIP_COST_LC | AK2: COST_RECOVERY_REQUIRED | AL2: COST_RECOVERY_TRACKING | AM2: ESTIM_SHIP_COST_LC | AN2: INVOICE_CURRENCY | AO2: SHIP_FROM_ADDRESS | AP2: SHIP_FROM_CITY | AQ2: SHIP_FROM_CODE | AR2: SHIP_FROM_COUNTRY | AS2: SHIP_FROM_REGION | AT2: SHIP_FROM_STATE | AU2: SHIP_FROM_ZIP | AV2: SHIP_TO_ADDRESS | AW2: SHIP_TO_CITY | AX2: SHIP_TO_CODE | AY2: SHIP_TO_COUNTRY | AZ2: SHIP_TO_REGION | BA2: SHIP_TO_STATE | BB2: SHIP_TO_ZIP | BC2: SEGMENT | BD2: APPROVAL_STATUS | BE2: APPROVED_BY_NAME | BF2: APPROVED_DATE | BG2: TMS_LOAD_ID | BH2: ACTUAL_CARRIER | BI2: ACTUAL_CARRIER_TRACKING_NUMBER | BJ2: PREMIUM_REASON_CODE_ACTUAL | BK2: DRIVER | BL2: ACTUAL_DRIVER | BM2: ESTIMATED_COST_SOURCE | BN2: ACTUAL_COST_SOURCE | BO2: ACTUAL_CUSTOMER | BP2: ACTUAL_SUPPLIER | BQ2: TOTAL_APPROVAL_TIME | BR2: APPROVED_LEVEL_AMOUNT(USD) | BS2: APPROVER_COMMENTS | BT2: TOTAL_COST | BU2: TOTAL_COST_LESS_RECOVERIES | BV2: NO_OF_CONTAINER | BW2: DIMENSION_OF_BOX(HxWxL) | BX2: UOM | BY2: COUNTRY | BZ2: FAMILY_NAME/PROGRAM | CA2: ESTIMATED_NAME_OF_INVOICE_CURRENCY | CB2: TOP_100_SUPPLIER | CC2: NAME_OF_RECOVERED_CURRENCY | CD2: UNIT_WEIGHTS | CE2: ADDITIONAL_COMMENTARY | CF2: ESTIMATE_INVOICE_EXCHANGE_RATE | CG2: ACTUAL_INVOICE_EXCHANGE_RATE | CH2: ACTUAL_RECOVERED_INVOICE_EXCHANGE_RATE | CI2: NORMAL_SHIPMENT_COST_IN_INVOICE_CURRENCY | CJ2: NORMAL_SHIPMENT_COST_(USD) | CK2: NAME_OF_NORMAL_SHIPMENT_INVOICE_CURRENCY | CL2: NORMAL_INVOICE_EXCHANGE_RATE | CM2: PROBLEM_REASON_CODE_ACTUAL | CN2: CANCELLATION_REMARK | CO2: SHIP_FROM_DUNS | CP2: SHIP_TO_DUNS | CQ2: ACTUAL_SUPPLIER_DUNS
A3: 44927 | B3: Internal problem - Manufacturing/ Ordering/ Purchasing/ IT | C3: 39680 | D3: Manufacturing Delay | E3: GM | F3: 44929 | G3: Ouros | H3: Outbound Premium | I3: 198.23 | J3: 197.23 | K3: =I3/$I$1 -> 0.00048520516 | L3: M1L-Manufacturing low efficiency | M3: Normal | N3: GENERAL MOTORS (72664)-700535 | O3: APTIV MANUFATURA E SERVICOS DE-104120 | P3: Manufacturing Delay | Q3: TRANSPORTADORA PITUTA | R3: PTA-00085578 | S3: 35548247; | T3: ; | U3: ; | V3: Aptiv | W3: Premium - Productive | X3: adriane.barbosa.silva@aptiv.com | Y3: 44929.107 | Z3: 44931.092 | AA3: SA | AB3: Closed Not Recovered | AC3: 0 | AE3: 19823 | AG3: 10023 | AH3: Q11 | AJ3: 104943 | AK3: Non-Recoverable | AM3: 104415 | AN3: BRL | AO3: AVENIDA AVELINO RIBEIRO, 900 | AP3: PARAISOPOLIS | AQ3: 104120 | AR3: BR | AS3: SA | AT3: MG | AU3: 37660-000 | AV3: CISCO 72664 | AW3: SAO JOSE DOS CAMPOS | AX3: 700535 | AY3: BR | AZ3: SA | BA3: SP | BB3: 12224-300 | BC3: SPS | BD3: Approved | BE3: Rebello, Andre | BF3: 44929.287 | BG3: 0 | BH3: TRANSPORTADORA PITUTA | BI3: PAR-000204432 | BK3: Aptiv | BM3: Invoice | BN3: Invoice | BQ3: 0 Days 4 Hr 20 Min | BR3: 500 | BS3: Approved - ;; Approved - ; | BT3: 19823 | BU3: 19823 | BV3: ; | BW3: ; | BX3: ; | BY3: BR | CA3: BRL | CF3: 18888952 | CG3: 18888952 | CJ3: 0
A4: 44927 | B4: Shipment delay | C4: 39789 | D4: Transportation Problem - Atraso ETA | E4: JOHN DEERE | F4: 44929 | G4: Paraisopolis | H4: Inbound Premium | I4: 56.43 | J4: 90 | K4: =I4/$I$1 -> 0.00013812302 | L4: T1-Transportation | M4: Normal | N4: APTIV MANUFATURA E SERVICOS DE-104120 | O4: APTIV WARREN (FR09)-702235 | P4: CONGESTIONAMENTO DOS PORTOS | Q4: DHL Express SA | R4: PTA-00085583 | S4: 12129615; | T4: ; | U4: ; | V4: Aptiv | W4: Premium - Productive | X4: Moraes.Arnaldo@aptiv.com | Y4: 44929.295 | Z4: 44936.275 | AA4: SA | AB4: Closed Not Recovered | AC4: 0 | AE4: 5643 | AG4: 10012 | AH4: Q11 | AJ4: 5643 | AK4: Non-Recoverable | AM4: 90 | AN4: USD | AO4: 1265 N RIVER RD NE | AP4: WARREN | AQ4: 702235 | AR4: US | AS4: NA | AT4: OH | AU4: 44483 | AV4: AVENIDA AVELINO RIBEIRO, 900 | AW4: PARAISOPOLIS | AX4: 104120 | AY4: BR | AZ4: SA | BA4: MG | BB4: 37660-000 | BC4: SPS | BD4: Approved | BE4: Rebello, Andre | BF4: 44929.324 | BG4: 0 | BH4: DHL Express SA | BI4: 8449388835 | BK4: Transportation | BM4: Invoice | BN4: Invoice | BQ4: 0 Days 0 Hr 42 Min | BR4: 500 | BS4: Approved - ;; Approved - ; | BT4: 5643 | BU4: 5643 | BV4: ; | BW4: ; | BX4: ; | BY4: BR | CA4: USD | CE4: POR ERRO DO FORNECEDOR FOI EMBARCADO EM DIFERENTE TRACKING SEM PTA | CF4: 1 | CG4: 1 | CJ4: 0
A5: 44927 | B5: Shipment delay | C5: 39792 | D5: Transportation Problem - Atraso ETA | E5: JOHN DEERE | F5: 44929 | G5: Paraisopolis | H5: Inbound Premium | I5: 84.97 | J5: 80 | K5: =I5/$I$1 -> 0.00020798004 | L5: T1-Transportation | M5: Normal | N5: APTIV MANUFATURA E SERVICOS DE-104120 | O5: APTIV WARREN (FR09)-702235 | P5: CONGESTIONAMENTO DOS PORTOS | Q5: DHL Express SA | R5: PTA-00085582 | S5: 02973407; | T5: ; | U5: ; | V5: Aptiv | W5: Premium - Productive | X5: Moraes.Arnaldo@aptiv.com | Y5: 44929.296 | Z5: 44936.272 | AA5: SA | AB5: Closed Not Recovered | AC5: 0 | AE5: 8497 | AG5: 10012 | AH5: Q11 | AJ5: 8497 | AK5: Non-Recoverable | AM5: 80 | AN5: USD | AO5: 1265 N RIVER RD NE | AP5: WARREN | AQ5: 702235 | AR5: US | AS5: NA | AT5: OH | AU5: 44483 | AV5: AVENIDA AVELINO RIBEIRO, 900 | AW5: PARAISOPOLIS | AX5: 104120 | AY5: BR | AZ5: SA | BA5: MG | BB5: 37660-000 | BC5: SPS | BD5: Approved | BE5: Rebello, Andre | BF5: 44929.324 | BG5: 0 | BH5: DHL Express SA | BI5: 8449406512 | BK5: Transportation | BM5: Invoice | BN5: Invoice | BQ5: 0 Days 0 Hr 40 Min | BR5: 500 | BS5: Approved - ;; Approved - ; | BT5: 8497 | BU5: 8497 | BV5: ; | BW5: ; | BX5: ; | BY5: BR | CA5: USD | CE5: POR ERRO DO FORNECEDOR FOI EMBARCADO EM DIFERENTE TRACKING SEM PTA | CF5: 1 | CG5: 1 | CJ5: 0
A6: 44927 | B6: Shipment delay | C6: 40049 | D6: Transportation Problem - Atraso ETA | E6: TOYOTA | F6: 44931 | G6: Paraisopolis | H6: Inbound Premium | I6: 119.41 | J6: 100 | K6: =I6/$I$1 -> 0.0002922784 | L6: T1-Transportation | M6: Normal | N6: APTIV MANUFATURA E SERVICOS DE-104120 | O6: APTIV PLANT FR47-725460 | P6: Congestionamento dos portos devido o feriado de Thanksgiving nos EUA | Q6: DHL Express SA | R6: PTA-00085850 | S6: 15317587; | T6: ; | U6: ; | V6: Aptiv | W6: Premium - Productive | X6: Moraes.Arnaldo@aptiv.com | Y6: 44930.225 | Z6: 44937.244 | AA6: SA | AB6: Closed Not Recovered | AC6: 0 | AE6: 11941 | AG6: 10012 | AH6: Q11 | AJ6: 11941 | AK6: Non-Recoverable | AM6: 100 | AN6: USD | AO6: 3400 AERO PARK DR | AP6: VIENNA | AQ6: 725460 | AR6: US | AS6: NA | AT6: OH | AU6: 44473-8704 | AV6: AVENIDA AVELINO RIBEIRO, 900 | AW6: PARAISOPOLIS | AX6: 104120 | AY6: BR | AZ6: SA | BA6: MG | BB6: 37660-000 | BC6: SPS | BD6: Approved | BE6: Rebello, Andre | BF6: 44930.333 | BG6: 0 | BH6: DHL Express SA | BI6: 6911280961 | BK6: Transportation | BM6: Personal Estimate | BN6: Invoice | BQ6: 0 Days 2 Hr 36 Min | BR6: 500 | BS6: Approved - ;; Approved - ; | BT6: 11941 | BU6: 11941 | BV6: ; | BW6: ; | BX6: ; | BY6: BR | CA6: USD | CE6: 13697415 | CF6: 1 | CG6: 1 | CJ6: 0
A7: 44927 | B7: Shipment delay | C7: 40090 | D7: Transportation Problem - Atraso ETA | E7: TOYOTA | F7: 44932 | G7: Paraisopolis | H7: Inbound Premium | I7: 162.56 | J7: 120 | K7: =I7/$I$1 -> 0.00039789613 | L7: T1-Transportation | M7: Normal | N7: APTIV MANUFATURA E SERVICOS DE-104120 | O7: APTIV LAREDO (FW80)-734188 | P7: ongestionamento dos portos devido feriado de Thanksgiving nos EUA. | Q7: DHL Express SA | R7: PTA-00085945 | S7: 13533399; | T7: ; | U7: ; | V7: Aptiv | W7: Premium - Productive | X7: Moraes.Arnaldo@aptiv.com | Y7: 44930.334 | Z7: 44937.26 | AA7: SA | AB7: Closed Not Recovered | AC7: 0 | AE7: 16256 | AG7: 10012 | AH7: Q11 | AJ7: 16256 | AK7: Recoverable | AM7: 120 | AN7: USD | AO7: 301 VALLECILLO ROAD | AP7: LAREDO | AQ7: 734188 | AR7: US | AS7: NA | AT7: TX | AU7: 78045-7847 | AV7: AVENIDA AVELINO RIBEIRO, 900 | AW7: PARAISOPOLIS | AX7: 104120 | AY7: BR | AZ7: SA | BA7: MG | BB7: 37660-000 | BC7: SPS | BD7: Approved | BE7: Rebello, Andre | BF7: 44931.463 | BG7: 0 | BH7: DHL Express SA | BI7: 2469905561 | BK7: Transportation | BM7: Invoice | BN7: Invoice | BQ7: 0 Days 15 Hr 6 Min | BR7: 500 | BS7: Approved - ;; Approved - ; | BT7: 16256 | BU7: 16256 | BV7: ; | BW7: ; | BX7: ; | BY7: BR | CA7: USD | CE7: 15305104-13697408 | CF7: 1 | CG7: 1 | CJ7: 0
A8: 44927 | B8: Supplier delay | C8: 40459 | D8: Supplier Delay - MTA | E8: JOHN DEERE | F8: 44932 | G8: Paraisopolis | H8: Inbound Premium | I8: 549 | J8: 640.97 | K8: =I8/$I$1 -> 0.0013437806 | L8: B3-Behind Schedule-External Supplier | M8: Cost Recovery Pending | N8: Paraisopolis-10012 | O8: MTA S P A-107597 | P8: Erro comercial do lado da MTA (COST RECOVERY SIM) | Q8: DHL Express SA | R8: PTA-00086142 | S8: 13673199 - 13881229; | T8: ; | U8: ; | V8: Supplier | W8: Premium - Productive | X8: william.de.siqueira@aptiv.com | Y8: 44932.462 | Z8: 44942.22 | AA8: SA | AB8: Open | AC8: 0 | AE8: 549 | AF8: 44938 | AG8: 10012 | AH8: Q11 | AJ8: 549 | AK8: Recoverable | AM8: 64097 | AN8: USD | AO8: VIALE DELLINDUSTRIA 12 | AP8: CODOGNO | AQ8: 107597 | AR8: IT | AS8: EMEA | AT8: LO | AU8: 26845 | AV8: Av. Avelino Ribeiro, 900 | AW8: Paraisopolis | AX8: 10012 | AY8: BR | AZ8: SA | BA8: Mina | BB8: 37660-000 | BC8: SPS | BD8: Approved | BE8: Naus, Angelica | BF8: 44932.072 | BG8: 0 | BI8: 4553768041 | BK8: Supplier | BM8: Invoice | BN8: Invoice | BP8: MTA SPA-8019235 | BQ8: 0 Days 2 Hr 37 Min | BR8: 800 | BS8: Approved - ;; Approved - ;; Approved - ; | BT8: 549 | BU8: 549 | BV8: ; | BW8: ; | BX8: ; | BY8: BR | CA8: USD | CB8: HONGFA TECHNOLOGY CO, LTD ULT DUNS 545268450 | CF8: 1 | CG8: 1 | CJ8: 0
A9: 44927 | B9: Shipment delay | C9: 40504 | D9: Transportation Problem - Atraso ETA | E9: JOHN DEERE | F9: 44935 | G9: Paraisopolis | H9: Inbound Premium | I9: 347.18 | J9: 301.58 | K9: =I9/$I$1 -> 0.00084978826 | L9: T1-Transportation | M9: Normal | N9: APTIV MANUFATURA E SERVICOS DE-104120 | O9: APTIV CENTEC II (FW97)-726918 | P9: Congestionamento dos portos devido feriado de thanksgiving nos EUA | Q9: DHL Express SA | R9: PTA-00086275 | S9: 10763696; | T9: ; | U9: ; | V9: Aptiv | W9: Premium - Productive | X9: Moraes.Arnaldo@aptiv.com | Y9: 44932.174 | Z9: 44939.287 | AA9: SA | AB9: Closed Not Recovered | AC9: 0 | AE9: 34718 | AG9: 10012 | AH9: Q11 | AJ9: 34718 | AK9: Non-Recoverable | AM9: 30158 | AN9: USD | AO9: BLVD ISIDRO LOPEZ ZERTUCHE 4890 | AP9: SALTILLO | AQ9: 726918 | AR9: MX | AS9: NA | AT9: COA | AU9: 25230 | AV9: AVENIDA AVELINO RIBEIRO, 900 | AW9: PARAISOPOLIS | AX9: 104120 | AY9: BR | AZ9: SA | BA9: MG | BB9: 37660-000 | BC9: SPS | BD9: Approved | BE9: Rebello, Andre | BF9: 44932.495 | BG9: 0 | BH9: DHL Express SA | BI9: 1017181196 | BK9: Transportation | BM9: Invoice | BN9: Invoice | BQ9: 0 Days 7 Hr 42 Min | BR9: 500 | BS9: Approved - ;; Approved - ; | BT9: 34718 | BU9: 34718 | BV9: ; | BW9: ; | BX9: ; | BY9: BR | CA9: USD | CE9: 15544892-15544324-33386302 | CF9: 1 | CG9: 1 | CJ9: 0
A10: 44927 | B10: Stock discrepancy | C10: 40525 | D10: Stock Discrepancy | E10: GM | F10: 44932 | G10: Pinhal | H10: Inbound Premium | I10: 2500 | J10: 2500 | K10: =I10/$I$1 -> 0.0061192196 | L10: S1I-Inventory loss/adjustments | M10: Normal | N10: APTIV MANUFATURA E SERVICOS DE-104991 | O10: APTIV HONDURAS HN11-765569 | P10: We had some problems in the transportation of Aptiv Hondura's materials that results in iventory loss. | Q10: DSV UTI Air & Sea Agenciamento de Transportes | S10: 47315376; | T10: ; | U10: ; | V10: Aptiv | W10: Premium - Productive | X10: rodrigo.perez@aptiv.com | Y10: 44957.111 | Z10: 44957.11 | AA10: SA | AB10: Closed Not Recovered | AC10: 0 | AE10: 0 | AF10: 44935 | AG10: 10010 | AH10: Q18 | AK10: Non-Recoverable | AM10: 2500 | AO10: KM 23/24 CARRETERA A OCCIDENTE ZOLI | AP10: QUIMISTAN | AQ10: 765569 | AR10: HN | AS10: NA | AT10: SB | AU10: 22101 | AV10: RODOVIA SP 342 KM 196 | AW10: ESPIRITO SANTO DO PINHAL | AX10: 104991 | AY10: BR | AZ10: SA | BA10: SP | BB10: 13990-000 | BC10: SPS | BD10: Pending | BG10: 0 | BH10: DSV UTI Air & Sea Agenciamento de Transportes | BK10: Aptiv | BM10: Personal Estimate | BN10: Personal Estimate | BR10: 0 | BS10: Approved - ;; Approved - ;; Approved - ;; Approved - ok ;; Pending - | BT10: 2500 | BU10: 2500 | BV10: ; | BW10: ; | BX10: ; | BY10: BR | CA10: USD | CF10: 1 | CJ10: 0
A11: 44927 | B11: BOM error | C11: 40542 | D11: BOM Error | E11: OTHER | F11: 44932 | G11: Paraisopolis | H11: Inbound Premium | I11: 148.89 | J11: 134.16 | K11: =I11/$I$1 -> 0.00036443624 | L11: E1B-BOM Errors | M11: Normal | N11: APTIV MANUFATURA E SERVICOS DE-106499 | O11: TECNOPRINT AUTOMACAO INDUSTRIAL LTDA-8125875 | P11: BOM Error | Q11: TRANSPORTADORA PITUTA | R11: PTA-00086274 | S11: 15368456; | T11: ; | U11: ; | V11: Aptiv | W11: Premium - Productive | X11: adriane.barbosa.silva@aptiv.com | Y11: 44932.249 | Z11: 44942.299 | AA11: SA | AB11: Closed Not Recovered | AC11: 0 | AE11: 14889 | AG11: 10012 | AH11: Q11 | AJ11: 77684 | AK11: Non-Recoverable | AM11: 700 | AN11: BRL | AO11: RUA SALVADOR DE SA 34/44 | AP11: SANTO ANDRE | AQ11: 8125875 | AR11: BR | AS11: SA | AT11: _ | AU11: 09210-490 | AV11: 900 AVENUE AVELINO RIBEIRO | AW11: PARAISOPOLIS | AX11: 106499 | AY11: BR | AZ11: SA | BA11: MG | BB11: 37660-000 | BC11: SPS | BD11: Approved | BE11: Rebello, Andre | BF11: 44932.495 | BG11: 0 | BI11: GRU-000896251 | BK11: Aptiv | BM11: Invoice | BN11: Invoice | BQ11: 0 Days 5 Hr 54 Min | BR11: 500 | BS11: Approved - ;; Approved - ; | BT11: 14889 | BU11: 14889 | BV11: ; | BW11: ; | BX11: ; | BY11: BR | CA11: BRL | CF11: 19165533 | CG11: 19165533 | CJ11: 0
A12: 44927 | B12: Shipment delay | C12: 40784 | D12: Transportation Problem - Atraso ETA | E12: GM | F12: 44936 | G12: Pinhal | H12: Inbound Premium | I12: 819.62 | J12: 150 | K12: =I12/$I$1 -> 0.0020061739 | L12: T1-Transportation | M12: Normal | N12: APTIV MANUFATURA E SERVICOS DE-104991 | O12: J.S.T. CORPORATION-1003317 | P12: Aéreo necessário devido ao atraso de ETA, Invoice 739741. | Q12: DHL Express SA | R12: PTA-00086456 | S12: 13646861; | T12: ; | U12: ; | V12: Aptiv | W12: Premium - Productive | X12: rodrigo.perez@aptiv.com | Y12: 44935.522 | Z12: 44957.514 | AA12: SA | AB12: Closed Not Recovered | AC12: 0 | AE12: 81962 | AF12: 44936 | AG12: 10010 | AH12: Q18 | AJ12: 81962 | AK12: Non-Recoverable | AM12: 150 | AN12: USD | AO12: 1957 S LAKESIDE DR | AP12: WAUKEGAN | AQ12: 1003317 | AR12: US | AS12: NA | AT12: IL | AU12: 60085-8331 | AV12: RODOVIA SP 342 KM 196 | AW12: ESPIRITO SANTO DO PINHAL | AX12: 104991 | AY12: BR | AZ12: SA | BA12: SP | BB12: 13990-000 | BC12: SPS | BD12: Approved | BE12: Edilson, Geraldo | BF12: 44935.28 | BG12: 0 | BH12: DHL Express SA | BI12: 8945077665 | BK12: Transportation | BM12: Personal Estimate | BN12: Personal Estimate | BQ12: 0 Days 6 Hr 11 Min | BR12: 500 | BS12: Approved - ;; Approved - ; | BT12: 81962 | BU12: 81962 | BV12: ; | BW12: ; | BX12: ; | BY12: BR | CA12: USD | CF12: 1 | CG12: 1 | CJ12: 0 | CO12: 690666524
A13: 44927 | B13: Stock discrepancy | C13: 40790 | D13: Stock Discrepancy | E13: JOHN DEERE | F13: 44935 | G13: Paraisopolis | H13: Inbound Premium | I13: 517.47 | J13: 517.47 | K13: =I13/$I$1 -> 0.001266605 | L13: S1I-Inventory loss/adjustments | M13: Normal | N13: APTIV MANUFATURA E SERVICOS DE-106499 | O13: Acome Irati-Dummy | P13: Stock Discrepancy | Q13: TRANSPORTADORA PITUTA | R13: PTA-00087990 | S13: 15368456; | T13: ; | U13: ; | V13: Aptiv | W13: Premium - Productive | X13: adriane.barbosa.silva@aptiv.com | Y13: 44942.065 | Z13: 44946.235 | AA13: SA | AB13: Closed Not Recovered | AC13: 0 | AE13: 0 | AG13: 10012 | AH13: Q11 | AJ13: 492499 | AK13: Non-Recoverable | AM13: 2700 | AN13: BRL | AO13: Irati | AP13: Irati | AQ13: Dummy | AR13: BR | AS13: SA | AT13: Parana | AU13: 0000 | AV13: 900 AVENUE AVELINO RIBEIRO | AW13: PARAISOPOLIS | AX13: 106499 | AY13: BR | AZ13: SA | BA13: MG | BB13: 37660-000 | BC13: SPS | BD13: Approved | BE13: Naus, Angelica | BF13: 44942.245 | BG13: 0 | BH13: TRANSPORTADORA PITUTA | BI13: COL-000009739 | BK13: Aptiv | BM13: Invoice | BN13: Invoice | BQ13: 0 Days 4 Hr 19 Min | BR13: 800 | BS13: Approved - ;; Approved - ;; Approved - ;; Approved - ; | BT13: 51747 | BU13: 51747 | BV13: ; | BW13: ; | BX13: ; | BY13: BR | CA13: BRL | CF13: 19165533 | CG13: 19165533 | CJ13: 0
A14: 44927 | B14: Project | C14: 40861 | D14: Projeto | E14: GM | F14: 44935 | G14: Paraisopolis | H14: Inbound Premium | I14: 77 | J14: 77 | K14: =I14/$I$1 -> 0.00018847196 | L14: E1P-Prototypes/Samples | M14: Cost Recovery | N14: Paraisopolis-10012 | O14: SERENDIPITY ELECTRONICS-749804 | P14: Parts for sales from protoypes pieces. Freigth included in the piece price. | Q14: DHL Express SA | R14: PTA-00086459 | S14: 13894085; | T14: ; | U14: ; | V14: Aptiv | W14: Premium - Productive | X14: rayzza.peres@aptiv.com | Y14: 44935.278 | Z14: 44935.277 | AA14: SA | AB14: Closed Recovered | AC14: 0 | AE14: 77 | AG14: 10012 | AH14: Q11 | AJ14: 77 | AK14: Recoverable | AM14: 77 | AN14: USD | AO14: 152 E MAIN ST | AP14: HUNTINGTON | AQ14: 749804 | AR14: US | AS14: NA | AT14: NY | AU14: 11743-2958 | AV14: Av. Avelino Ribeiro, 900 | AW14: Paraisopolis | AX14: 10012 | AY14: BR | AZ14: SA | BA14: Mina | BB14: 37660-000 | BC14: SPS | BD14: Approved | BE14: Edilson, Geraldo | BF14: 44935.286 | BG14: 0 | BK14: Aptiv | BM14: Invoice | BN14: Invoice | BQ14: 0 Days 0 Hr 10 Min | BR14: 500 | BS14: Approved - ;; Approved - ; | BT14: 77 | BU14: 77 | BV14: ; | BW14: ; | BX14: ; | BY14: BR | BZ14: PL8 | CA14: USD | CE14: DPP67515 | CF14: 1 | CG14: 1 | CJ14: 0
A15: 44927 | B15: Supplier delay | C15: 40905 | D15: Supplier Delay - Serendipity | E15: JOHN DEERE | F15: 44936 | G15: Paraisopolis | H15: Inbound Premium | I15: 40.13 | J15: 40.13 | K15: =I15/$I$1 -> 9.8225713e-05 | L15: B3-Behind Schedule-External Supplier | M15: Cost Recovery Pending | N15: Paraisopolis-10012 | O15: SERENDIPITY ELECTRONICS-749804 | P15: Atraso do fornecedor - Cost recovery sim | Q15: DHL Express SA | R15: PTA-00086461 | S15: 13934466; | T15: ; | U15: ; | V15: Supplier | W15: Premium - Productive | X15: william.de.siqueira@aptiv.com | Y15: 44935.266 | Z15: 44942.221 | AA15: SA | AB15: Open | AC15: 0 | AE15: 4013 | AF15: 44942 | AG15: 10012 | AH15: Q11 | AJ15: 4013 | AK15: Recoverable | AM15: 4013 | AN15: USD | AO15: 152 E MAIN ST | AP15: HUNTINGTON | AQ15: 749804 | AR15: US | AS15: NA | AT15: NY | AU15: 11743-2958 | AV15: Av. Avelino Ribeiro, 900 | AW15: Paraisopolis | AX15: 10012 | AY15: BR | AZ15: SA | BA15: Mina | BB15: 37660-000 | BC15: SPS | BD15: Approved | BE15: Edilson, Geraldo | BF15: 44935.286 | BG15: 0 | BI15: 2469837436 | BK15: Supplier | BM15: Invoice | BN15: Invoice | BP15: SERENDIPITY ELECTRONICS, INC.-8115180 | BQ15: 0 Days 0 Hr 28 Min | BR15: 500 | BS15: Approved - ;; Approved - ; | BT15: 4013 | BU15: 4013 | BV15: ; | BW15: ; | BX15: ; | BY15: BR | CA15: USD | CB15: MTA SPA ULT DUNS 428456263 | CF15: 1 | CG15: 1 | CJ15: 0
A16: 44927 | B16: Project | C16: 41113 | D16: Engineering Changes | E16: DAIMLER | F16: 44936 | G16: Paraisopolis | H16: Inbound Premium | I16: 567.67 | J16: 567.67 | K16: =I16/$I$1 -> 0.001389479 | L16: E1D-Aptiv Design/Engineering changes | M16: Normal | N16: APTIV MANUFATURA E SERVICOS DE-104120 | O16: FRAENKISCHE INDUSTRIAL PIPES GMBH &-1049617 | P16: Critical material to meet engineering modification, as per customer request due to quality problem. | Q16: DHL Express SA | R16: PTA-00086682 | S16: M3794521; | T16: 2000 metros; | U16: 89.80; | V16: Aptiv | W16: Premium - Productive | X16: marcia.p.torres@aptiv.com | Y16: 44936.452 | Z16: 44960.227 | AA16: SA | AB16: Closed Not Recovered | AC16: 0 | AE16: 0 | AF16: 44936 | AG16: 10012 | AH16: Q11 | AJ16: 833 | AK16: Non-Recoverable | AM16: 83309 | AO16: HELLINGER STR. 1 | AP16: KOENIGSBERG I.BAY. | AQ16: 1049617 | AR16: DE | AS16: EMEA | AT16: BY | AU16: 97486 | AV16: AVENIDA AVELINO RIBEIRO, 900 | AW16: PARAISOPOLIS | AX16: 104120 | AY16: BR | AZ16: SA | BA16: MG | BB16: 37660-000 | BC16: SPS | BD16: Approved | BE16: Naus, Angelica | BF16: 44936.232 | BG16: 0 | BI16: 6905119104 | BK16: Aptiv | BM16: Invoice | BN16: Invoice | BQ16: 0 Days 6 Hr 42 Min | BR16: 800 | BS16: Approved - ;; Approved - ;; Approved - ok ; | BT16: 56767 | BU16: 56767 | BV16: ; | BW16: 1200x800x950; | BX16: ; | BY16: BR | BZ16: MOTOR | CA16: AUD | CD16: Kg | CE16: Critical material to meet engineering modification, as per customer request due to quality problem. MBB | CF16: 6814 | CJ16: 0 | CO16: 329846877
A17: 44927 | B17: Stock discrepancy | C17: 41136 | D17: Stock Discrepancy | E17: FIAT | F17: 44937 | G17: Paraisopolis | H17: Inbound Premium | I17: 463.27 | J17: 670 | K17: =I17/$I$1 -> 0.0011339403 | L17: S1I-Inventory loss/adjustments | M17: Normal | N17: Paraisopolis-10012 | O17: MTA SPA-1014076 | P17: Reajuste de estoque | Q17: DHL Express SA | R17: PTA-00086681 | S17: 15369145 - 13864152 - 10820257; | T17: ; | U17: ; | V17: Aptiv | W17: Premium - Productive | X17: william.de.siqueira@aptiv.com | Y17: 44936.082 | Z17: 44942.229 | AA17: SA | AB17: Closed Not Recovered | AC17: 0 | AE17: 46327 | AF17: 44942 | AG17: 10012 | AH17: Q11 | AJ17: 46327 | AK17: Non-Recoverable | AM17: 670 | AN17: USD | AO17: VIALE DELLINDUSTRIA 12 | AP17: CODOGNO | AQ17: 1014076 | AR17: IT | AS17: EMEA | AT17: LO | AU17: 26845 | AV17: Av. Avelino Ribeiro, 900 | AW17: Paraisopolis | AX17: 10012 | AY17: BR | AZ17: SA | BA17: Mina | BB17: 37660-000 | BC17: SPS | BD17: Approved | BE17: Naus, Angelica | BF17: 44936.231 | BG17: 0 | BI17: 5372890401 | BK17: Aptiv | BM17: Invoice | BN17: Invoice | BQ17: 0 Days 3 Hr 35 Min | BR17: 800 | BS17: Approved - ;; Approved - ;; Approved - ok ; | BT17: 46327 | BU17: 46327 | BV17: ; | BW17: ; | BX17: ; | BY17: BR | CA17: USD | CF17: 1 | CG17: 1 | CJ17: 0 | CO17: 428456263
A18: 44927 | B18: Internal problem - Manufacturing/ Ordering/ Purchasing/ IT | C18: 41146 | D18: Ordering Erro Acumulado | E18: VW | F18: 44938 | G18: Pinhal | H18: Inbound Premium | I18: 512.17 | J18: 823 | K18: =I18/$I$1 -> 0.0012536323 | L18: PC-Plant PC Resp | M18: Normal | N18: APTIV MANUFATURA E SERVICOS DE-104991 | O18: APTIV SERVICES DEUTSCHLAND GMBH-103215 | P18: Air Freight required due to communication problems with the supplier, which caused errors in the accumulated. | Q18: DHL Express SA | R18: PTA-00086957 | S18: 15365811; | T18: ; | U18: ; | V18: Aptiv | W18: Premium - Productive | X18: bruno.g.silva2@aptiv.com | Y18: 44936.119 | Z18: 44958.087 | AA18: SA | AB18: Closed Not Recovered | AC18: 0 | AE18: 51217 | AF18: 44936 | AG18: 10010 | AH18: Q18 | AJ18: 51217 | AK18: Non-Recoverable | AM18: 823 | AN18: USD | AO18: BEUTHENER STRASSE 41 | AP18: NUREMBERG | AQ18: 103215 | AR18: DE | AS18: EMEA | AT18: BY | AU18: 90329 | AV18: RODOVIA SP 342 KM 196 | AW18: ESPIRITO SANTO DO PINHAL | AX18: 104991 | AY18: BR | AZ18: SA | BA18: SP | BB18: 13990-000 | BC18: SPS | BD18: Approved | BE18: Lopez, Tanya S | BF18: 44937.222 | BG18: 0 | BH18: DHL Express SA | BI18: 1534280355 | BK18: Aptiv | BM18: Personal Estimate | BN18: Invoice | BQ18: 1 Days 2 Hr 29 Min | BR18: 1000 | BS18: Approved - ;; Approved - ;; Approved - ok ;; Approved - ; | BT18: 51217 | BU18: 51217 | BV18: ; | BW18: ; | BX18: ; | BY18: BR | BZ18: 23X | CA18: USD | CF18: 1 | CG18: 1 | CJ18: 0
A19: 44927 | B19: Project | C19: 41163 | D19: Projeto | E19: FIAT | F19: 44936 | G19: Paraisopolis | H19: Inbound Premium | I19: 38 | J19: 38 | K19: =I19/$I$1 -> 9.3012138e-05 | L19: E1P-Prototypes/Samples | M19: Normal | N19: Paraisopolis-10012 | O19: SERENDIPITY ELECTRONICS-749804 | P19: Parts for sales from protoypes pieces. Freigth included in the piece price. | Q19: DHL Express SA | R19: PTA-00086683 | S19: PE55625513532153; | T19: ; | U19: ; | V19: Aptiv | W19: Premium - Productive | X19: rayzza.peres@aptiv.com | Y19: 44936.143 | Z19: 44936.143 | AA19: SA | AB19: Closed Not Recovered | AC19: 0 | AE19: 38 | AG19: 10012 | AH19: Q11 | AJ19: 38 | AK19: Recoverable | AM19: 38 | AN19: USD | AO19: 152 E MAIN ST | AP19: HUNTINGTON | AQ19: 749804 | AR19: US | AS19: NA | AT19: NY | AU19: 11743-2958 | AV19: Av. Avelino Ribeiro, 900 | AW19: Paraisopolis | AX19: 10012 | AY19: BR | AZ19: SA | BA19: Mina | BB19: 37660-000 | BC19: SPS | BD19: Approved | BE19: Edilson, Geraldo | BF19: 44936.237 | BG19: 0 | BK19: Aptiv | BM19: Invoice | BN19: Invoice | BQ19: 0 Days 2 Hr 14 Min | BR19: 500 | BS19: Approved - ;; Approved - ; | BT19: 38 | BU19: 38 | BV19: ; | BW19: ; | BX19: ; | BY19: BR | BZ19: GSE ORVR PL8 | CA19: USD | CE19: DPP67537 | CF19: 1 | CG19: 1 | CJ19: 0
A20: 44927 | B20: P&A | C20: 41253 | D20: P&A | E20: JOHN DEERE | F20: 44936 | G20: Paraisopolis | H20: Inbound Premium | I20: 691.42 | J20: 400 | K20: =I20/$I$1 -> 0.0016923803 | L20: OOOT-Other/Sales | M20: Normal | N20: APTIV MANUFATURA E SERVICOS DE-104120 | O20: LEONI CABLE-115491 | P20: DEMAND FOR P&A SERVICE | Q20: DHL Express SA | R20: PTA-00086889 | S20: M7600101; | T20: ; | U20: ; | V20: Aptiv | W20: Premium - Productive | X20: jorge.luis.almeida@aptiv.com | Y20: 44936.296 | Z20: 44961.514 | AA20: SA | AB20: Closed Not Recovered | AC20: 0 | AE20: 69142 | AG20: 10012 | AH20: Q11 | AJ20: 69142 | AK20: Non-Recoverable | AM20: 400 | AN20: USD | AO20: 321 EAST 2ND STREET SUITE B | AP20: ROCHESTER | AQ20: 115491 | AR20: US | AS20: NA | AT20: MI | AU20: 48307 | AV20: AVENIDA AVELINO RIBEIRO, 900 | AW20: PARAISOPOLIS | AX20: 104120 | AY20: BR | AZ20: SA | BA20: MG | BB20: 37660-000 | BC20: SPS | BD20: Approved | BE20: Edilson, Geraldo | BF20: 44937.459 | BG20: 0 | BH20: DHL Express SA | BI20: 4892732460 | BK20: Aptiv | BM20: Invoice | BN20: Invoice | BQ20: 0 Days 15 Hr 53 Min | BR20: 500 | BS20: Approved - ;; Approved - ; | BT20: 69142 | BU20: 69142 | BV20: ; | BW20: ; | BX20: ; | BY20: BR | CA20: USD | CE20: demand for attend P&A - JD client | CF20: 1 | CG20: 1 | CJ20: 0
A21: 44927 | B21: Internal problem - Manufacturing/ Ordering/ Purchasing/ IT | C21: 41461 | D21: Ordering Erro Acumulado | E21: VW | F21: 44939 | G21: Pinhal | H21: Inbound Premium | I21: 250 | J21: 250 | K21: =I21/$I$1 -> 0.00061192196 | L21: PC-Plant PC Resp | M21: Normal | N21: APTIV MANUFATURA E SERVICOS DE-104991 | O21: APTIV SERVICES DEUTSCHLAND GMBH-103215 | P21: Air Freight required due to communication problems with the supplier, which caused errors in the accumulated. | Q21: DHL Express SA | R21: PTA-00087241 | S21: 33405737; | T21: ; | U21: ; | V21: Aptiv | W21: Premium - Productive | X21: bruno.g.silva2@aptiv.com | Y21: 44937.407 | Z21: 44960.121 | AA21: SA | AB21: Closed Not Recovered | AC21: 0 | AE21: 0 | AF21: 44937 | AG21: 10010 | AH21: Q18 | AJ21: 17265 | AK21: Non-Recoverable | AM21: 250 | AN21: USD | AO21: BEUTHENER STRASSE 41 | AP21: NUREMBERG | AQ21: 103215 | AR21: DE | AS21: EMEA | AT21: BY | AU21: 90329 | AV21: RODOVIA SP 342 KM 196 | AW21: ESPIRITO SANTO DO PINHAL | AX21: 104991 | AY21: BR | AZ21: SA | BA21: SP | BB21: 13990-000 | BC21: SPS | BD21: Approved | BE21: Edilson, Geraldo | BF21: 44938.108 | BG21: 0 | BH21: DHL Express SA | BI21: 4724361110 | BK21: Aptiv | BM21: Personal Estimate | BN21: Invoice | BQ21: 1 Days 4 Hr 49 Min | BR21: 500 | BS21: Approved - ;; Approved - ; | BT21: 250 | BU21: 250 | BV21: ; | BW21: ; | BX21: ; | BY21: BR | BZ21: 23X | CA21: USD | CF21: 1 | CG21: 1 | CJ21: 0
A22: 44927 | B22: Shipment delay | C22: 41481 | D22: Transportation Problem - Atraso ETA | E22: GM | F22: 44938 | G22: Pinhal | H22: Inbound Premium | I22: 543.83 | J22: 150 | K22: =I22/$I$1 -> 0.0013311261 | L22: T1-Transportation | M22: Normal | N22: APTIV MANUFATURA E SERVICOS DE-104991 | O22: KOSTAL KONTAKT SYSTEME, INC-701557 | P22: Aéreo necessário devido ao atraso de ETA da Invoice 502075. | Q22: DHL Express SA | R22: PTA-00087247 | S22: 13869004; | T22: ; | U22: ; | V22: Aptiv | W22: Premium - Productive | X22: rodrigo.perez@aptiv.com | Y22: 44937.064 | Z22: 44957.516 | AA22: SA | AB22: Closed Not Recovered | AC22: 0 | AE22: 54383 | AF22: 44937 | AG22: 10010 | AH22: Q18 | AJ22: 54383 | AK22: Non-Recoverable | AM22: 150 | AN22: USD | AO22: 1350 W HAMLIN RD | AP22: ROCHESTER HILLS | AQ22: 701557 | AR22: US | AS22: NA | AT22: MI | AU22: 48309 | AV22: RODOVIA SP 342 KM 196 | AW22: ESPIRITO SANTO DO PINHAL | AX22: 104991 | AY22: BR | AZ22: SA | BA22: SP | BB22: 13990-000 | BC22: SPS | BD22: Approved | BE22: Edilson, Geraldo | BF22: 44938.13 | BG22: 0 | BH22: DHL Express SA | BI22: 1203350293 | BK22: Transportation | BM22: Personal Estimate | BN22: Personal Estimate | BQ22: 1 Days 1 Hr 35 Min | BR22: 500 | BS22: Approved - ;; Approved - ; | BT22: 54383 | BU22: 54383 | BV22: ; | BW22: ; | BX22: ; | BY22: BR | CA22: USD | CE22: 13735326 | CF22: 1 | CG22: 1 | CJ22: 0
A23: 44927 | B23: Stock discrepancy | C23: 41773 | D23: Stock Discrepancy | E23: GM | F23: 44938 | G23: Paraisopolis | H23: Inbound Premium | I23: 140.96 | J23: 140.96 | K23: =I23/$I$1 -> 0.00034502608 | L23: S1I-Inventory loss/adjustments | M23: Normal | N23: Paraisopolis-10012 | O23: A123 SYSTEMS (CHINA) MATERIALS CO-1041023 | P23: Tivemos uma Rolagen de 7 dias - consumo de 1000 peças sem estar planejado - divergencia de estoque de 1185 peças | Q23: DHL Express SA | R23: PTA-00087230 | S23: 25329659; | T23: ; | U23: ; | V23: Aptiv | W23: Premium - Productive | X23: william.de.siqueira@aptiv.com | Y23: 44938.509 | Z23: 44949.324 | AA23: SA | AB23: Closed Not Recovered | AC23: 0 | AE23: 14096 | AF23: 44945 | AG23: 10012 | AH23: Q11 | AJ23: 14096 | AK23: Non-Recoverable | AM23: 14096 | AN23: USD | AO23: A5 BUILDING, XINZHU RD. | AP23: CHANGZHOU | AQ23: 1041023 | AR23: CN | AS23: AP | AT23: 100 | AU23: 213031 | AV23: Av. Avelino Ribeiro, 900 | AW23: Paraisopolis | AX23: 10012 | AY23: BR | AZ23: SA | BA23: Mina | BB23: 37660-000 | BC23: SPS | BD23: Approved | BE23: Edilson, Geraldo | BF23: 44938.538 | BG23: 0 | BI23: 5827058440 | BK23: Aptiv | BM23: Invoice | BN23: Invoice | BQ23: 0 Days 0 Hr 41 Min | BR23: 500 | BS23: Approved - ;; Approved - ; | BT23: 14096 | BU23: 14096 | BV23: ; | BW23: ; | BX23: ; | BY23: BR | CA23: USD | CF23: 1 | CG23: 1 | CJ23: 0 | CO23: 544702061
A24: 44927 | B24: Stock discrepancy | C24: 41795 | D24: Stock Discrepancy | E24: GM | F24: 44939 | G24: Pinhal | H24: Inbound Premium | I24: 2191.89 | J24: 2000 | K24: =I24/$I$1 -> 0.0053650625 | L24: S1I-Inventory loss/adjustments | M24: Normal | N24: APTIV MANUFATURA E SERVICOS DE-104991 | O24: APTIV HONDURAS HN11-765569 | P24: We had some problems in the transportation of Aptiv Hondura's materials that results in iventory loss. | Q24: DSV UTI Air & Sea Agenciamento de Transportes | R24: PTA-00087693 | S24: 35578211; | T24: ; | U24: ; | V24: Aptiv | W24: Premium - Productive | X24: rodrigo.perez@aptiv.com | Y24: 44938.092 | Z24: 44957.519 | AA24: SA | AB24: Closed Not Recovered | AC24: 0 | AE24: 219189 | AF24: 44938 | AG24: 10010 | AH24: Q18 | AJ24: 219189 | AK24: Non-Recoverable | AM24: 2000 | AN24: USD | AO24: KM 23/24 CARRETERA A OCCIDENTE ZOLI | AP24: QUIMISTAN | AQ24: 765569 | AR24: HN | AS24: NA | AT24: SB | AU24: 22101 | AV24: RODOVIA SP 342 KM 196 | AW24: ESPIRITO SANTO DO PINHAL | AX24: 104991 | AY24: BR | AZ24: SA | BA24: SP | BB24: 13990-000 | BC24: SPS | BD24: Approved | BE24: Garcia Puente, Jorge | BF24: 44940.076 | BG24: 0 | BH24: DSV UTI Air & Sea Agenciamento de Transportes | BI24: SAP501006953 | BK24: Aptiv | BM24: Personal Estimate | BN24: Personal Estimate | BQ24: 1 Days 11 Hr 37 Min | BR24: 5000 | BS24: Approved - ;; Approved - ;; Approved - ;; Approved - ;; Approved - ; | BT24: 219189 | BU24: 219189 | BV24: ; | BW24: ; | BX24: ; | BY24: BR | CA24: USD | CF24: 1 | CG24: 1 | CJ24: 0
A25: 44927 | B25: Shipment delay | C25: 41799 | D25: Transportation Problem - Atraso ETA | E25: GM | F25: 44939 | G25: Pinhal | H25: Inbound Premium | I25: 464.65 | J25: 250 | K25: =I25/$I$1 -> 0.0011373182 | L25: T1-Transportation | M25: Normal | N25: APTIV MANUFATURA E SERVICOS DE-104991 | O25: APTIV SERVICES US LLC-111089 | P25: Aéreo necessário devido ao atraso de ETA do navio MONTE CERVANTES. Invoice Afetada : 11052167. | Q25: DHL Express SA | R25: PTA-00087245 | S25: 15482324; | T25: ; | U25: ; | V25: Aptiv | W25: Premium - Productive | X25: rodrigo.perez@aptiv.com | Y25: 44938.098 | Z25: 44957.52 | AA25: SA | AB25: Closed Not Recovered | AC25: 0 | AE25: 46465 | AF25: 44938 | AG25: 10010 | AH25: Q18 | AJ25: 46465 | AK25: Non-Recoverable | AM25: 250 | AN25: USD | AO25: 5725 DELPHI DR | AP25: TROY | AQ25: 111089 | AR25: US | AS25: NA | AT25: MI | AU25: 48098-2815 | AV25: RODOVIA SP 342 KM 196 | AW25: ESPIRITO SANTO DO PINHAL | AX25: 104991 | AY25: BR | AZ25: SA | BA25: SP | BB25: 13990-000 | BC25: SPS | BD25: Approved | BE25: Edilson, Geraldo | BF25: 44938.126 | BG25: 0 | BH25: DHL Express SA | BI25: 5403900563 | BK25: Transportation | BM25: Personal Estimate | BN25: Personal Estimate | BQ25: 0 Days 0 Hr 40 Min | BR25: 500 | BS25: Approved - ;; Approved - ; | BT25: 46465 | BU25: 46465 | BV25: ; | BW25: ; | BX25: ; | BY25: BR | CA25: USD | CF25: 1 | CG25: 1 | CJ25: 0
A26: 44927 | B26: Shipment delay | C26: 41899 | D26: Transportation Problem - Atraso ETA | E26: TOYOTA | F26: 44939 | G26: Paraisopolis | H26: Inbound Premium | I26: 310.16 | J26: 255 | K26: =I26/$I$1 -> 0.00075917486 | L26: PORT-PORT DELAYS | M26: Normal | N26: APTIV MANUFATURA E SERVICOS DE-104120 | O26: D.A. INC.-1048429 | P26: atraso de processo devido à torca de booking entre o navio monte azul para o monte olivia | Q26: DHL Express SA | R26: PTA-00087324 | S26: 13653037; | T26: ; | U26: 6000.00; | V26: Aptiv | W26: Premium - Productive | X26: jorge.luis.almeida@aptiv.com | Y26: 44938.288 | Z26: 44961.515 | AA26: SA | AB26: Closed Not Recovered | AC26: 0 | AE26: 31016 | AG26: 10012 | AH26: Q11 | AJ26: 31016 | AK26: Non-Recoverable | AM26: 255 | AN26: USD | AO26: 100 LINDBERGH DR | AP26: SANTA TERESA | AQ26: 1048429 | AR26: US | AS26: NA | AT26: NM | AU26: 88008-9706 | AV26: AVENIDA AVELINO RIBEIRO, 900 | AW26: PARAISOPOLIS | AX26: 104120 | AY26: BR | AZ26: SA | BA26: MG | BB26: 37660-000 | BC26: SPS | BD26: Approved | BE26: Edilson, Geraldo | BF26: 44938.302 | BG26: 0 | BH26: DHL Express SA | BI26: 7740203236 | BK26: Significant_event | BM26: Invoice | BN26: Invoice | BQ26: 0 Days 0 Hr 19 Min | BR26: 500 | BS26: Approved - ;; Approved - ; | BT26: 31016 | BU26: 31016 | BV26: ; | BW26: ; | BX26: ; | BY26: BR | CA26: USD | CE26: atraso de processo devido à torca de booking entre o navio monte azul para o monte olivia | CF26: 1 | CG26: 1 | CJ26: 0 | CO26: 690984533
A27: 44927 | B27: P&A | C27: 42182 | D27: P&A | E27: VW | F27: 44939 | G27: Paraisopolis | H27: Inbound Premium | I27: 28.48 | J27: 28.48 | K27: =I27/$I$1 -> 6.9710149e-05 | L27: OOOT-Other/Sales | M27: Normal | N27: APTIV MANUFATURA E SERVICOS DE-104120 | O27: SERENDIPITY ELECTRONICS-110404 | P27: Material to meet MAN customer's P&A program. | Q27: DHL Express SA | R27: PTA-00087890 | S27: 13741166; | T27: 100; | U27: 0.45; | V27: Aptiv | W27: Premium - Productive | X27: marcia.p.torres@aptiv.com | Y27: 44939.131 | Z27: 44960.242 | AA27: SA | AB27: Closed Not Recovered | AC27: 0 | AE27: 2848 | AF27: 44939 | AG27: 10012 | AH27: Q11 | AJ27: 2848 | AK27: Non-Recoverable | AM27: 2848 | AN27: USD | AO27: 152 E MAIN ST | AP27: HUNTINGTON | AQ27: 110404 | AR27: US | AS27: NA | AT27: NY | AU27: 11743-2958 | AV27: AVENIDA AVELINO RIBEIRO, 900 | AW27: PARAISOPOLIS | AX27: 104120 | AY27: BR | AZ27: SA | BA27: MG | BB27: 37660-000 | BC27: SPS | BD27: Approved | BE27: Edilson, Geraldo | BF27: 44942.46 | BG27: 0 | BH27: DHL Express SA | BI27: 2903559993 | BK27: Aptiv | BM27: Invoice | BN27: Invoice | BQ27: 2 Days 19 Hr 53 Min | BR27: 500 | BS27: Approved - ;; Approved - ; | BT27: 2848 | BU27: 2848 | BV27: 1; | BW27: 12x9x4; | BX27: ; | BY27: BR | BZ27: P&A | CA27: USD | CD27: Kg | CE27: Material to meet MAN customer's P&A program. | CF27: 1 | CG27: 1 | CJ27: 0
A28: 44927 | B28: Project | C28: 42654 | D28: Projeto | E28: JOHN DEERE | F28: 44943 | G28: Paraisopolis | H28: Inbound Premium | I28: 180 | J28: 180 | K28: =I28/$I$1 -> 0.00044058381 | L28: E1P-Prototypes/Samples | M28: Cost Recovery Pending | N28: Paraisopolis-10012 | O28: CHIEF ENTERPRISES INC-767169 | P28: Parts for project development. Freight will be absorbed at the SC 126-22 quotation. | Q28: DHL Express SA | R28: PTA-00087995 | S28: 35209963; | T28: ; | U28: ; | V28: Aptiv | W28: Premium - Productive | X28: william.de.siqueira@aptiv.com | Y28: 44942.241 | Z28: 44942.241 | AA28: SA | AB28: Open | AC28: 0 | AE28: 0 | AF28: 44949 | AG28: 10012 | AH28: Q11 | AK28: Recoverable | AM28: 180 | AO28: 545 WEST LAKE STREET | AP28: ELMHURST | AQ28: 767169 | AR28: US | AS28: NA | AT28: IL | AU28: 60126 | AV28: Av. Avelino Ribeiro, 900 | AW28: Paraisopolis | AX28: 10012 | AY28: BR | AZ28: SA | BA28: Mina | BB28: 37660-000 | BC28: SPS | BD28: Approved | BE28: Carvalho, Eliane R | BF28: 44942.254 | BG28: 0 | BK28: Aptiv | BM28: Invoice | BQ28: 0 Days 0 Hr 18 Min | BR28: 250 | BS28: Approved - ;; Approved - ; | BT28: 180 | BU28: 180 | BV28: ; | BW28: ; | BX28: ; | BY28: BR | CA28: USD | CF28: 1 | CJ28: 0
A29: 44927 | B29: Project | C29: 42655 | D29: Projeto | E29: JOHN DEERE | F29: 44943 | G29: Paraisopolis | H29: Inbound Premium | I29: 69.31 | J29: 60 | K29: =I29/$I$1 -> 0.00016964924 | L29: E1P-Prototypes/Samples | M29: Cost Recovery Pending | N29: Paraisopolis-10012 | O29: APPARATEBAU KIRCHHEIM-TECK GMBH-7043806 | P29: Parts for project development. Freight will be absorbed at the SC 126-22 quotation. | Q29: DHL Express SA | R29: PTA-00088233 | S29: 15339884; | T29: ; | U29: ; | V29: Aptiv | W29: Premium - Productive | X29: william.de.siqueira@aptiv.com | Y29: 44942.243 | Z29: 44953.118 | AA29: SA | AB29: Open | AC29: 0 | AE29: 6931 | AF29: 44949 | AG29: 10012 | AH29: Q11 | AJ29: 6931 | AK29: Recoverable | AM29: 60 | AN29: USD | AO29: ALLEENSTR. 36 | AP29: KIRCHHEIM UNTER TECK | AQ29: 7043806 | AR29: DE | AS29: EMEA | AT29: BW | AU29: 73230 | AV29: Av. Avelino Ribeiro, 900 | AW29: Paraisopolis | AX29: 10012 | AY29: BR | AZ29: SA | BA29: Mina | BB29: 37660-000 | BC29: SPS | BD29: Approved | BE29: Carvalho, Eliane R | BF29: 44943.538 | BG29: 0 | BI29: 6376562323 | BK29: Aptiv | BM29: Invoice | BN29: Invoice | BQ29: 0 Days 19 Hr 5 Min | BR29: 250 | BS29: Approved - ;; Approved - ; | BT29: 6931 | BU29: 6931 | BV29: ; | BW29: ; | BX29: ; | BY29: BR | CA29: USD | CF29: 1 | CG29: 1 | CJ29: 0 | CO29: 315566067
A30: 44927 | B30: Shipment delay | C30: 42712 | D30: Transportation Problem - Atraso ETA | E30: TOYOTA | F30: 44943 | G30: Paraisopolis | H30: Inbound Premium | I30: 224.79 | J30: 120 | K30: =I30/$I$1 -> 0.00055021575 | L30: T1-Transportation | M30: Normal | N30: APTIV MANUFATURA E SERVICOS DE-104120 | O30: APTIV LAREDO (FW80)-734188 | P30: INVOICE 10829477 SEM MANIFESTAR E NÃO TEMOS CERTEZA EM QUAL PROCESSO ESTÁ FISICAMENTE | Q30: DHL Express SA | R30: PTA-00088032 | S30: 13533399; | T30: ; | U30: ; | V30: Aptiv | W30: Premium - Productive | X30: Moraes.Arnaldo@aptiv.com | Y30: 44942.319 | Z30: 44960.191 | AA30: SA | AB30: Closed Not Recovered | AC30: 0 | AE30: 22479 | AG30: 10012 | AH30: Q11 | AJ30: 22479 | AK30: Non-Recoverable | AM30: 120 | AN30: USD | AO30: 301 VALLECILLO ROAD | AP30: LAREDO | AQ30: 734188 | AR30: US | AS30: NA | AT30: TX | AU30: 78045-7847 | AV30: AVENIDA AVELINO RIBEIRO, 900 | AW30: PARAISOPOLIS | AX30: 104120 | AY30: BR | AZ30: SA | BA30: MG | BB30: 37660-000 | BC30: SPS | BD30: Approved | BE30: Carvalho, Eliane R | BF30: 44942.338 | BG30: 0 | BI30: 3831132826 | BK30: Transportation | BM30: Personal Estimate | BN30: Invoice | BQ30: 0 Days 0 Hr 27 Min | BR30: 250 | BS30: Approved - ;; Approved - ; | BT30: 22479 | BU30: 22479 | BV30: ; | BW30: ; | BX30: ; | BY30: BR | CA30: USD | CF30: 1 | CG30: 1 | CJ30: 0
A31: 44927 | B31: Customer reschedule | C31: 42717 | D31: Customer Reschedule VW | E31: VW | F31: 44942 | G31: Pinhal | H31: Inbound Premium | I31: 401.52 | J31: 401.52 | K31: =I31/$I$1 -> 0.00098279562 | L31: C4-Capacity-External Customer Resp | M31: Cost Recovery Pending | N31: APTIV MANUFATURA E SERVICOS DE-104991 | O31: Arniflex Monte Alto-Dummy | P31: Customer Reschedule | Q31: TRANSPORTADORA PITUTA | R31: PTA-00088356 | S31: 13921536; | T31: ; | U31: ; | V31: Customer | W31: Premium - Productive | X31: adriane.barbosa.silva@aptiv.com | Y31: 44942.337 | Z31: 44946.222 | AA31: SA | AB31: Closed Not Recovered | AC31: 0 | AE31: 0 | AG31: 10010 | AH31: Q18 | AJ31: 211341 | AK31: Non-Recoverable | AM31: 2095 | AN31: BRL | AO31: Monte Alto | AP31: Monte Alto | AQ31: Dummy | AR31: BR | AS31: SA | AT31: Sao Paulo | AU31: 0000 | AV31: RODOVIA SP 342 KM 196 | AW31: ESPIRITO SANTO DO PINHAL | AX31: 104991 | AY31: BR | AZ31: SA | BA31: SP | BB31: 13990-000 | BC31: SPS | BD31: Approved | BE31: Edilson, Geraldo | BF31: 44943.262 | BG31: 0 | BH31: TRANSPORTADORA PITUTA | BI31: ESP-000037266 | BK31: Customer | BM31: Invoice | BN31: Invoice | BQ31: 0 Days 22 Hr 11 Min | BR31: 500 | BS31: Approved - ;; Approved - ;; Approved - ; | BT31: 40152 | BU31: 40152 | BV31: ; | BW31: ; | BX31: ; | BY31: BR | CA31: BRL | CF31: 19165533 | CG31: 19165533 | CJ31: 0
A32: 44927 | B32: Project | C32: 42868 | D32: BOM Error | E32: FIAT | F32: 44944 | G32: Paraisopolis | H32: Inbound Premium | I32: 432.88 | J32: 420 | K32: =I32/$I$1 -> 0.0010595551 | L32: E1B-BOM Errors | M32: Normal | N32: Paraisopolis-10012 | O32: MTA S P A-737725 | P32: Atraso na implementação da BP por parte da Engenharia - A SSCR deu início em 03/06/2022 e a logistica foi informada apenas 03/10/2022 sobre a obsolecencia. E O BP só foi efetivado na semana 48 onde reprogramamos a MTA de imediato. | Q32: DHL Express SA | R32: PTA-00088302 | S32: 10864719; | T32: ; | U32: ; | V32: Aptiv | W32: Premium - Productive | X32: william.de.siqueira@aptiv.com | Y32: 44943.539 | Z32: 44949.325 | AA32: SA | AB32: Closed Not Recovered | AC32: 0 | AE32: 43288 | AF32: 44950 | AG32: 10012 | AH32: Q11 | AJ32: 43288 | AK32: Non-Recoverable | AM32: 420 | AN32: USD | AO32: VIALE DELLINDUSTRIA 12 | AP32: CODOGNO | AQ32: 737725 | AR32: IT | AS32: EMEA | AT32: LO | AU32: 26845 | AV32: Av. Avelino Ribeiro, 900 | AW32: Paraisopolis | AX32: 10012 | AY32: BR | AZ32: SA | BA32: Mina | BB32: 37660-000 | BC32: SPS | BD32: Approved | BE32: Edilson, Geraldo | BF32: 44943.093 | BG32: 0 | BI32: 4534512791 | BK32: Aptiv | BM32: Invoice | BN32: Invoice | BQ32: 0 Days 1 Hr 16 Min | BR32: 500 | BS32: Approved - ;; Approved - ;; Approved - ; | BT32: 43288 | BU32: 43288 | BV32: ; | BW32: ; | BX32: ; | BY32: BR | CA32: USD | CF32: 1 | CG32: 1 | CJ32: 0
A33: 44927 | B33: Internal problem - Manufacturing/ Ordering/ Purchasing/ IT | C33: 42926 | D33: Ordering Problem - Problemas com forecast causando atraso embarque fornecedor Aptiv Honduras | E33: GM | F33: 44944 | G33: Pinhal | H33: Inbound Premium | I33: 1690 | J33: 3000 | K33: =I33/$I$1 -> 0.0041365924 | L33: B2-Behind Schedule-Aptiv | M33: Normal | N33: APTIV MANUFATURA E SERVICOS DE-104991 | O33: APTIV HONDURAS HN11-765569 | P33: We had some problems with our forecasts with Aptiv Honduras that caused shipment delay. | Q33: DSV UTI Air & Sea Agenciamento de Transportes | R33: PTA-00088499 | S33: 47315377; | T33: ; | U33: ; | V33: Aptiv | W33: Premium - Productive | X33: rodrigo.perez@aptiv.com | Y33: 44943.158 | Z33: 44957.521 | AA33: SA | AB33: Closed Not Recovered | AC33: 0 | AE33: 1690 | AF33: 44943 | AG33: 10010 | AH33: Q18 | AJ33: 1690 | AK33: Non-Recoverable | AM33: 3000 | AN33: USD | AO33: KM 23/24 CARRETERA A OCCIDENTE ZOLI | AP33: QUIMISTAN | AQ33: 765569 | AR33: HN | AS33: NA | AT33: SB | AU33: 22101 | AV33: RODOVIA SP 342 KM 196 | AW33: ESPIRITO SANTO DO PINHAL | AX33: 104991 | AY33: BR | AZ33: SA | BA33: SP | BB33: 13990-000 | BC33: SPS | BD33: Approved | BE33: Garcia Puente, Jorge | BF33: 44944.051 | BG33: 0 | BH33: DSV UTI Air & Sea Agenciamento de Transportes | BI33: SAP501006954 | BK33: Aptiv | BM33: Personal Estimate | BN33: Personal Estimate | BQ33: 0 Days 9 Hr 25 Min | BR33: 5000 | BS33: Approved - ;; Approved - ;; Approved - ;; Approved - ;; Approved - ;; Approved - ; | BT33: 1690 | BU33: 1690 | BV33: ; | BW33: ; | BX33: ; | BY33: BR | CA33: USD | CE33: 47315378 | CF33: 1 | CG33: 1 | CJ33: 0
A34: 44927 | B34: Shipment delay | C34: 43056 | D34: Transportation Problem - Atraso ETA | E34: GM | F34: 44944 | G34: Pinhal | H34: Inbound Premium | I34: 410.71 | J34: 410.71 | K34: =I34/$I$1 -> 0.0010052899 | L34: PC-Plant PC Resp | M34: Normal | N34: APTIV MANUFATURA E SERVICOS DE DIST-1039282 | O34: Empresa de Transportes Covre-Dummy | P34: Entrega Emergencial da Pasta M1018/22, para evitar parada de linha GM. | Q34: EMPRESA DE TRANSPORTES COVRE | R34: PTA-00088408 | S34: 47315375; | T34: ; | U34: ; | V34: Aptiv | W34: Premium - Productive | X34: rodrigo.perez@aptiv.com | Y34: 44943.307 | Z34: 44957.523 | AA34: SA | AB34: Closed Not Recovered | AC34: 0 | AE34: 41071 | AF34: 44943 | AG34: 10010 | AH34: Q18 | AJ34: 41071 | AK34: Non-Recoverable | AM34: 41071 | AN34: USD | AO34: R. Hercílio Camargo Barbosa, 207 | AP34: Santos | AQ34: Dummy | AR34: BR | AS34: SA | AT34: Sao Paulo | AU34: 11095-590 | AV34: RUA JOSE MONFARDINI 3845 | AW34: ESPIRITO SANTO DO PINHAL | AX34: 1039282 | AY34: BR | AZ34: SA | BA34: SP | BB34: 13990-000 | BC34: SPS | BD34: Approved | BE34: Edilson, Geraldo | BF34: 44943.343 | BG34: 0 | BH34: EMPRESA DE TRANSPORTES COVRE | BI34: ENTREGA EMERGENCIAL | BK34: Aptiv | BM34: Personal Estimate | BN34: Personal Estimate | BQ34: 0 Days 0 Hr 52 Min | BR34: 500 | BS34: Approved - ;; Approved - ;; Approved - ; | BT34: 41071 | BU34: 41071 | BV34: ; | BW34: ; | BX34: ; | BY34: BR | CA34: USD | CF34: 1 | CG34: 1 | CJ34: 0 | CP34: 217616996
A35: 44927 | B35: Project | C35: 43063 | D35: Projeto | E35: OTHER | F35: 44944 | G35: Paraisopolis | H35: Inbound Premium | I35: 43 | J35: 0 | K35: =I35/$I$1 -> 0.00010525058 | L35: E1P-Prototypes/Samples | M35: Cost Recovery | N35: Paraisopolis-10012 | O35: SERENDIPITY ELECTRONICS, INC.-1062318 | P35: Parts for project development. Freight will be absorbed at the SC 564-21A quotation. | Q35: DHL Express SA | R35: PTA-00088622 | S35: 13949148PE55625513532153; | T35: ; | U35: ; | V35: Aptiv | W35: Premium - Productive | X35: rayzza.peres@aptiv.com | Y35: 44943.335 | Z35: 44944.145 | AA35: SA | AB35: Closed Recovered | AC35: 0 | AE35: 43 | AG35: 10012 | AH35: Q11 | AJ35: 43 | AK35: Recoverable | AM35: 43 | AN35: USD | AO35: 152 E MAIN ST STE D | AP35: HUNTINGTON | AQ35: 1062318 | AR35: US | AS35: NA | AT35: NY | AU35: 11743-2958 | AV35: Av. Avelino Ribeiro, 900 | AW35: Paraisopolis | AX35: 10012 | AY35: BR | AZ35: SA | BA35: Mina | BB35: 37660-000 | BC35: SPS | BD35: Approved | BE35: Carvalho, Eliane R | BF35: 44944.104 | BG35: 0 | BH35: DHL Express SA | BI35: 4405736580 | BK35: Aptiv | BM35: Invoice | BN35: Invoice | BQ35: 0 Days 18 Hr 27 Min | BR35: 250 | BS35: Approved - ;; Approved - ; | BT35: 43 | BU35: 43 | BV35: ; | BW35: ; | BX35: ; | BY35: BR | BZ35: CNH - ARO 10 | CA35: USD | CE35: DPP67537 DPP67622 | CF35: 1 | CG35: 1 | CJ35: 0 | CO35: 800114696
A36: 44927 | B36: Shipment delay | C36: 43397 | D36: Transportation Problem - Atraso ETA | E36: GM | F36: 44945 | G36: Pinhal | H36: Inbound Premium | I36: 740.44 | J36: 750 | K36: =I36/$I$1 -> 0.001812366 | L36: T1-Transportation | M36: Normal | N36: APTIV MANUFATURA E SERVICOS DE-104991 | O36: J.S.T. CORPORATION-7025683 | P36: Air Freight needed due to the ETA delay of ONE HAWK. | Q36: DHL Express SA | R36: PTA-00088853 | S36: 13646861; | T36: ; | U36: ; | V36: Aptiv | W36: Premium - Productive | X36: rodrigo.perez@aptiv.com | Y36: 44944.297 | Z36: 44957.524 | AA36: SA | AB36: Closed Not Recovered | AC36: 0 | AE36: 74044 | AF36: 44944 | AG36: 10010 | AH36: Q18 | AJ36: 74044 | AK36: Non-Recoverable | AM36: 750 | AN36: USD | AO36: 37879 INTERCHANGE DR | AP36: FARMINGTON HILLS | AQ36: 7025683 | AR36: US | AS36: NA | AT36: MI | AU36: 48335-1024 | AV36: RODOVIA SP 342 KM 196 | AW36: ESPIRITO SANTO DO PINHAL | AX36: 104991 | AY36: BR | AZ36: SA | BA36: SP | BB36: 13990-000 | BC36: SPS | BD36: Approved | BE36: Naus, Angelica | BF36: 44945.074 | BG36: 0 | BH36: DHL Express SA | BI36: 5570183883 | BK36: Transportation | BM36: Invoice | BN36: Personal Estimate | BQ36: 0 Days 18 Hr 38 Min | BR36: 800 | BS36: Approved - ;; Approved - ;; Approved - ;; Approved - ; | BT36: 74044 | BU36: 74044 | BV36: ; | BW36: ; | BX36: ; | BY36: BR | CA36: USD | CE36: 13588505/13595476/35028910/35120496. | CF36: 1 | CG36: 1 | CJ36: 0 | CO36: 690666524
A37: 44927 | B37: Internal problem - Manufacturing/ Ordering/ Purchasing/ IT | C37: 43630 | D37: Ordering Problem - Problemas com forecast causando atraso embarque fornecedor Aptiv Honduras | E37: GM | F37: 44946 | G37: Pinhal | H37: Inbound Premium | I37: 2000 | J37: 2000 | K37: =I37/$I$1 -> 0.0048953757 | L37: B2-Behind Schedule-Aptiv | M37: Normal | N37: APTIV MANUFATURA E SERVICOS DE-104991 | O37: APTIV HONDURAS HN11-765569 | P37: We had some problems with our forecasts with Aptiv Honduras that caused shipment delay. | Q37: DSV UTI Air & Sea Agenciamento de Transportes | S37: 13818129; | T37: ; | U37: ; | V37: Aptiv | W37: Premium - Productive | X37: rodrigo.perez@aptiv.com | Y37: 44957.11 | Z37: 44957.11 | AA37: SA | AB37: Closed Not Recovered | AC37: 0 | AE37: 0 | AF37: 44945 | AG37: 10010 | AH37: Q18 | AK37: Non-Recoverable | AM37: 2000 | AO37: KM 23/24 CARRETERA A OCCIDENTE ZOLI | AP37: QUIMISTAN | AQ37: 765569 | AR37: HN | AS37: NA | AT37: SB | AU37: 22101 | AV37: RODOVIA SP 342 KM 196 | AW37: ESPIRITO SANTO DO PINHAL | AX37: 104991 | AY37: BR | AZ37: SA | BA37: SP | BB37: 13990-000 | BC37: SPS | BD37: Pending | BG37: 0 | BH37: DSV UTI Air & Sea Agenciamento de Transportes | BK37: Aptiv | BM37: Personal Estimate | BN37: Personal Estimate | BR37: 0 | BS37: Approved - ;; Approved - ;; Approved - ;; Approved - ok ;; Pending - | BT37: 2000 | BU37: 2000 | BV37: ; | BW37: ; | BX37: ; | BY37: BR | CA37: USD | CE37: 47315375/47314246/47315376 | CF37: 1 | CJ37: 0
A38: 44927 | B38: Stock discrepancy | C38: 43813 | D38: Stock Discrepancy | E38: JOHN DEERE | F38: 44949 | G38: Paraisopolis | H38: Inbound Premium | I38: 816.66 | J38: 248 | K38: =I38/$I$1 -> 0.0019989287 | L38: S1I-Inventory loss/adjustments | M38: Normal | N38: APTIV MANUFATURA E SERVICOS DE-104120 | O38: HARNESS CODE LTD OOD-7089652 | P38: Material inventariado erroneamente - risco de parada do cliente JD | Q38: Expeditors International | R38: PTA-00089104 | S38: 10737325; | T38: ; | U38: ; | V38: Aptiv | W38: Premium - Productive | X38: jorge.luis.almeida@aptiv.com | Y38: 44946.485 | Z38: 44961.515 | AA38: SA | AB38: Closed Not Recovered | AC38: 0 | AE38: 81666 | AG38: 10012 | AH38: Q11 | AJ38: 81666 | AK38: Non-Recoverable | AM38: 248 | AN38: USD | AO38: 12 DOSPAT STR./BLVD. | AP38: SOFIA | AQ38: 7089652 | AR38: BG | AS38: EMEA | AT38: 22 | AU38: 1606 | AV38: AVENIDA AVELINO RIBEIRO, 900 | AW38: PARAISOPOLIS | AX38: 104120 | AY38: BR | AZ38: SA | BA38: MG | BB38: 37660-000 | BC38: SPS | BD38: Approved | BE38: Carvalho, Eliane R | BF38: 44946.512 | BG38: 0 | BH38: Expeditors International | BI38: 2977928590 | BK38: Aptiv | BM38: Invoice | BN38: Invoice | BQ38: 0 Days 0 Hr 38 Min | BR38: 250 | BS38: Approved - ;; Approved - ; | BT38: 81666 | BU38: 81666 | BV38: ; | BW38: ; | BX38: ; | BY38: BR | BZ38: 6M | CA38: USD | CE38: Mterial de baixo volume inventariado errado no inventário sem opção de desvio e com risco de parada do cliente JD | CF38: 1 | CG38: 1 | CJ38: 0 | CO38: 507488352
A39: 44927 | B39: Shipment delay | C39: 43815 | D39: Transportation Problem - Atraso ETA | E39: GM | F39: 44946 | G39: Pinhal | H39: Inbound Premium | I39: 546.61 | J39: 442 | K39: =I39/$I$1 -> 0.0013379306 | L39: T1-Transportation | M39: Normal | N39: APTIV MANUFATURA E SERVICOS DE-104991 | O39: APTIV SERVICES US, LLC-1056313 | P39: Aéreo necessário devido ao atraso de ETA do Navio ONE HAWK. Invoices Afetadas : 10954307 / 11040992. | Q39: DHL Express SA | R39: PTA-00089116 | S39: 15429045; | T39: ; | U39: ; | V39: Aptiv | W39: Premium - Productive | X39: rodrigo.perez@aptiv.com | Y39: 44946.506 | Z39: 44957.53 | AA39: SA | AB39: Closed Not Recovered | AC39: 0 | AE39: 54661 | AF39: 44946 | AG39: 10010 | AH39: Q18 | AJ39: 54661 | AK39: Non-Recoverable | AM39: 442 | AN39: USD | AO39: AV. DE LAS INDUSTRIAS 1410 | AP39: CIUDAD JUAREZ | AQ39: 1056313 | AR39: MX | AS39: NA | AT39: CHH | AU39: 32470 | AV39: RODOVIA SP 342 KM 196 | AW39: ESPIRITO SANTO DO PINHAL | AX39: 104991 | AY39: BR | AZ39: SA | BA39: SP | BB39: 13990-000 | BC39: SPS | BD39: Approved | BE39: Edilson, Geraldo | BF39: 44946.089 | BG39: 0 | BH39: DHL Express SA | BI39: 1088515411 | BK39: Transportation | BM39: Personal Estimate | BN39: Personal Estimate | BQ39: 0 Days 1 Hr 59 Min | BR39: 500 | BS39: Approved - ;; Approved - ;; Approved - ; | BT39: 54661 | BU39: 54661 | BV39: ; | BW39: ; | BX39: ; | BY39: BR | CA39: USD | CE39: 15513474/15514821/35031567/35072403 | CF39: 1 | CG39: 1 | CJ39: 0 | CO39: 43898092
A40: 44927 | B40: Shipment delay | C40: 43816 | D40: Transportation Problem - Atraso ETA | E40: GM | F40: 44946 | G40: Pinhal | H40: Inbound Premium | I40: 581.54 | J40: 513 | K40: =I40/$I$1 -> 0.0014234284 | L40: T1-Transportation | M40: Normal | N40: APTIV MANUFATURA E SERVICOS DE-104991 | O40: APTIV SERVICES US, LLC-1001280 | P40: Aéreo necessário devido ao atraso de ETA do Navio ONE HAWK. Invoices Afetadas : 11052167 / 11134170. | Q40: DHL Express SA | R40: PTA-00089197 | S40: 15482324; | T40: ; | U40: ; | V40: Aptiv | W40: Premium - Productive | X40: rodrigo.perez@aptiv.com | Y40: 44946.511 | Z40: 44957.532 | AA40: SA | AB40: Closed Not Recovered | AC40: 0 | AE40: 58154 | AF40: 44946 | AG40: 10010 | AH40: Q18 | AJ40: 58154 | AK40: Non-Recoverable | AM40: 513 | AN40: USD | AO40: 1265 N RIVER RD NE | AP40: WARREN | AQ40: 1001280 | AR40: US | AS40: NA | AT40: OH | AU40: 44483-2352 | AV40: RODOVIA SP 342 KM 196 | AW40: ESPIRITO SANTO DO PINHAL | AX40: 104991 | AY40: BR | AZ40: SA | BA40: SP | BB40: 13990-000 | BC40: SPS | BD40: Approved | BE40: Naus, Angelica | BF40: 44946.288 | BG40: 0 | BH40: DHL Express SA | BI40: 1088803096 | BK40: Transportation | BM40: Personal Estimate | BN40: Personal Estimate | BQ40: 0 Days 6 Hr 39 Min | BR40: 800 | BS40: Approved - ;; Approved - ;; Approved - ;; Approved - ; | BT40: 58154 | BU40: 58154 | BV40: ; | BW40: ; | BX40: ; | BY40: BR | CA40: USD | CF40: 1 | CG40: 1 | CJ40: 0 | CO40: 217616996
A41: 44927 | B41: P&A | C41: 43820 | D41: P&A | E41: FIAT | F41: 44946 | G41: Paraisopolis | H41: Inbound Premium | I41: 71.81 | J41: 42.9 | K41: =I41/$I$1 -> 0.00017576846 | L41: OOOT-Other/Sales | M41: Normal | N41: APTIV MANUFATURA E SERVICOS DE-104120 | O41: CHIP 1 EXCHANGE USA, INC.-1067251 | P41: Material to meet the P&A assembly according to the FIAT customer's schedule at the Paraisopolis plant. | Q41: DHL Express SA | R41: PTA-00089113 | S41: 10756350; | T41: 1500; | U41: 2.63; | V41: Aptiv | W41: Premium - Productive | X41: marcia.p.torres@aptiv.com | Y41: 44946.541 | Z41: 44960.243 | AA41: SA | AB41: Closed Not Recovered | AC41: 0 | AE41: 7181 | AF41: 44946 | AG41: 10012 | AH41: Q11 | AJ41: 7181 | AK41: Non-Recoverable | AM41: 429 | AN41: USD | AO41: 701 EIGHT TWENTY BLVD STE 101 | AP41: FORT WORTH | AQ41: 1067251 | AR41: US | AS41: NA | AT41: TX | AU41: 76106-2002 | AV41: AVENIDA AVELINO RIBEIRO, 900 | AW41: PARAISOPOLIS | AX41: 104120 | AY41: BR | AZ41: SA | BA41: MG | BB41: 37660-000 | BC41: SPS | BD41: Approved | BE41: Carvalho, Eliane R | BF41: 44946.088 | BG41: 0 | BH41: DHL Express SA | BI41: 1505062532 | BK41: Aptiv | BM41: Invoice | BN41: Invoice | BO41: FIAT | BQ41: 0 Days 1 Hr 6 Min | BR41: 250 | BS41: Approved - ;; Approved - ; | BT41: 7181 | BU41: 7181 | BV41: 1; | BW41: 26x26x6; | BX41: ; | BY41: BR | BZ41: P&A | CA41: USD | CD41: Kg | CE41: Material to meet the P&A assembly according to the FIAT customer's schedule at the Paraisopolis plant. | CF41: 1 | CG41: 1 | CJ41: 0 | CO41: 537330958
A42: 44927 | B42: Project | C42: 43822 | D42: Projeto | E42: JOHN DEERE | F42: 44946 | G42: Paraisopolis | H42: Inbound Premium | I42: 160 | J42: 160 | K42: =I42/$I$1 -> 0.00039163005 | L42: S1E-Planner/Schedule/customer service errors | M42: Cost Recovery | N42: APTIV MANUFATURA E SERVICOS DE-104120 | O42: MURAT TICARET KABLO SANAYI ANONIM S-1068506 | P42: Parts for project development. Freight will be absorbed at the SC 126-22 quotation. | Q42: DHL Express SA | R42: PTA-00089114 | S42: 35699068; | T42: ; | U42: ; | V42: Aptiv | W42: Premium - Productive | X42: jorge.luis.almeida@aptiv.com | Y42: 44946.054 | Z42: 44946.054 | AA42: SA | AB42: Closed - Negotiated (w/Customer) | AC42: 0 | AE42: 0 | AG42: 10012 | AH42: Q11 | AK42: Recoverable | AM42: 160 | AO42: A BLOK, BELEDIYE SANAYI SITESI | AP42: ISTANBUL (EUROPE) | AQ42: 1068506 | AR42: TR | AS42: EMEA | AT42: 34 | AU42: 34197 | AV42: AVENIDA AVELINO RIBEIRO, 900 | AW42: PARAISOPOLIS | AX42: 104120 | AY42: BR | AZ42: SA | BA42: MG | BB42: 37660-000 | BC42: SPS | BD42: Approved | BE42: Carvalho, Eliane R | BF42: 44946.088 | BG42: 0 | BK42: Aptiv | BM42: Invoice | BQ42: 0 Days 0 Hr 47 Min | BR42: 250 | BS42: Approved - ;; Approved - ; | BT42: 160 | BU42: 160 | BV42: ; | BW42: ; | BX42: ; | BY42: BR | BZ42: PROJETO CNH TB15 | CA42: USD | CE42: Parts for project development. Freight will be absorbed at the SC 126-22 quotation. | CF42: 1 | CJ42: 0 | CO42: 644176299
A43: 44927 | B43: Internal problem - Manufacturing/ Ordering/ Purchasing/ IT | C43: 43906 | D43: Ordering Problem - Problemas com forecast causando atraso embarque fornecedor Aptiv Honduras | E43: GM | F43: 44946 | G43: Pinhal | H43: Inbound Premium | I43: 2000 | J43: 2000 | K43: =I43/$I$1 -> 0.0048953757 | L43: B2-Behind Schedule-Aptiv | M43: Normal | N43: APTIV MANUFATURA E SERVICOS DE-104991 | O43: APTIV HONDURAS HN11-765569 | P43: We had some problems with our forecasts with Aptiv Honduras that caused shipment delay. | Q43: DSV UTI Air & Sea Agenciamento de Transportes | S43: 35578211; | T43: ; | U43: ; | V43: Aptiv | W43: Premium - Productive | X43: rodrigo.perez@aptiv.com | Y43: 44957.11 | Z43: 44957.11 | AA43: SA | AB43: Closed Not Recovered | AC43: 0 | AE43: 0 | AF43: 44946 | AG43: 10010 | AH43: Q18 | AK43: Non-Recoverable | AM43: 2000 | AO43: KM 23/24 CARRETERA A OCCIDENTE ZOLI | AP43: QUIMISTAN | AQ43: 765569 | AR43: HN | AS43: NA | AT43: SB | AU43: 22101 | AV43: RODOVIA SP 342 KM 196 | AW43: ESPIRITO SANTO DO PINHAL | AX43: 104991 | AY43: BR | AZ43: SA | BA43: SP | BB43: 13990-000 | BC43: SPS | BD43: Pending | BG43: 0 | BH43: DSV UTI Air & Sea Agenciamento de Transportes | BK43: Aptiv | BM43: Personal Estimate | BN43: Personal Estimate | BR43: 0 | BS43: Approved - ;; Approved - ;; Approved - ;; Approved - ok ;; Pending - | BT43: 2000 | BU43: 2000 | BV43: ; | BW43: ; | BX43: ; | BY43: BR | CA43: USD | CF43: 1 | CJ43: 0
A44: 44927 | B44: Project | C44: 44087 | D44: BOM Error | E44: FIAT | F44: 44944 | G44: Paraisopolis | H44: Inbound Premium | I44: 205.93 | J44: 170 | K44: =I44/$I$1 -> 0.00050405236 | L44: E1B-BOM Errors | M44: Normal | N44: Paraisopolis-10012 | O44: MTA S P A-737725 | P44: Atraso na implementação da BP por parte da Engenharia - A SSCR deu início em 03/06/2022 e a logistica foi informada apenas 03/10/2022 sobre a obsolecencia. E O BP só foi efetivado na semana 48 onde reprogramamos a MTA de imediato.(PRODUZINDO DENTRO DO LT) | Q44: DHL Express SA | R44: PTA-00089398 | S44: 10864719; | T44: ; | U44: ; | V44: Aptiv | W44: Premium - Productive | X44: william.de.siqueira@aptiv.com | Y44: 44949.522 | Z44: 44953.119 | AA44: SA | AB44: Closed Not Recovered | AC44: 0 | AE44: 20593 | AF44: 44950 | AG44: 10012 | AH44: Q11 | AJ44: 20593 | AK44: Non-Recoverable | AM44: 170 | AN44: USD | AO44: VIALE DELLINDUSTRIA 12 | AP44: CODOGNO | AQ44: 737725 | AR44: IT | AS44: EMEA | AT44: LO | AU44: 26845 | AV44: Av. Avelino Ribeiro, 900 | AW44: Paraisopolis | AX44: 10012 | AY44: BR | AZ44: SA | BA44: Mina | BB44: 37660-000 | BC44: SPS | BD44: Approved | BE44: Carvalho, Eliane R | BF44: 44949.082 | BG44: 0 | BI44: 1088726085 | BK44: Aptiv | BM44: Invoice | BN44: Invoice | BQ44: 0 Days 1 Hr 26 Min | BR44: 250 | BS44: Approved - ;; Approved - ; | BT44: 20593 | BU44: 20593 | BV44: ; | BW44: ; | BX44: ; | BY44: BR | CA44: USD | CF44: 1 | CG44: 1 | CJ44: 0
A45: 44927 | B45: Shipment delay | C45: 44445 | D45: Shipment Delay Aptiv | E45: GM | F45: 44950 | G45: Ouros | H45: Outbound Premium | I45: 240.6 | J45: 240.6 | K45: =I45/$I$1 -> 0.00058891369 | L45: S1E-Planner/Schedule/customer service errors | M45: Normal | N45: GENERAL MOTORS (72664)-700535 | O45: APTIV MANUFATURA E SERVICOS DE-109304 | P45: Shipment Delay | Q45: TRANSPORTADORA PITUTA | R45: PTA-00089714 | S45: 35706140; | T45: ; | U45: ; | V45: Aptiv | W45: Premium - Productive | X45: adriane.barbosa.silva@aptiv.com | Y45: 44950.141 | Z45: 44950.14 | AA45: SA | AB45: Closed Not Recovered | AC45: 0 | AE45: 0 | AG45: 10023 | AH45: Q11 | AK45: Non-Recoverable | AM45: 125538 | AO45: TV ANTONIO E FONSECA 250 BAIRRO | AP45: CONCEICAO DOS OUROS | AQ45: 109304 | AR45: BR | AS45: SA | AT45: MG | AU45: 37548-000 | AV45: CISCO 72664 | AW45: SAO JOSE DOS CAMPOS | AX45: 700535 | AY45: BR | AZ45: SA | BA45: SP | BB45: 12224-300 | BC45: SPS | BD45: Approved | BE45: Carvalho, Eliane R | BF45: 44950.232 | BG45: 0 | BH45: TRANSPORTADORA PITUTA | BK45: Aptiv | BM45: Invoice | BN45: Invoice | BQ45: 0 Days 2 Hr 10 Min | BR45: 250 | BS45: Approved - ;; Approved - ; | BT45: 2406 | BU45: 2406 | BV45: ; | BW45: ; | BX45: ; | BY45: BR | CA45: BRL | CF45: 19165533 | CJ45: 0
A46: 44927 | B46: Project | C46: 44458 | D46: Projeto | E46: GM | F46: 44950 | G46: Paraisopolis | H46: Inbound Premium | I46: 38 | J46: 0 | K46: =I46/$I$1 -> 9.3012138e-05 | L46: E1P-Prototypes/Samples | M46: Cost Recovery | N46: Paraisopolis-10012 | O46: SERENDIPITY ELECTRONICS-110404 | P46: Parts for sales from protoypes pieces. Freigth included in the piece price. | Q46: DHL Express SA | R46: PTA-00089715 | S46: 13611693; | T46: ; | U46: ; | V46: Aptiv | W46: Premium - Productive | X46: rayzza.peres@aptiv.com | Y46: 44950.147 | Z46: 44950.256 | AA46: SA | AB46: Closed Recovered | AC46: 0 | AE46: 38 | AG46: 10012 | AH46: Q11 | AJ46: 38 | AK46: Recoverable | AM46: 38 | AN46: USD | AO46: 152 E MAIN ST | AP46: HUNTINGTON | AQ46: 110404 | AR46: US | AS46: NA | AT46: NY | AU46: 11743-2958 | AV46: Av. Avelino Ribeiro, 900 | AW46: Paraisopolis | AX46: 10012 | AY46: BR | AZ46: SA | BA46: Mina | BB46: 37660-000 | BC46: SPS | BD46: Approved | BE46: Carvalho, Eliane R | BF46: 44950.232 | BG46: 0 | BI46: 7919757274 | BK46: Aptiv | BM46: Invoice | BN46: Invoice | BQ46: 0 Days 2 Hr 2 Min | BR46: 250 | BS46: Approved - ;; Approved - ; | BT46: 38 | BU46: 38 | BV46: ; | BW46: ; | BX46: ; | BY46: BR | BZ46: BSUV PL8 - PROTOTYPE | CA46: USD | CE46: DPP67515 | CF46: 1 | CG46: 1 | CJ46: 0
A47: 44927 | B47: Project | C47: 44461 | D47: Projeto | E47: OTHER | F47: 44951 | G47: Paraisopolis | H47: Inbound Premium | I47: 478 | J47: 478 | K47: =I47/$I$1 -> 0.0011699948 | L47: E1P-Prototypes/Samples | M47: Cost Recovery | N47: Paraisopolis-10012 | O47: APTIV CENTEC II (FW97)-726918 | P47: Parts for project development. Freight will be absorbed at the SC 126-22 quotation. | Q47: DHL Express SA | R47: PTA-00089742 | S47: 15544343 15544345 15544350; | T47: ; | U47: ; | V47: Aptiv | W47: Premium - Productive | X47: rayzza.peres@aptiv.com | Y47: 44950.15 | Z47: 44950.15 | AA47: SA | AB47: Closed Recovered | AC47: 0 | AE47: 478 | AG47: 10012 | AH47: Q11 | AJ47: 478 | AK47: Recoverable | AM47: 478 | AN47: USD | AO47: BLVD ISIDRO LOPEZ ZERTUCHE 4890 | AP47: SALTILLO | AQ47: 726918 | AR47: MX | AS47: NA | AT47: COA | AU47: 25230 | AV47: Av. Avelino Ribeiro, 900 | AW47: Paraisopolis | AX47: 10012 | AY47: BR | AZ47: SA | BA47: Mina | BB47: 37660-000 | BC47: SPS | BD47: Approved | BE47: Edilson, Geraldo | BF47: 44950.279 | BG47: 0 | BH47: DHL Express SA | BK47: Aptiv | BM47: Invoice | BN47: Invoice | BQ47: 0 Days 3 Hr 4 Min | BR47: 500 | BS47: Approved - ;; Approved - ;; Approved - ; | BT47: 478 | BU47: 478 | BV47: ; | BW47: ; | BX47: ; | BY47: BR | BZ47: CNH TB15 | CA47: USD | CE47: DPP65725 | CF47: 1 | CG47: 1 | CJ47: 0
A48: 44927 | B48: Project | C48: 44531 | D48: Projeto | E48: TOYOTA | F48: 44951 | G48: Paraisopolis | H48: Inbound Premium | I48: 35 | J48: 35 | K48: =I48/$I$1 -> 8.5669074e-05 | L48: E1P-Prototypes/Samples | M48: Cost Recovery | N48: Paraisopolis-10012 | O48: HARNESS CODE LTD-762363 | P48: Parts for sales from protoypes pieces. Freigth included in the piece price. | Q48: DHL Express SA | R48: PTA-00090274 | S48: PE501069; | T48: ; | U48: ; | V48: Aptiv | W48: Premium - Productive | X48: rayzza.peres@aptiv.com | Y48: 44950.243 | Z48: 44950.243 | AA48: SA | AB48: Closed Recovered | AC48: 0 | AE48: 35 | AG48: 10012 | AH48: Q11 | AJ48: 35 | AK48: Recoverable | AM48: 35 | AN48: USD | AO48: 12 DOSPAT STREET FL 1 SUITE T | AP48: SOFIA | AQ48: 762363 | AR48: BG | AS48: EMEA | AT48: 23 | AU48: 1606 | AV48: Av. Avelino Ribeiro, 900 | AW48: Paraisopolis | AX48: 10012 | AY48: BR | AZ48: SA | BA48: Mina | BB48: 37660-000 | BC48: SPS | BD48: Approved | BE48: Carvalho, Eliane R | BF48: 44953.072 | BG48: 0 | BH48: DHL Express SA | BK48: Aptiv | BM48: Invoice | BN48: Invoice | BQ48: 2 Days 19 Hr 53 Min | BR48: 250 | BS48: Approved - ;; Approved - ; | BT48: 35 | BU48: 35 | BV48: ; | BW48: ; | BX48: ; | BY48: BR | BZ48: 397D | CA48: USD | CE48: DPP66885 | CF48: 1 | CG48: 1 | CJ48: 0
A49: 44927 | B49: Shipment delay | C49: 44532 | D49: Shipment Delay Aptiv | E49: TOYOTA | F49: 44950 | G49: Paraisopolis | H49: Outbound Premium | I49: 459.97 | J49: 459.97 | K49: =I49/$I$1 -> 0.001125863 | L49: S1E-Planner/Schedule/customer service errors | M49: Normal | N49: Toyota Sorocaba -Dummy | O49: APTIV MANUFATURA E SERVICOS DE-104120 | P49: Shipment Delay | Q49: TRANSPORTADORA PITUTA | R49: PTA-00089851 | S49: 35358112; | T49: ; | U49: ; | V49: Aptiv | W49: Premium - Productive | X49: adriane.barbosa.silva@aptiv.com | Y49: 44950.251 | Z49: 44950.251 | AA49: SA | AB49: Closed Not Recovered | AC49: 0 | AE49: 0 | AG49: 10012 | AH49: Q11 | AK49: Non-Recoverable | AM49: 2400 | AO49: AVENIDA AVELINO RIBEIRO, 900 | AP49: PARAISOPOLIS | AQ49: 104120 | AR49: BR | AS49: SA | AT49: MG | AU49: 37660-000 | AV49: Sorocaba | AW49: Sorocaba | AX49: Dummy | AY49: BR | AZ49: SA | BA49: Sao Paulo | BB49: 0000 | BC49: SPS | BD49: Approved | BE49: Edilson, Geraldo | BF49: 44951.074 | BG49: 0 | BK49: Aptiv | BM49: Invoice | BN49: Invoice | BQ49: 0 Days 19 Hr 45 Min | BR49: 500 | BS49: Approved - ;; Approved - ;; Approved - ; | BT49: 45997 | BU49: 45997 | BV49: ; | BW49: ; | BX49: ; | BY49: BR | CA49: BRL | CF49: 19165533 | CJ49: 0
A50: 44927 | B50: Internal problem - Manufacturing/ Ordering/ Purchasing/ IT | C50: 44560 | D50: Ordering Problem - Problemas com forecast causando atraso embarque fornecedor Aptiv Honduras | E50: GM | F50: 44951 | G50: Pinhal | H50: Inbound Premium | I50: 2000 | J50: 2000 | K50: =I50/$I$1 -> 0.0048953757 | L50: B2-Behind Schedule-Aptiv | M50: Normal | N50: APTIV MANUFATURA E SERVICOS DE-104991 | O50: APTIV HONDURAS HN11-765569 | P50: We had some problems with our forecasts with Aptiv Honduras that caused shipment delay. | Q50: DSV UTI Air & Sea Agenciamento de Transportes | S50: 35578211; | T50: ; | U50: ; | V50: Aptiv | W50: Premium - Productive | X50: rodrigo.perez@aptiv.com | Y50: 44957.108 | Z50: 44957.105 | AA50: SA | AB50: Closed Not Recovered | AC50: 0 | AE50: 0 | AF50: 44950 | AG50: 10010 | AH50: Q18 | AK50: Non-Recoverable | AM50: 2000 | AO50: KM 23/24 CARRETERA A OCCIDENTE ZOLI | AP50: QUIMISTAN | AQ50: 765569 | AR50: HN | AS50: NA | AT50: SB | AU50: 22101 | AV50: RODOVIA SP 342 KM 196 | AW50: ESPIRITO SANTO DO PINHAL | AX50: 104991 | AY50: BR | AZ50: SA | BA50: SP | BB50: 13990-000 | BC50: SPS | BD50: Pending | BG50: 0 | BH50: DSV UTI Air & Sea Agenciamento de Transportes | BK50: Aptiv | BM50: Personal Estimate | BN50: Personal Estimate | BR50: 0 | BS50: Approved - ;; Approved - ;; Approved - ;; Approved - ok ;; Pending - | BT50: 2000 | BU50: 2000 | BV50: ; | BW50: ; | BX50: ; | BY50: BR | CA50: USD | CE50: 47314246/47315378/35657027/35657024/35657026 | CF50: 1 | CJ50: 0
A51: 44927 | B51: Stock discrepancy | C51: 44821 | D51: Stock Discrepancy | E51: JOHN DEERE | F51: 44951 | G51: Paraisopolis | H51: Inbound Premium | I51: 172.81 | J51: 172.81 | K51: =I51/$I$1 -> 0.00042298493 | L51: S1I-Inventory loss/adjustments | M51: Normal | N51: Tyco Bragança Paulista-Dummy | O51: Lear Navegantes-Dummy | P51: Stock Discrepancy | Q51: Brix | R51: PTA-00090037 | S51: 10846434; | T51: ; | U51: ; | V51: Aptiv | W51: Premium - Productive | X51: adriane.barbosa.silva@aptiv.com | Y51: 44951.374 | Z51: 44951.374 | AA51: SA | AB51: Closed Not Recovered | AC51: 0 | AE51: 0 | AG51: 10012 | AH51: Q11 | AK51: Non-Recoverable | AM51: 90168 | AO51: Navegantes | AP51: Navegantes | AQ51: Dummy | AR51: BR | AS51: SA | AT51: Santa Catarina | AU51: 0000 | AV51: Bragança Paulista | AW51: Bragança Paulista | AX51: Dummy | AY51: BR | AZ51: SA | BA51: MG | BB51: 0000 | BC51: SPS | BD51: Approved | BE51: Carvalho, Eliane R | BF51: 44952.484 | BG51: 0 | BH51: Brix | BK51: Aptiv | BM51: Invoice | BN51: Invoice | BQ51: 0 Days 14 Hr 38 Min | BR51: 250 | BS51: Approved - ;; Approved - ; | BT51: 17281 | BU51: 17281 | BV51: ; | BW51: ; | BX51: ; | BY51: BR | CA51: BRL | CF51: 19165533 | CJ51: 0
A52: 44927 | B52: Project | C52: 44827 | D52: Engineering Problem | E52: JOHN DEERE | F52: 44951 | G52: Paraisopolis | H52: Inbound Premium | I52: 1192.78 | J52: 1192.78 | K52: =I52/$I$1 -> 0.0029195531 | L52: E1D-Aptiv Design/Engineering changes | M52: Normal | N52: APTIV MANUFATURA E SERVICOS DE-104120 | O52: Acome Irati-Dummy | P52: Engineering change, impacting production scheduling and material planning, not generating demand for the supplier | Q52: TRANSPORTADORA PITUTA | S52: M3398205; | T52: ; | U52: ; | V52: Aptiv | W52: Premium - Productive | X52: adriane.barbosa.silva@aptiv.com | Y52: 44957.096 | Z52: 44957.092 | AA52: SA | AB52: Closed Not Recovered | AC52: 0 | AE52: 0 | AG52: 10012 | AH52: Q11 | AK52: Non-Recoverable | AM52: 622356 | AO52: Irati | AP52: Irati | AQ52: Dummy | AR52: BR | AS52: SA | AT52: Parana | AU52: 0000 | AV52: AVENIDA AVELINO RIBEIRO, 900 | AW52: PARAISOPOLIS | AX52: 104120 | AY52: BR | AZ52: SA | BA52: MG | BB52: 37660-000 | BC52: SPS | BD52: Pending | BG52: 0 | BH52: TRANSPORTADORA PITUTA | BK52: Aptiv | BM52: Invoice | BN52: Invoice | BR52: 0 | BS52: Approved - ;; Approved - ;; Approved - ;; Approved - ok ;; Pending - | BT52: 119278 | BU52: 119278 | BV52: ; | BW52: ; | BX52: ; | BY52: BR | CA52: BRL | CF52: 19165533 | CJ52: 0
A53: 44927 | B53: Stock discrepancy | C53: 44943 | D53: Stock Discrepancy | E53: JOHN DEERE | F53: 44953 | G53: Paraisopolis | H53: Inbound Premium | I53: 222 | J53: 222 | K53: =I53/$I$1 -> 0.0005433867 | L53: S1I-Inventory loss/adjustments | M53: Normal | N53: Paraisopolis-10012 | O53: COOPER BUSSMANN-Dummy | P53: Divergencia de 4 caixas STD PACKING. | Q53: DHL Express SA | R53: PTA-00090038 | S53: 1393744; | T53: ; | U53: ; | V53: Aptiv | W53: Premium - Productive | X53: william.de.siqueira@aptiv.com | Y53: 44952.476 | Z53: 44952.475 | AA53: SA | AB53: Closed Not Recovered | AC53: 0 | AE53: 0 | AF53: 44957 | AG53: 10012 | AH53: Q11 | AK53: Non-Recoverable | AM53: 222 | AO53: PO BOX 640837 | AP53: PITTSBURGH | AQ53: Dummy | AR53: US | AS53: NA | AT53: _ | AU53: 15264-0837 | AV53: Av. Avelino Ribeiro, 900 | AW53: Paraisopolis | AX53: 10012 | AY53: BR | AZ53: SA | BA53: Mina | BB53: 37660-000 | BC53: SPS | BD53: Approved | BE53: Carvalho, Eliane R | BF53: 44952.485 | BG53: 0 | BK53: Aptiv | BM53: Invoice | BQ53: 0 Days 0 Hr 11 Min | BR53: 250 | BS53: Approved - ;; Approved - ; | BT53: 222 | BU53: 222 | BV53: ; | BW53: ; | BX53: ; | BY53: BR | CA53: USD | CF53: 1 | CJ53: 0
A54: 44927 | B54: Internal problem - Manufacturing/ Ordering/ Purchasing/ IT | C54: 44945 | D54: Ordering Problem - Problemas com forecast causando atraso embarque fornecedor Aptiv Honduras | E54: GM | F54: 44952 | G54: Pinhal | H54: Inbound Premium | I54: 3000 | J54: 3000 | K54: =I54/$I$1 -> 0.0073430635 | L54: B2-Behind Schedule-Aptiv | M54: Normal | N54: APTIV MANUFATURA E SERVICOS DE-104991 | O54: APTIV HONDURAS HN11-765569 | P54: We had some problems with our forecasts with Aptiv Honduras that caused shipment delay. | Q54: DSV UTI Air & Sea Agenciamento de Transportes | S54: 47315374; | T54: ; | U54: ; | V54: Aptiv | W54: Premium - Productive | X54: rodrigo.perez@aptiv.com | Y54: 44958.479 | Z54: 44958.479 | AA54: SA | AB54: Closed Not Recovered | AC54: 0 | AE54: 0 | AF54: 44952 | AG54: 10010 | AH54: Q18 | AK54: Non-Recoverable | AM54: 3000 | AO54: KM 23/24 CARRETERA A OCCIDENTE ZOLI | AP54: QUIMISTAN | AQ54: 765569 | AR54: HN | AS54: NA | AT54: SB | AU54: 22101 | AV54: RODOVIA SP 342 KM 196 | AW54: ESPIRITO SANTO DO PINHAL | AX54: 104991 | AY54: BR | AZ54: SA | BA54: SP | BB54: 13990-000 | BC54: SPS | BD54: Pending | BG54: 0 | BH54: DSV UTI Air & Sea Agenciamento de Transportes | BK54: Aptiv | BM54: Personal Estimate | BN54: Personal Estimate | BR54: 0 | BS54: Approved - ;; Approved - ;; Approved - ;; Approved - ;; Pending - | BT54: 3000 | BU54: 3000 | BV54: ; | BW54: ; | BX54: ; | BY54: BR | CA54: USD | CE54: 47315377/47315378/47315376/35578211 | CF54: 1 | CJ54: 0
A55: 44927 | B55: Internal problem - Manufacturing/ Ordering/ Purchasing/ IT | C55: 45199 | D55: Ordering Problem - Problemas com forecast causando atraso embarque fornecedor Aptiv Honduras | E55: GM | F55: 44953 | G55: Pinhal | H55: Inbound Premium | I55: 3000 | J55: 3000 | K55: =I55/$I$1 -> 0.0073430635 | L55: B2-Behind Schedule-Aptiv | M55: Normal | N55: APTIV MANUFATURA E SERVICOS DE-104991 | O55: APTIV HONDURAS HN11-765569 | P55: We had some problems with our forecasts with Aptiv Honduras that caused shipment delay. | Q55: DSV UTI Air & Sea Agenciamento de Transportes | S55: 47315376; | T55: ; | U55: ; | V55: Aptiv | W55: Premium - Productive | X55: rodrigo.perez@aptiv.com | Y55: 44957.11 | Z55: 44957.11 | AA55: SA | AB55: Closed Not Recovered | AC55: 0 | AE55: 0 | AF55: 44953 | AG55: 10010 | AH55: Q18 | AK55: Non-Recoverable | AM55: 3000 | AO55: KM 23/24 CARRETERA A OCCIDENTE ZOLI | AP55: QUIMISTAN | AQ55: 765569 | AR55: HN | AS55: NA | AT55: SB | AU55: 22101 | AV55: RODOVIA SP 342 KM 196 | AW55: ESPIRITO SANTO DO PINHAL | AX55: 104991 | AY55: BR | AZ55: SA | BA55: SP | BB55: 13990-000 | BC55: SPS | BD55: Pending | BG55: 0 | BH55: DSV UTI Air & Sea Agenciamento de Transportes | BK55: Aptiv | BM55: Personal Estimate | BN55: Personal Estimate | BR55: 0 | BS55: Approved - ;; Approved - ;; Approved - ;; Approved - ok ;; Pending - | BT55: 3000 | BU55: 3000 | BV55: ; | BW55: ; | BX55: ; | BY55: BR | CA55: USD | CE55: 35578211/47315374/47315375/47315377 | CF55: 1 | CJ55: 0
A56: 44927 | B56: P&A | C56: 45200 | D56: P&A | E56: PSA | F56: 44953 | G56: Paraisopolis | H56: Inbound Premium | I56: 56.43 | J56: 56.43 | K56: =I56/$I$1 -> 0.00013812302 | L56: OOOT-Other/Sales | M56: Normal | N56: APTIV MANUFATURA E SERVICOS DE-104120 | O56: SERENDIPITY ELECTRONICS-110404 | P56: Critical material to meet the P&A program as requested by the customer. | Q56: DHL Express SA | R56: PTA-00090265 | S56: 10756349;10774417;10820170;10820174;10820548;15346434;12147208;13842715;13960118;15317151;15324895;15364445;15470381;10774417;10820170;10820174;10820548;15346434;12147208;13842715;13960118;15317151;15324895;15364445;15470381 | T56: 2500;50;13;30;50;160;886;100;20;100;214;29;300;50;13;30;50;160;886;100;20;100;214;29;300 | U56: 5.44;0;0;0;0;0;0;0;0;0;0;0;0;0;0;0;0;0;0;0;0;0;0;0;0 | V56: Aptiv | W56: Premium - Productive | X56: marcia.p.torres@aptiv.com | Y56: 44953.45 | Z56: 44953.438 | AA56: SA | AB56: Closed Not Recovered | AC56: 0 | AE56: 0 | AF56: 44953 | AG56: 10012 | AH56: Q11 | AK56: Non-Recoverable | AM56: 5643 | AO56: 152 E MAIN ST | AP56: HUNTINGTON | AQ56: 110404 | AR56: US | AS56: NA | AT56: NY | AU56: 11743-2958 | AV56: AVENIDA AVELINO RIBEIRO, 900 | AW56: PARAISOPOLIS | AX56: 104120 | AY56: BR | AZ56: SA | BA56: MG | BB56: 37660-000 | BC56: SPS | BD56: Approved | BE56: Carvalho, Eliane R | BF56: 44953.463 | BG56: 0 | BK56: Aptiv | BM56: Invoice | BO56: PSA | BP56: SERENDIPITY ELECTRONICS-110404 | BQ56: 0 Days 0 Hr 18 Min | BR56: 250 | BS56: Approved - ;; Approved - ; | BT56: 5643 | BU56: 5643 | BV56: 1;0;0;0;0;0;0;0;0;0;0;0;0;0;0;0;0;0;0;0;0;0;0;0;0 | BW56: 26x26x4;; ; ; ; ; ; ; ; ; ; ; ;; ; ; ; ; ; ; ; ; ; ; | BX56: ;; ; ; ; ; ; ; ; ; ; ; ;; ; ; ; ; ; ; ; ; ; ; | BY56: BR | BZ56: P&A | CA56: USD | CD56: Kg | CE56: Critical material to meet the P&A program as requested by the customer. | CF56: 1 | CJ56: 0
A57: 44927 | B57: Shipment delay | C57: 45203 | D57: Transportation Problem - Atraso ETA | E57: GM | F57: 44953 | G57: Pinhal | H57: Inbound Premium | I57: 77.12 | J57: 200 | K57: =I57/$I$1 -> 0.00018876569 | L57: T1-Transportation | M57: Normal | N57: APTIV MANUFATURA E SERVICOS DE-104991 | O57: LITTELFUSE, INC.-1014557 | P57: Aéreo necessário devido ao atraso de ETA do navio MSC PHOENIX. Invoice afetada : 115758782. | Q57: DHL Express SA | R57: PTA-00090266 | S57: 13815971; | T57: ; | U57: ; | V57: Aptiv | W57: Premium - Productive | X57: rodrigo.perez@aptiv.com | Y57: 44953.462 | Z57: 44958.088 | AA57: SA | AB57: Closed Not Recovered | AC57: 0 | AE57: 7712 | AF57: 44953 | AG57: 10010 | AH57: Q18 | AJ57: 7712 | AK57: Non-Recoverable | AM57: 200 | AN57: USD | AO57: 1779 BROWN ST STE A1 | AP57: EAGLE PASS | AQ57: 1014557 | AR57: US | AS57: NA | AT57: TX | AU57: 78852-5442 | AV57: RODOVIA SP 342 KM 196 | AW57: ESPIRITO SANTO DO PINHAL | AX57: 104991 | AY57: BR | AZ57: SA | BA57: SP | BB57: 13990-000 | BC57: SPS | BD57: Approved | BE57: Carvalho, Eliane R | BF57: 44953.471 | BG57: 0 | BH57: DHL Express SA | BI57: 2899757626 | BK57: Transportation | BM57: Personal Estimate | BN57: Personal Estimate | BQ57: 0 Days 0 Hr 13 Min | BR57: 250 | BS57: Approved - ;; Approved - ; | BT57: 7712 | BU57: 7712 | BV57: ; | BW57: ; | BX57: ; | BY57: BR | CA57: USD | CF57: 1 | CG57: 1 | CJ57: 0 | CO57: 5212246
A58: 44927 | B58: Internal problem - Manufacturing/ Ordering/ Purchasing/ IT | C58: 45222 | D58: Purchasing Problem - PN sem fornecedor padrao | E58: FIAT | F58: 44956 | G58: Paraisopolis | H58: Inbound Premium | I58: 52 | J58: 52 | K58: =I58/$I$1 -> 0.00012727977 | L58: E&O-E & O Sales | M58: Normal | N58: Paraisopolis-10012 | O58: HARNESS CODE LTD-114485 | P58: SPOT BUY DPP67791 - ITEM OBSOLETADO PELA MTA EM 2020 - NÃO TEM FORNECEDOR PADRAO. | Q58: DHL Express SA | R58: PTA-00090277 | S58: 10776395; | T58: ; | U58: ; | V58: Aptiv | W58: Premium - Productive | X58: william.de.siqueira@aptiv.com | Y58: 44953.071 | Z58: 44953.071 | AA58: SA | AB58: Closed Not Recovered | AC58: 0 | AE58: 0 | AF58: 44957 | AG58: 10012 | AH58: Q11 | AK58: Non-Recoverable | AM58: 52 | AO58: MLADOST 4 STR PROF ALEKSANDAR | AP58: SOFIA | AQ58: 114485 | AR58: BG | AS58: EMEA | AT58: 23 | AU58: 1715 | AV58: Av. Avelino Ribeiro, 900 | AW58: Paraisopolis | AX58: 10012 | AY58: BR | AZ58: SA | BA58: Mina | BB58: 37660-000 | BC58: SPS | BD58: Approved | BE58: Carvalho, Eliane R | BF58: 44953.074 | BG58: 0 | BK58: Aptiv | BM58: Invoice | BQ58: 0 Days 0 Hr 4 Min | BR58: 250 | BS58: Approved - ;; Approved - ; | BT58: 52 | BU58: 52 | BV58: ; | BW58: ; | BX58: ; | BY58: BR | CA58: USD | CF58: 1 | CJ58: 0
A59: 44927 | B59: Project | C59: 45583 | D59: Projeto | E59: FIAT | F59: 44956 | G59: Paraisopolis | H59: Inbound Premium | I59: 97 | J59: 97 | K59: =I59/$I$1 -> 0.00023742572 | L59: E1P-Prototypes/Samples | M59: Normal | N59: Paraisopolis-10012 | O59: DELFINGEN DE-HASSFURT GMBH-1085272 | P59: Parts for sales from protoypes pieces. Freigth included in the piece price. | Q59: DHL Express SA | R59: PTA-00090740 | S59: DPP67176 ; | T59: ; | U59: ; | V59: Aptiv | W59: Premium - Productive | X59: rayzza.peres@aptiv.com | Y59: 44956.489 | Z59: 44956.146 | AA59: SA | AB59: Closed Not Recovered | AC59: 0 | AE59: 97 | AG59: 10012 | AH59: Q11 | AJ59: 97 | AK59: Recoverable | AM59: 97 | AN59: USD | AO59: PHILIPP-REIS-STR. 18 | AP59: HASSFURT | AQ59: 1085272 | AR59: DE | AS59: EMEA | AT59: BY | AU59: 97437 | AV59: Av. Avelino Ribeiro, 900 | AW59: Paraisopolis | AX59: 10012 | AY59: BR | AZ59: SA | BA59: Mina | BB59: 37660-000 | BC59: SPS | BD59: Approved | BE59: Carvalho, Eliane R | BF59: 44956.042 | BG59: 0 | BH59: DHL Express SA | BI59: 4165316923 | BK59: Aptiv | BM59: Invoice | BN59: Invoice | BQ59: 0 Days 1 Hr 16 Min | BR59: 250 | BS59: Approved - ;; Approved - ; | BT59: 97 | BU59: 97 | BV59: ; | BW59: ; | BX59: ; | BY59: BR | BZ59: GSE T3/T4 + SOMDA LAMBDA | CA59: USD | CE59: DPP67176 | CF59: 1 | CG59: 1 | CJ59: 0 | CO59: 505882451
A60: 44927 | B60: Customer reschedule | C60: 45601 | D60: Customer Reschedule - JD Consulta 03: JD SJ42831 E SJ42869 | E60: JOHN DEERE | F60: 44957 | G60: Paraisopolis | H60: Inbound Premium | I60: 130 | J60: 130 | K60: =I60/$I$1 -> 0.00031819942 | L60: C4-Capacity-External Customer Resp | M60: Cost Recovery Pending | N60: Paraisopolis-10012 | O60: APTIV SERVICES DEUTSCHLAND-764011 | P60: Reprograma Jd - Consulta Aprovada pelo cliente. (Consulta 03: JD SJ42831 E SJ42869) | Q60: DHL Express SA | R60: PTA-00090753 | S60: 15344866; | T60: ; | U60: ; | V60: Customer | W60: Premium - Productive | X60: william.de.siqueira@aptiv.com | Y60: 44956.077 | Z60: 44956.077 | AA60: SA | AB60: Open | AC60: 0 | AE60: 0 | AF60: 44959 | AG60: 10012 | AH60: Q11 | AK60: Recoverable | AM60: 130 | AO60: MUNCHENER RING 1 | AP60: NEUMARKT | AQ60: 764011 | AR60: DE | AS60: EMEA | AT60: DE | AU60: 92318 | AV60: Av. Avelino Ribeiro, 900 | AW60: Paraisopolis | AX60: 10012 | AY60: BR | AZ60: SA | BA60: Mina | BB60: 37660-000 | BC60: SPS | BD60: Approved | BE60: Carvalho, Eliane R | BF60: 44956.105 | BG60: 0 | BK60: Customer | BM60: Invoice | BO60: JOHN DEERE | BQ60: 0 Days 0 Hr 40 Min | BR60: 250 | BS60: Approved - ;; Approved - ; | BT60: 130 | BU60: 130 | BV60: ; | BW60: ; | BX60: ; | BY60: BR | CA60: USD | CF60: 1 | CJ60: 0
A61: 44927 | B61: Project | C61: 46027 | D61: Projeto | E61: OTHER | F61: 44957 | G61: Paraisopolis | H61: Inbound Premium | I61: 57 | J61: 57 | K61: =I61/$I$1 -> 0.00013951821 | L61: E1P-Prototypes/Samples | M61: Cost Recovery | N61: Paraisopolis-10012 | O61: AMERICAN CABLE COMPANY-1008589 | P61: Parts for project development. Freight will be absorbed at the SC 126-22 quotation. | Q61: DHL Express SA | R61: PTA-00091035 | S61: 33368145 ; | T61: ; | U61: ; | V61: Aptiv | W61: Premium - Productive | X61: rayzza.peres@aptiv.com | Y61: 44957.071 | Z61: 44957.071 | AA61: SA | AB61: Closed Recovered | AC61: 0 | AE61: 57 | AG61: 10012 | AH61: Q11 | AJ61: 57 | AK61: Recoverable | AM61: 57 | AN61: USD | AO61: 1200 E ERIE AVE | AP61: PHILADELPHIA | AQ61: 1008589 | AR61: US | AS61: NA | AT61: PA | AU61: 19124-5526 | AV61: Av. Avelino Ribeiro, 900 | AW61: Paraisopolis | AX61: 10012 | AY61: BR | AZ61: SA | BA61: Mina | BB61: 37660-000 | BC61: SPS | BD61: Approved | BE61: Carvalho, Eliane R | BF61: 44957.073 | BG61: 0 | BK61: Aptiv | BM61: Invoice | BN61: Invoice | BQ61: 0 Days 0 Hr 3 Min | BR61: 250 | BS61: Approved - ;; Approved - ; | BT61: 57 | BU61: 57 | BV61: ; | BW61: ; | BX61: ; | BY61: BR | BZ61: TB15 - CNH | CA61: USD | CE61: Atender SOP do projeto | CF61: 1 | CG61: 1 | CJ61: 0 | CO61: 76951458
A62: 44927 | B62: Shipment delay | C62: 46205 | D62: Transportation Problem - Atraso ETA | E62: GM | F62: 44963 | G62: Ouros | H62: Inbound Premium | I62: 1751.45 | J62: 1751.45 | K62: =I62/$I$1 -> 0.0042870029 | L62: T1-Transportation | M62: Normal | N62: APTIV MANUFATURA E SERVICOS DE-104120 | O62: Aptiv Shanghai 2208-2208 | P62: Delay of vessel of one month due transbord of cargo in Sigapore | Q62: DHL Express SA | S62: 13990581; | T62: ; | U62: ; | V62: Aptiv | W62: Premium - Productive | X62: Moraes.Arnaldo@aptiv.com | Y62: 44957.328 | Z62: 44957.328 | AA62: SA | AB62: Closed Not Recovered | AC62: 0 | AE62: 0 | AG62: 10023 | AH62: Q11 | AK62: Non-Recoverable | AM62: 175145 | AO62: No. 200 Yuanguo Rd. | AP62: Shanghai | AQ62: 2208 | AR62: CN | AS62: AP | AT62: Shan | AU62: 201814 | AV62: AVENIDA AVELINO RIBEIRO, 900 | AW62: PARAISOPOLIS | AX62: 104120 | AY62: BR | AZ62: SA | BA62: MG | BB62: 37660-000 | BC62: SPS | BD62: Pending | BG62: 0 | BK62: Transportation | BM62: Invoice | BR62: 0 | BS62: Approved - ;; Approved - ;; Approved - ;; Approved - ok ;; Pending - | BT62: 175145 | BU62: 175145 | BV62: ; | BW62: ; | BX62: ; | BY62: BR | CA62: USD | CE62: 13968446-13956259-13990569-13990573-15533696-13990584-13955069 | CF62: 1 | CJ62: 0
A63: 44927 | B63: Shipment delay | C63: 46207 | D63: Transportation Problem - Atraso ETA | E63: GM | F63: 44963 | G63: Ouros | H63: Inbound Premium | I63: 525.91 | J63: 525.91 | K63: =I63/$I$1 -> 0.0012872635 | L63: T1-Transportation | M63: Normal | N63: APTIV MANUFATURA E SERVICOS DE-109304 | O63: APTIV CONNECTION SYSTEMS (NANTONG)-109707 | P63: Delay of vessel of one month due transbord of cargo in Sigapore | Q63: DHL Express SA | R63: PTA-00091352 | S63: 35524876; | T63: ; | U63: ; | V63: Aptiv | W63: Premium - Productive | X63: Moraes.Arnaldo@aptiv.com | Y63: 44957.341 | Z63: 44957.341 | AA63: SA | AB63: Closed Not Recovered | AC63: 0 | AE63: 0 | AG63: 10023 | AH63: Q11 | AK63: Non-Recoverable | AM63: 52591 | AO63: NO. 9 HEBIN ROAD, TONGZHOU ECONOMIC | AP63: TONGZHOU | AQ63: 109707 | AR63: CN | AS63: AP | AT63: 100 | AU63: 226300 | AV63: TV ANTONIO E FONSECA 250 BAIRRO | AW63: CONCEICAO DOS OUROS | AX63: 109304 | AY63: BR | AZ63: SA | BA63: MG | BB63: 37548-000 | BC63: SPS | BD63: Approved | BE63: Naus, Angelica | BF63: 44958.174 | BG63: 0 | BK63: Transportation | BM63: Invoice | BQ63: 0 Days 19 Hr 59 Min | BR63: 800 | BS63: Approved - ;; Approved - ;; Approved - ;; Approved - ; | BT63: 52591 | BU63: 52591 | BV63: ; | BW63: ; | BX63: ; | BY63: BR | CA63: USD | CF63: 1 | CJ63: 0
A64: 44927 | B64: P&A | C64: 46405 | D64: P&A | E64: VW | F64: 44958 | G64: Paraisopolis | H64: Inbound Premium | I64: 53.54 | J64: 53.54 | K64: =I64/$I$1 -> 0.00013104921 | L64: OOOT-Other/Sales | M64: Normal | N64: APTIV MANUFATURA E SERVICOS DE-104120 | O64: SERENDIPITY ELECTRONICS-110404 | P64: Critical material to meet the P&A program as requested by the customer. | Q64: DHL Express SA | R64: PTA-00091312 | S64: 12198184; | T64: 2500; | U64: 4.54; | V64: Aptiv | W64: Premium - Productive | X64: marcia.p.torres@aptiv.com | Y64: 44958.44 | Z64: 44958.433 | AA64: SA | AB64: Closed Not Recovered | AC64: 0 | AE64: 0 | AF64: 44958 | AG64: 10012 | AH64: Q11 | AK64: Non-Recoverable | AM64: 5354 | AN64: USD | AO64: 152 E MAIN ST | AP64: HUNTINGTON | AQ64: 110404 | AR64: US | AS64: NA | AT64: NY | AU64: 11743-2958 | AV64: AVENIDA AVELINO RIBEIRO, 900 | AW64: PARAISOPOLIS | AX64: 104120 | AY64: BR | AZ64: SA | BA64: MG | BB64: 37660-000 | BC64: SPS | BD64: Approved | BE64: Carvalho, Eliane R | BF64: 44958.486 | BG64: 0 | BI64: 3539793773 | BK64: Aptiv | BM64: Invoice | BO64: VW | BP64: SERENDIPITY ELECTRONICS-110404 | BQ64: 0 Days 1 Hr 5 Min | BR64: 250 | BS64: Approved - ;; Approved - ; | BT64: 5354 | BU64: 5354 | BV64: ; | BW64: 26x5x31; | BX64: ; | BY64: BR | BZ64: P&A | CA64: USD | CD64: Kg | CE64: Critical material to meet the P&A program as requested by the customer. | CF64: 1 | CG64: 1 | CJ64: 0
A65: 44958 | B65: Shipment delay | C65: 46407 | D65: Transportation Problem - Atraso ETA | E65: GM | F65: 44959 | G65: Pinhal | H65: Inbound Premium | I65: 410.71 | J65: 410.71 | K65: =I65/$I$1 -> 0.0010052899 | L65: PC-Plant PC Resp | M65: Normal | N65: APTIV MANUFATURA E SERVICOS DE DIST-1039282 | O65: Empresa de Transportes Covre-Dummy | P65: Entrega Emergencial da Pasta M1037/22, para evitar parada de linha GM. | Q65: EMPRESA DE TRANSPORTES COVRE | R65: PTA-00091334 | S65: 47315374; | T65: ; | U65: ; | V65: Aptiv | W65: Premium - Productive | X65: rodrigo.perez@aptiv.com | Y65: 44958.488 | Z65: 44958.214 | AA65: SA | AB65: Closed Not Recovered | AC65: 0 | AE65: 41071 | AF65: 44958 | AG65: 10010 | AH65: Q18 | AJ65: 41071 | AK65: Non-Recoverable | AM65: 41071 | AN65: USD | AO65: R. Hercílio Camargo Barbosa, 207 | AP65: Santos | AQ65: Dummy | AR65: BR | AS65: SA | AT65: Sao Paulo | AU65: 11095-590 | AV65: RUA JOSE MONFARDINI 3845 | AW65: ESPIRITO SANTO DO PINHAL | AX65: 1039282 | AY65: BR | AZ65: SA | BA65: SP | BB65: 13990-000 | BC65: SPS | BD65: Approved | BE65: Edilson, Geraldo | BF65: 44958.136 | BG65: 0 | BH65: EMPRESA DE TRANSPORTES COVRE | BI65: EMERGENCIAL | BK65: Aptiv | BM65: Personal Estimate | BN65: Personal Estimate | BQ65: 0 Days 3 Hr 32 Min | BR65: 500 | BS65: Approved - ;; Approved - ;; Approved - ; | BT65: 41071 | BU65: 41071 | BV65: ; | BW65: ; | BX65: ; | BY65: BR | CA65: USD | CF65: 1 | CG65: 1 | CJ65: 0
A66: 44958 | B66: P&A | C66: 46713 | D66: P&A | E66: DAIMLER | F66: 44959 | G66: Paraisopolis | H66: Inbound Premium | I66: 47.25 | J66: 47.25 | K66: =I66/$I$1 -> 0.00011565325 | L66: OOOT-Other/Sales | M66: Normal | N66: APTIV MANUFATURA E SERVICOS DE-104120 | O66: APTIV TURKEY TEKNOLOJI HIZMETL-1051994 | P66: Critical material to meet the P&A program as requested by the customer. | Q66: DHL Express SA | R66: PTA-00091543 | S66: 15470493; | T66: 120; | U66: 0.60; | V66: Aptiv | W66: Premium - Productive | X66: marcia.p.torres@aptiv.com | Y66: 44959.449 | Z66: 44959.439 | AA66: SA | AB66: Closed Not Recovered | AC66: 0 | AE66: 0 | AF66: 44959 | AG66: 10012 | AH66: Q11 | AK66: Non-Recoverable | AM66: 4725 | AN66: USD | AO66: HASANAGA MH. 12. CD. NO8/1 | AP66: NILUEFER/BURSA | AQ66: 1051994 | AR66: TR | AS66: EMEA | AT66: 16 | AU66: 16280 | AV66: AVENIDA AVELINO RIBEIRO, 900 | AW66: PARAISOPOLIS | AX66: 104120 | AY66: BR | AZ66: SA | BA66: MG | BB66: 37660-000 | BC66: SPS | BD66: Approved | BE66: Carvalho, Eliane R | BF66: 44959.114 | BG66: 0 | BK66: Aptiv | BM66: Invoice | BO66: DAIMLER | BQ66: 0 Days 3 Hr 57 Min | BR66: 250 | BS66: Approved - ;; Approved - ; | BT66: 4725 | BU66: 4725 | BV66: 1; | BW66: 19x22x16; | BX66: ; | BY66: BR | BZ66: P&A | CA66: USD | CD66: Kg | CE66: Critical material to meet the P&A program as requested by the customer. | CF66: 1 | CG66: 1 | CJ66: 0
A67: 44958 | B67: Shipment delay | C67: 46793 | D67: Transportation Problem - Atraso ETA | E67: GM | F67: 44960 | G67: Pinhal | H67: Inbound Premium | I67: 592.49 | J67: 585.06 | K67: =I67/$I$1 -> 0.0014502306 | L67: T1-Transportation | M67: Normal | N67: APTIV MANUFATURA E SERVICOS DE-104991 | O67: J.S.T. CORPORATION-1003317 | P67: Aéreo necessário devido ao atraso do HBL DET206167199. Invoices afetadas : 739741 / 740060 e 740489. | Q67: DHL Express SA | R67: PTA-00091634 | S67: 35028910; | T67: ; | U67: ; | V67: Aptiv | W67: Premium - Productive | X67: rodrigo.perez@aptiv.com | Y67: 44959.161 | Z67: 44986.245 | AA67: SA | AB67: Closed Not Recovered | AC67: 0 | AE67: 59249 | AF67: 44959 | AG67: 10010 | AH67: Q18 | AJ67: 59249 | AK67: Non-Recoverable | AM67: 58506 | AN67: USD | AO67: 1957 S LAKESIDE DR | AP67: WAUKEGAN | AQ67: 1003317 | AR67: US | AS67: NA | AT67: IL | AU67: 60085-8331 | AV67: RODOVIA SP 342 KM 196 | AW67: ESPIRITO SANTO DO PINHAL | AX67: 104991 | AY67: BR | AZ67: SA | BA67: SP | BB67: 13990-000 | BC67: SPS | BD67: Approved | BE67: Naus, Angelica | BF67: 44959.287 | BG67: 0 | BI67: 7116106406 | BK67: Transportation | BM67: Personal Estimate | BN67: Personal Estimate | BQ67: 0 Days 3 Hr 0 Min | BR67: 800 | BS67: Approved - ;; Approved - ;; Approved - ;; Approved - ok ; | BT67: 59249 | BU67: 59249 | BV67: ; | BW67: ; | BX67: ; | BY67: BR | CA67: USD | CE67: 13588505/13595476/35120496 | CF67: 1 | CG67: 1 | CJ67: 0
A68: 44958 | B68: Shipment delay | C68: 46966 | D68: Transportation Problem - Atraso ETA - Vessel Hella | E68: GM | F68: 44960 | G68: Pinhal | H68: Inbound Premium | I68: 686.14 | J68: 711.08 | K68: =I68/$I$1 -> 0.0016794565 | L68: T1-Transportation | M68: Normal | N68: APTIV MANUFATURA E SERVICOS DE-104991 | O68: APTIV HONDURAS HN11-765569 | P68: Tivemos problemas com atraso do embarque dos EUA, HBL DET206167199, Navio atual HELLA. Invoices Afetadas : 10823252/10831638/10756535/10795315/10760175. | Q68: DHL Express SA | R68: PTA-00091784 | S68: 47314246; | T68: ; | U68: ; | V68: Aptiv | W68: Premium - Productive | X68: rodrigo.perez@aptiv.com | Y68: 44960.434 | Z68: 44986.245 | AA68: SA | AB68: Closed Not Recovered | AC68: 0 | AE68: 68614 | AF68: 44960 | AG68: 10010 | AH68: Q18 | AJ68: 68614 | AK68: Non-Recoverable | AM68: 71108 | AN68: USD | AO68: KM 23/24 CARRETERA A OCCIDENTE ZOLI | AP68: QUIMISTAN | AQ68: 765569 | AR68: HN | AS68: NA | AT68: SB | AU68: 22101 | AV68: RODOVIA SP 342 KM 196 | AW68: ESPIRITO SANTO DO PINHAL | AX68: 104991 | AY68: BR | AZ68: SA | BA68: SP | BB68: 13990-000 | BC68: SPS | BD68: Approved | BE68: Naus, Angelica | BF68: 44960.162 | BG68: 0 | BH68: DHL Express SA | BI68: 2136407464 | BK68: Transportation | BM68: Personal Estimate | BN68: Personal Estimate | BQ68: 0 Days 5 Hr 27 Min | BR68: 800 | BS68: Approved - ;; Approved - ;; Approved - ;; Approved - ok ; | BT68: 68614 | BU68: 68614 | BV68: ; | BW68: ; | BX68: ; | BY68: BR | CA68: USD | CE68: 47315374/47315376 | CF68: 1 | CG68: 1 | CJ68: 0
A69: 44958 | B69: Stock discrepancy | C69: 46980 | D69: Stock Discrepancy | E69: JOHN DEERE | F69: 44963 | G69: Paraisopolis | H69: Inbound Premium | I69: 84.26 | J69: 118.17 | K69: =I69/$I$1 -> 0.00020624218 | L69: S1I-Inventory loss/adjustments | M69: Normal | N69: Paraisopolis-10012 | O69: SERENDIPITY ELECTRONICS-749804 | P69: DIVERGENCIA DE ESTOQUE (900 PÇS - 4 SEMANAS DE MATERIAL) | Q69: DHL Express SA | R69: PTA-00091749 | S69: 15422718; | T69: ; | U69: ; | V69: Aptiv | W69: Premium - Productive | X69: william.de.siqueira@aptiv.com | Y69: 44960.489 | Z69: 44965.264 | AA69: SA | AB69: Closed Not Recovered | AC69: 0 | AE69: 8426 | AF69: 44967 | AG69: 10012 | AH69: Q11 | AJ69: 8426 | AK69: Non-Recoverable | AM69: 11817 | AN69: USD | AO69: 152 E MAIN ST | AP69: HUNTINGTON | AQ69: 749804 | AR69: US | AS69: NA | AT69: NY | AU69: 11743-2958 | AV69: Av. Avelino Ribeiro, 900 | AW69: Paraisopolis | AX69: 10012 | AY69: BR | AZ69: SA | BA69: Mina | BB69: 37660-000 | BC69: SPS | BD69: Approved | BE69: Carvalho, Eliane R | BF69: 44960.517 | BG69: 0 | BI69: 2136072131 | BK69: Aptiv | BM69: Invoice | BN69: Invoice | BQ69: 0 Days 0 Hr 40 Min | BR69: 250 | BS69: Approved - ;; Approved - ; | BT69: 8426 | BU69: 8426 | BV69: ; | BW69: ; | BX69: ; | BY69: BR | CA69: USD | CF69: 1 | CG69: 1 | CJ69: 0
A70: 44958 | B70: Shipment delay | C70: 47115 | D70: Transportation Problem - Atraso ETA | E70: GM | F70: 44963 | G70: Paraisopolis | H70: Inbound Premium | I70: 451.18 | J70: 210 | K70: =I70/$I$1 -> 0.0011043478 | L70: T1-Transportation | M70: Normal | N70: APTIV MANUFATURA E SERVICOS DE-104120 | O70: APTIV PLANT FR47-725460 | P70: Material não recebido fisicamente (zimport) | Q70: DHL Express SA | R70: PTA-00091824 | S70: 13928634; | T70: ; | U70: ; | V70: Aptiv | W70: Premium - Productive | X70: Moraes.Arnaldo@aptiv.com | Y70: 44960.289 | Z70: 44973.25 | AA70: SA | AB70: Closed Not Recovered | AC70: 0 | AE70: 45118 | AG70: 10012 | AH70: Q11 | AJ70: 45118 | AK70: Non-Recoverable | AM70: 210 | AN70: USD | AO70: 3400 AERO PARK DR | AP70: VIENNA | AQ70: 725460 | AR70: US | AS70: NA | AT70: OH | AU70: 44473-8704 | AV70: AVENIDA AVELINO RIBEIRO, 900 | AW70: PARAISOPOLIS | AX70: 104120 | AY70: BR | AZ70: SA | BA70: MG | BB70: 37660-000 | BC70: SPS | BD70: Approved | BE70: Carvalho, Eliane R | BF70: 44960.308 | BG70: 0 | BH70: DHL Express SA | BI70: 8527200485 | BK70: Transportation | BM70: Invoice | BN70: Invoice | BQ70: 0 Days 0 Hr 26 Min | BR70: 250 | BS70: Approved - ;; Approved - ; | BT70: 45118 | BU70: 45118 | BV70: ; | BW70: ; | BX70: ; | BY70: BR | CA70: USD | CE70: 15448130-13950776 | CF70: 1 | CG70: 1 | CJ70: 0
A71: 44958 | B71: Shipment delay | C71: 47350 | D71: Transportation Problem - Atraso ETA | E71: TOYOTA | F71: 44963 | G71: Paraisopolis | H71: Inbound Premium | I71: 120 | J71: 120 | K71: =I71/$I$1 -> 0.00029372254 | L71: T1-Transportation | M71: Normal | N71: APTIV MANUFATURA E SERVICOS DE-104120 | O71: JST CORPORATION-7059485 | P71: Carga com atraso de embarque na Penske devido a falta de documentação (em avaliação de quem está errado Penske X fornecedor) | Q71: DHL Express SA | R71: PTA-00092234 | S71: 13533032; | T71: ; | U71: ; | V71: Aptiv | W71: Premium - Productive | X71: jorge.luis.almeida@aptiv.com | Y71: 44963.34 | Z71: 44963.34 | AA71: SA | AB71: Closed Not Recovered | AC71: 0 | AE71: 0 | AG71: 10012 | AH71: Q11 | AK71: Non-Recoverable | AM71: 120 | AO71: 11101 METRO AIRPORT CENTER DR 100 | AP71: ROMULUS | AQ71: 7059485 | AR71: US | AS71: NA | AT71: MI | AU71: 48174-1694 | AV71: AVENIDA AVELINO RIBEIRO, 900 | AW71: PARAISOPOLIS | AX71: 104120 | AY71: BR | AZ71: SA | BA71: MG | BB71: 37660-000 | BC71: SPS | BD71: Approved | BE71: Carvalho, Eliane R | BF71: 44963.393 | BG71: 0 | BK71: Transportation | BM71: Invoice | BQ71: 0 Days 1 Hr 16 Min | BR71: 250 | BS71: Approved - ;; Approved - ; | BT71: 120 | BU71: 120 | BV71: ; | BW71: ; | BX71: ; | BY71: BR | BZ71: 740 - floor | CA71: USD | CE71: Carga com atraso de embarque na Penske devido a falta de documentação (em avaliação de quem está errado Penske X fornecedor) | CF71: 1 | CJ71: 0
A72: 44958 | B72: P&A | C72: 47470 | D72: P&A | E72: PSA | F72: 44964 | G72: Paraisopolis | H72: Inbound Premium | I72: 58.39 | J72: 58.39 | K72: =I72/$I$1 -> 0.00014292049 | L72: OOOT-Other/Sales | M72: Normal | N72: APTIV MANUFATURA E SERVICOS DE-104120 | O72: SERENDIPITY ELECTRONICS-110404 | P72: Critical material to meet the P&A program as requested by the customer. | Q72: DHL Express SA | R72: PTA-00092277 | S72: 10768692-13934567; | T72: 220-200; | U72: 5.89; | V72: Aptiv | W72: Premium - Productive | X72: marcia.p.torres@aptiv.com | Y72: 44964.442 | Z72: 44964.439 | AA72: SA | AB72: Closed Not Recovered | AC72: 0 | AE72: 0 | AF72: 44964 | AG72: 10012 | AH72: Q11 | AK72: Non-Recoverable | AM72: 5839 | AO72: 152 E MAIN ST | AP72: HUNTINGTON | AQ72: 110404 | AR72: US | AS72: NA | AT72: NY | AU72: 11743-2958 | AV72: AVENIDA AVELINO RIBEIRO, 900 | AW72: PARAISOPOLIS | AX72: 104120 | AY72: BR | AZ72: SA | BA72: MG | BB72: 37660-000 | BC72: SPS | BD72: Approved | BE72: Carvalho, Eliane R | BF72: 44964.482 | BG72: 0 | BK72: Aptiv | BM72: Invoice | BO72: PSA | BP72: SERENDIPITY ELECTRONICS-110404 | BQ72: 0 Days 0 Hr 58 Min | BR72: 250 | BS72: Approved - ;; Approved - ; | BT72: 5839 | BU72: 5839 | BV72: ; | BW72: 16x12x12; | BX72: ; | BY72: BR | BZ72: P&A | CA72: USD | CD72: Kg | CE72: Critical material to meet the P&A program as requested by the customer. | CF72: 1 | CJ72: 0
A73: 44958 | B73: Shipment delay | C73: 47505 | D73: Transportation Problem - Atraso ETA - Vessel Hella | E73: GM | F73: 44965 | G73: Pinhal | H73: Inbound Premium | I73: 627.15 | J73: 616 | K73: =I73/$I$1 -> 0.0015350674 | L73: T1-Transportation | M73: Normal | N73: APTIV MANUFATURA E SERVICOS DE-104991 | O73: TYZ ALL PLASTICS, INC-7003611 | P73: Aéreo necessário devido ao atraso de dois navios. Primeiro atraso no Navio Hella, segundo atraso Navio MSC Alessia. | Q73: DHL Express SA | R73: PTA-00092317 | S73: 13600893; | T73: ; | U73: 88.00; | V73: Aptiv | W73: Premium - Productive | X73: rodrigo.perez@aptiv.com | Y73: 44964.114 | Z73: 44986.245 | AA73: SA | AB73: Closed Not Recovered | AC73: 0 | AE73: 62715 | AF73: 44964 | AG73: 10010 | AH73: Q18 | AJ73: 62715 | AK73: Non-Recoverable | AM73: 616 | AN73: USD | AO73: 120 EXPRESS ST STE 1 | AP73: PLAINVIEW | AQ73: 7003611 | AR73: US | AS73: NA | AT73: NY | AU73: 11803 | AV73: RODOVIA SP 342 KM 196 | AW73: ESPIRITO SANTO DO PINHAL | AX73: 104991 | AY73: BR | AZ73: SA | BA73: SP | BB73: 13990-000 | BC73: SPS | BD73: Approved | BE73: Naus, Angelica | BF73: 44964.194 | BG73: 0 | BI73: 8088025083 | BK73: Transportation | BM73: Personal Estimate | BN73: Personal Estimate | BQ73: 0 Days 1 Hr 55 Min | BR73: 800 | BS73: Approved - ;; Approved - ;; Approved - ;; Approved - ok ; | BT73: 62715 | BU73: 62715 | BV73: ; | BW73: ; | BX73: ; | BY73: BR | CA73: USD | CD73: Kg | CF73: 1 | CG73: 1 | CJ73: 0
A74: 44958 | B74: Shipment delay | C74: 47509 | D74: Transportation Problem - Atraso ETA - Vessel Hella | E74: GM | F74: 44965 | G74: Pinhal | H74: Inbound Premium | I74: 343.38 | J74: 313 | K74: =I74/$I$1 -> 0.00084048705 | L74: T1-Transportation | M74: Normal | N74: APTIV MANUFATURA E SERVICOS DE-104991 | O74: AVERY DENNISON CORP-749603 | P74: Aéreo necessário devido ao atraso de dois navios. Primeiro atraso no Navio Hella, segundo atraso Navio MSC Alessia. | Q74: DHL Express SA | R74: PTA-00092316 | S74: 13617456; | T74: ; | U74: ; | V74: Aptiv | W74: Premium - Productive | X74: rodrigo.perez@aptiv.com | Y74: 44964.121 | Z74: 44986.246 | AA74: SA | AB74: Closed Not Recovered | AC74: 0 | AE74: 34338 | AF74: 44964 | AG74: 10010 | AH74: Q18 | AJ74: 34338 | AK74: Non-Recoverable | AM74: 313 | AN74: USD | AO74: 224 INDUSTRIAL RD | AP74: FITCHBURG | AQ74: 749603 | AR74: US | AS74: NA | AT74: MA | AU74: 01420-4634 | AV74: RODOVIA SP 342 KM 196 | AW74: ESPIRITO SANTO DO PINHAL | AX74: 104991 | AY74: BR | AZ74: SA | BA74: SP | BB74: 13990-000 | BC74: SPS | BD74: Approved | BE74: Edilson, Geraldo | BF74: 44964.18 | BG74: 0 | BI74: 5116281951 | BK74: Transportation | BM74: Personal Estimate | BN74: Personal Estimate | BQ74: 0 Days 1 Hr 24 Min | BR74: 500 | BS74: Approved - ;; Approved - ;; Approved - ; | BT74: 34338 | BU74: 34338 | BV74: ; | BW74: ; | BX74: ; | BY74: BR | CA74: USD | CF74: 1 | CG74: 1 | CJ74: 0
A75: 44958 | B75: Shipment delay | C75: 47514 | D75: Transportation Problem - Atraso ETA - Vessel Hella | E75: GM | F75: 44966 | G75: Pinhal | H75: Inbound Premium | I75: 3334.04 | J75: 1500 | K75: =I75/$I$1 -> 0.0081606891 | L75: T1-Transportation | M75: Normal | N75: APTIV MANUFATURA E SERVICOS DE-104991 | O75: APTIV HONDURAS HN11-765569 | P75: Air Freight needed due the delay of two shipments. Fist one in the HELLA and the second one in MSC Alessia. Several Invoices affected. | Q75: DHL Express SA | R75: PTA-00092597 | S75: 47315378; | T75: ; | U75: ; | V75: Aptiv | W75: Premium - Productive | X75: rodrigo.perez@aptiv.com | Y75: 44964.124 | Z75: 44970.439 | AA75: SA | AB75: Closed Not Recovered | AC75: 0 | AE75: 333404 | AF75: 44964 | AG75: 10010 | AH75: Q18 | AJ75: 333404 | AK75: Non-Recoverable | AM75: 1500 | AN75: USD | AO75: KM 23/24 CARRETERA A OCCIDENTE ZOLI | AP75: QUIMISTAN | AQ75: 765569 | AR75: HN | AS75: NA | AT75: SB | AU75: 22101 | AV75: RODOVIA SP 342 KM 196 | AW75: ESPIRITO SANTO DO PINHAL | AX75: 104991 | AY75: BR | AZ75: SA | BA75: SP | BB75: 13990-000 | BC75: SPS | BD75: Approved | BE75: Garcia Puente, Jorge | BF75: 44965.26 | BG75: 0 | BH75: DSV UTI Air & Sea Agenciamento de Transportes | BI75: SAP501006967 | BK75: Transportation | BM75: Personal Estimate | BN75: Personal Estimate | BQ75: 1 Days 3 Hr 16 Min | BR75: 5000 | BS75: Approved - ;; Approved - ;; Approved - ;; Approved - ;; Approved - ;; Approved - ; | BT75: 333404 | BU75: 333404 | BV75: ; | BW75: ; | BX75: ; | BY75: BR | CA75: USD | CE75: 47315377/47315375/47314246 | CF75: 1 | CG75: 1 | CJ75: 0
A76: 44958 | B76: Shipment delay | C76: 47528 | D76: Transportation Problem - Atraso ETA - Vessel Hella | E76: GM | F76: 44965 | G76: Pinhal | H76: Inbound Premium | I76: 103.16 | J76: 146 | K76: =I76/$I$1 -> 0.00025250348 | L76: T1-Transportation | M76: Normal | N76: APTIV MANUFATURA E SERVICOS DE-104991 | O76: HAMLIN / LITTELFUSE-104227 | P76: Aéreo necessário devido ao atraso de dois navios. Primeiro atraso no Navio Hella, segundo atraso Navio MSC Alessia. | Q76: DHL Express SA | R76: PTA-00092331 | S76: 13815974; | T76: ; | U76: ; | V76: Aptiv | W76: Premium - Productive | X76: rodrigo.perez@aptiv.com | Y76: 44964.163 | Z76: 44986.254 | AA76: SA | AB76: Closed Not Recovered | AC76: 0 | AE76: 10316 | AF76: 44964 | AG76: 10010 | AH76: Q18 | AJ76: 10316 | AK76: Non-Recoverable | AM76: 146 | AN76: USD | AO76: 612 E LAKE ST | AP76: LAKE MILLS | AQ76: 104227 | AR76: US | AS76: NA | AT76: WI | AU76: 53551-1737 | AV76: RODOVIA SP 342 KM 196 | AW76: ESPIRITO SANTO DO PINHAL | AX76: 104991 | AY76: BR | AZ76: SA | BA76: SP | BB76: 13990-000 | BC76: SPS | BD76: Approved | BE76: Carvalho, Eliane R | BF76: 44964.242 | BG76: 0 | BI76: 1727003305 | BK76: Transportation | BM76: Personal Estimate | BN76: Personal Estimate | BQ76: 0 Days 1 Hr 53 Min | BR76: 250 | BS76: Approved - ;; Approved - ; | BT76: 10316 | BU76: 10316 | BV76: ; | BW76: ; | BX76: ; | BY76: BR | CA76: USD | CE76: 33324974 | CF76: 1 | CG76: 1 | CJ76: 0
A77: 44958 | B77: Shipment delay | C77: 47594 | D77: Transportation Problem - Atraso ETA - Vessel Hella | E77: GM | F77: 44966 | G77: Pinhal | H77: Inbound Premium | I77: 2309.81 | J77: 4442 | K77: =I77/$I$1 -> 0.0056536938 | L77: T1-Transportation | M77: Normal | N77: APTIV MANUFATURA E SERVICOS DE-104991 | O77: DLHBOWLES, INC.-1064198 | P77: Air Freight needed due the delay of two shipments. Fist one in the HELLA and the second one in MSC Alessia. Several Invoices affected. | Q77: DHL Express SA | R77: PTA-00092596 | S77: 35311048; | T77: ; | U77: ; | V77: Aptiv | W77: Premium - Productive | X77: rodrigo.perez@aptiv.com | Y77: 44964.285 | Z77: 44986.254 | AA77: SA | AB77: Closed Not Recovered | AC77: 0 | AE77: 230981 | AF77: 44964 | AG77: 10010 | AH77: Q18 | AJ77: 230981 | AK77: Non-Recoverable | AM77: 4442 | AN77: USD | AO77: 12114 J E F DR STE A | AP77: LAREDO | AQ77: 1064198 | AR77: US | AS77: NA | AT77: TX | AU77: 78045-1834 | AV77: RODOVIA SP 342 KM 196 | AW77: ESPIRITO SANTO DO PINHAL | AX77: 104991 | AY77: BR | AZ77: SA | BA77: SP | BB77: 13990-000 | BC77: SPS | BD77: Approved | BE77: Garcia Puente, Jorge | BF77: 44965.26 | BG77: 0 | BI77: 1374633691 | BK77: Transportation | BM77: Personal Estimate | BN77: Personal Estimate | BQ77: 0 Days 23 Hr 24 Min | BR77: 5000 | BS77: Approved - ;; Approved - ;; Approved - ;; Approved - ok ;; Approved - ;; Approved - ; | BT77: 230981 | BU77: 230981 | BV77: ; | BW77: ; | BX77: ; | BY77: BR | CA77: USD | CF77: 1 | CG77: 1 | CJ77: 0
A78: 44958 | B78: Stock discrepancy | C78: 47628 | D78: Stock Discrepancy | E78: GM | F78: 44964 | G78: Paraisopolis | H78: Inbound Premium | I78: 196.5 | J78: 196.5 | K78: =I78/$I$1 -> 0.00048097066 | L78: S1I-Inventory loss/adjustments | M78: Normal | N78: APTIV MANUFATURA E SERVICOS DE-104120 | O78: Lear Camanducaia-Dummy | P78: Stock Discrepancy | Q78: TRANSPORTADORA PITUTA | R78: PTA-00092373 | S78: 15393422; | T78: ; | U78: ; | V78: Aptiv | W78: Premium - Productive | X78: adriane.barbosa.silva@aptiv.com | Y78: 44964.36 | Z78: 44964.36 | AA78: SA | AB78: Closed Not Recovered | AC78: 0 | AE78: 0 | AG78: 10012 | AH78: Q11 | AK78: Non-Recoverable | AM78: 1002 | AO78: Camanducaia | AP78: Camanducaia | AQ78: Dummy | AR78: BR | AS78: SA | AT78: Minas Gerais | AU78: 0000 | AV78: AVENIDA AVELINO RIBEIRO, 900 | AW78: PARAISOPOLIS | AX78: 104120 | AY78: BR | AZ78: SA | BA78: MG | BB78: 37660-000 | BC78: SPS | BD78: Approved | BE78: Carvalho, Eliane R | BF78: 44964.364 | BG78: 0 | BK78: Aptiv | BM78: Invoice | BQ78: 0 Days 0 Hr 5 Min | BR78: 250 | BS78: Approved - ;; Approved - ; | BT78: 1965 | BU78: 1965 | BV78: ; | BW78: ; | BX78: ; | BY78: BR | BZ78: IP PM7 | CA78: BRL | CF78: 19610535 | CJ78: 0
A79: 44958 | B79: Project | C79: 47836 | D79: Projeto | E79: PSA | F79: 44965 | G79: Paraisopolis | H79: Inbound Premium | I79: 68 | J79: 68 | K79: =I79/$I$1 -> 0.00016644277 | L79: E1P-Prototypes/Samples | M79: Cost Recovery | N79: Paraisopolis-10012 | O79: SERENDIPITY ELECTRONICS, INC.-7074024 | P79: Parts for project development. Freight approved by email by the Project Manager. | Q79: DHL Express SA | R79: PTA-00092590 | S79: 10723772 10734652 13974320 15316617 35072405; | T79: ; | U79: ; | V79: Aptiv | W79: Premium - Productive | X79: rayzza.peres@aptiv.com | Y79: 44965.222 | Z79: 44965.222 | AA79: SA | AB79: Closed Recovered | AC79: 0 | AE79: 0 | AG79: 10012 | AH79: Q11 | AK79: Non-Recoverable | AM79: 68 | AN79: USD | AO79: 152 E MAIN ST STE D | AP79: HUNTINGTON | AQ79: 7074024 | AR79: US | AS79: NA | AT79: NY | AU79: 11743-2958 | AV79: Av. Avelino Ribeiro, 900 | AW79: Paraisopolis | AX79: 10012 | AY79: BR | AZ79: SA | BA79: Mina | BB79: 37660-000 | BC79: SPS | BD79: Approved | BE79: Carvalho, Eliane R | BF79: 44965.245 | BG79: 0 | BH79: DHL Express SA | BI79: 51 9540 4351 | BK79: Aptiv | BM79: Invoice | BN79: Invoice | BQ79: 0 Days 0 Hr 33 Min | BR79: 250 | BS79: Approved - ;; Approved - ; | BT79: 68 | BU79: 68 | BV79: ; | BW79: ; | BX79: ; | BY79: BR | BZ79: KZERO | CA79: USD | CE79: DPP67922 | CF79: 1 | CG79: 1 | CJ79: 0
A80: 44958 | B80: Stock discrepancy | C80: 48023 | D80: Stock Discrepancy | E80: JOHN DEERE | F80: 44966 | G80: Paraisopolis | H80: Inbound Premium | I80: 82.42 | J80: 0 | K80: =I80/$I$1 -> 0.00020173843 | L80: S1I-Inventory loss/adjustments | M80: Normal | N80: Paraisopolis-10012 | O80: HERMES ENGINEERING OOD-1072462 | P80: Material contado a mais no IFA. REAJUSTE DE 3 SEMANAS. | Q80: DHL Express SA | R80: PTA-00092711 | S80: 13509280; | T80: ; | U80: ; | V80: Aptiv | W80: Premium - Productive | X80: william.de.siqueira@aptiv.com | Y80: 44966.485 | Z80: 44980.214 | AA80: SA | AB80: Closed Not Recovered | AC80: 0 | AE80: 8242 | AF80: 44966 | AG80: 10012 | AH80: Q11 | AJ80: 8242 | AK80: Non-Recoverable | AM80: 6305 | AN80: USD | AO80: MUR 15 STR. | AP80: SOFIA | AQ80: 1072462 | AR80: BG | AS80: EMEA | AT80: 23 | AU80: 1680 | AV80: Av. Avelino Ribeiro, 900 | AW80: Paraisopolis | AX80: 10012 | AY80: BR | AZ80: SA | BA80: Mina | BB80: 37660-000 | BC80: SPS | BD80: Approved | BE80: Carvalho, Eliane R | BF80: 44966.073 | BG80: 0 | BI80: 1137841316 | BK80: Aptiv | BM80: Invoice | BN80: Invoice | BQ80: 0 Days 2 Hr 7 Min | BR80: 250 | BS80: Approved - ;; Approved - ; | BT80: 8242 | BU80: 8242 | BV80: ; | BW80: ; | BX80: ; | BY80: BR | CA80: USD | CF80: 1 | CG80: 1 | CJ80: 0
A81: 44958 | B81: Stock discrepancy | C81: 48025 | D81: Stock Discrepancy | E81: GM | F81: 44967 | G81: Ouros | H81: Inbound Premium | I81: 65.68 | J81: 65.68 | K81: =I81/$I$1 -> 0.00016076414 | L81: S1I-Inventory loss/adjustments | M81: Normal | N81: Paraisopolis-10012 | O81: LORENTSON MANUFACTURING CO-104298 | P81: Divergencia de floor. | Q81: DHL Express SA | R81: PTA-00092712 | S81: 15356825; | T81: ; | U81: ; | V81: Customer | W81: Premium - Productive | X81: william.de.siqueira@aptiv.com | Y81: 44966.488 | Z81: 44980.215 | AA81: SA | AB81: Closed Not Recovered | AC81: 0 | AE81: 0 | AF81: 44972 | AG81: 10023 | AH81: Q11 | AJ81: 6811 | AK81: Recoverable | AM81: 6568 | AN81: USD | AO81: PO BOX 932 | AP81: KOKOMO | AQ81: 104298 | AR81: US | AS81: NA | AT81: IN | AU81: 46903-0932 | AV81: Av. Avelino Ribeiro, 900 | AW81: Paraisopolis | AX81: 10012 | AY81: BR | AZ81: SA | BA81: Mina | BB81: 37660-000 | BC81: SPS | BD81: Approved | BE81: Carvalho, Eliane R | BF81: 44966.074 | BG81: 0 | BI81: 4303700881 | BK81: Aptiv | BM81: Invoice | BN81: Invoice | BO81: JOHN DEERE | BQ81: 0 Days 2 Hr 3 Min | BR81: 250 | BS81: Approved - ;; Approved - ; | BT81: 6568 | BU81: 6568 | BV81: ; | BW81: ; | BX81: ; | BY81: BR | CA81: USD | CF81: 1 | CG81: 1 | CJ81: 0
A82: 44958 | B82: Internal problem - Manufacturing/ Ordering/ Purchasing/ IT | C82: 48043 | D82: Ordering Problem - LT Divergence | E82: JOHN DEERE | F82: 44967 | G82: Paraisopolis | H82: Inbound Premium | I82: 65.68 | J82: 65.68 | K82: =I82/$I$1 -> 0.00016076414 | L82: L1-Lead Time Mismatch-Aptiv Resp | M82: Normal | N82: Paraisopolis-10012 | O82: SEWS COMPONENTS AND ELECTRONICS EUR-1066296 | P82: material baixo de volume e com 15 semanas de LT firme, o material foi programado dentro do LT porem o mesmo necessita de ter uma previsao com pelo menos 26 semanas. Time comercial foi envolvido e iremos alterar nosso LT para 26 semanas. | Q82: DHL Express SA | R82: PTA-00092918 | S82: 33282516; | T82: ; | U82: ; | V82: Aptiv | W82: Premium - Productive | X82: william.de.siqueira@aptiv.com | Y82: 44966.078 | Z82: 44980.218 | AA82: SA | AB82: Closed Not Recovered | AC82: 0 | AE82: 0 | AF82: 44967 | AG82: 10012 | AH82: Q11 | AJ82: 57357 | AK82: Non-Recoverable | AM82: 240 | AN82: USD | AO82: EUROPA U. 12 | AP82: BUDAPEST | AQ82: 1066296 | AR82: HU | AS82: EMEA | AT82: BU | AU82: 1239 | AV82: Av. Avelino Ribeiro, 900 | AW82: Paraisopolis | AX82: 10012 | AY82: BR | AZ82: SA | BA82: Mina | BB82: 37660-000 | BC82: SPS | BD82: Approved | BE82: Carvalho, Eliane R | BF82: 44967.071 | BG82: 0 | BI82: 7458082883 | BK82: Aptiv | BM82: Invoice | BN82: Invoice | BQ82: 0 Days 23 Hr 50 Min | BR82: 250 | BS82: Approved - ;; Approved - ; | BT82: 6568 | BU82: 6568 | BV82: ; | BW82: ; | BX82: ; | BY82: BR | CA82: USD | CF82: 1 | CG82: 1 | CJ82: 0
A83: 44958 | B83: Stock discrepancy | C83: 48079 | D83: Stock Discrepancy | E83: GM | F83: 44967 | G83: Paraisopolis | H83: Inbound Premium | I83: 90 | J83: 90 | K83: =I83/$I$1 -> 0.0002202919 | L83: S1I-Inventory loss/adjustments | M83: Normal | N83: APTIV MANUFATURA E SERVICOS DE-104120 | O83: APTIV PLANT FR47-725460 | P83: divergencia de estoque | Q83: DHL Express SA | R83: PTA-00092755 | S83: 15393422; | T83: ; | U83: ; | V83: Aptiv | W83: Premium - Productive | X83: Moraes.Arnaldo@aptiv.com | Y83: 44966.114 | Z83: 44973.253 | AA83: SA | AB83: Closed Not Recovered | AC83: 0 | AE83: 0 | AG83: 10012 | AH83: Q11 | AJ83: 5473 | AK83: Non-Recoverable | AM83: 90 | AO83: 3400 AERO PARK DR | AP83: VIENNA | AQ83: 725460 | AR83: US | AS83: NA | AT83: OH | AU83: 44473-8704 | AV83: AVENIDA AVELINO RIBEIRO, 900 | AW83: PARAISOPOLIS | AX83: 104120 | AY83: BR | AZ83: SA | BA83: MG | BB83: 37660-000 | BC83: SPS | BD83: Approved | BE83: Carvalho, Eliane R | BF83: 44966.128 | BG83: 0 | BH83: DHL Express SA | BI83: 1261888946 | BK83: Aptiv | BM83: Personal Estimate | BN83: Invoice | BQ83: 0 Days 0 Hr 21 Min | BR83: 250 | BS83: Approved - ;; Approved - ; | BT83: 90 | BU83: 90 | BV83: ; | BW83: ; | BX83: ; | BY83: BR | CA83: USD | CF83: 1 | CJ83: 0
A84: 44958 | B84: Internal problem - Manufacturing/ Ordering/ Purchasing/ IT | C84: 48338 | D84: Purchasing Problem - PN sem Contrato | E84: JOHN DEERE | F84: 44970 | G84: Paraisopolis | H84: Inbound Premium | I84: 701.06 | J84: 701.06 | K84: =I84/$I$1 -> 0.001715976 | L84: P1-Purchasing-Aptiv Resp | M84: Normal | N84: Paraisopolis-10012 | O84: APTIVPORT SERVICES S A-753066 | P84: Problema Comercial - Item sem contrato, esse material é comprado apenas para revenda JD. Nesse caso como ação o time de compras esta criando contrato com a YAZAKY apartir de 08/05/2023. | Q84: DHL Express SA | R84: PTA-00092984 | S84: 15326369; | T84: ; | U84: ; | V84: Aptiv | W84: Premium - Productive | X84: william.de.siqueira@aptiv.com | Y84: 44967.046 | Z84: 44970.127 | AA84: SA | AB84: Closed Not Recovered | AC84: 0 | AE84: 0 | AF84: 44970 | AG84: 10012 | AH84: Q11 | AK84: Non-Recoverable | AM84: 70106 | AO84: RUA G - ZONA INDUSTRIAL | AP84: CASTELO BRANCO | AQ84: 753066 | AR84: PT | AS84: EMEA | AT84: 28 | AU84: 6001-909 | AV84: Av. Avelino Ribeiro, 900 | AW84: Paraisopolis | AX84: 10012 | AY84: BR | AZ84: SA | BA84: Mina | BB84: 37660-000 | BC84: SPS | BD84: Approved | BE84: Naus, Angelica | BF84: 44967.197 | BG84: 0 | BK84: Aptiv | BM84: Invoice | BQ84: 0 Days 3 Hr 36 Min | BR84: 800 | BS84: Approved - ;; Approved - ;; Approved - ;; Approved - ; | BT84: 70106 | BU84: 70106 | BV84: ; | BW84: ; | BX84: ; | BY84: BR | CA84: USD | CF84: 1 | CJ84: 0
A85: 44958 | B85: Project | C85: 48345 | D85: Projeto | E85: GM | F85: 44967 | G85: Paraisopolis | H85: Inbound Premium | I85: 35 | J85: 35 | K85: =I85/$I$1 -> 8.5669074e-05 | L85: E1P-Prototypes/Samples | M85: Cost Recovery | N85: Paraisopolis-10012 | O85: SERENDIPITY ELECTRONICS-110404 | P85: Parts for sales from protoypes pieces. Freigth included in the piece price. | Q85: DHL Express SA | R85: PTA-00092923 | S85: 13611693 ; | T85: ; | U85: ; | V85: Aptiv | W85: Premium - Productive | X85: rayzza.peres@aptiv.com | Y85: 44967.075 | Z85: 44967.075 | AA85: SA | AB85: Closed Recovered | AC85: 0 | AE85: 35 | AG85: 10012 | AH85: Q11 | AJ85: 35 | AK85: Recoverable | AM85: 35 | AN85: USD | AO85: 152 E MAIN ST | AP85: HUNTINGTON | AQ85: 110404 | AR85: US | AS85: NA | AT85: NY | AU85: 11743-2958 | AV85: Av. Avelino Ribeiro, 900 | AW85: Paraisopolis | AX85: 10012 | AY85: BR | AZ85: SA | BA85: Mina | BB85: 37660-000 | BC85: SPS | BD85: Approved | BE85: Carvalho, Eliane R | BF85: 44967.083 | BG85: 0 | BI85: 1622815154 | BK85: Aptiv | BM85: Invoice | BN85: Invoice | BQ85: 0 Days 0 Hr 11 Min | BR85: 250 | BS85: Approved - ;; Approved - ; | BT85: 35 | BU85: 35 | BV85: ; | BW85: ; | BX85: ; | BY85: BR | BZ85: BSUV PL8 | CA85: USD | CE85: DPP68060 | CF85: 1 | CG85: 1 | CJ85: 0
A86: 44958 | B86: Shipment delay | C86: 48359 | D86: Transportation Problem - Atraso ETA - Vessel Hella | E86: GM | F86: 44967 | G86: Pinhal | H86: Inbound Premium | I86: 322.33 | J86: 250 | K86: =I86/$I$1 -> 0.00078896322 | L86: T1-Transportation | M86: Normal | N86: APTIV MANUFATURA E SERVICOS DE-104991 | O86: APTIV SERVICES US, LLC-1001280 | P86: Aéreo necessário devido ao atraso de dois navios. Primeiro atraso no Navio Hella, segundo atraso Navio MSC Alessia. | Q86: DHL Express SA | R86: PTA-00093201 | S86: 15332132; | T86: ; | U86: ; | V86: Aptiv | W86: Premium - Productive | X86: rodrigo.perez@aptiv.com | Y86: 44967.095 | Z86: 44986.243 | AA86: SA | AB86: Closed Not Recovered | AC86: 0 | AE86: 32233 | AF86: 44967 | AG86: 10010 | AH86: Q18 | AJ86: 32233 | AK86: Non-Recoverable | AM86: 250 | AN86: USD | AO86: 1265 N RIVER RD NE | AP86: WARREN | AQ86: 1001280 | AR86: US | AS86: NA | AT86: OH | AU86: 44483-2352 | AV86: RODOVIA SP 342 KM 196 | AW86: ESPIRITO SANTO DO PINHAL | AX86: 104991 | AY86: BR | AZ86: SA | BA86: SP | BB86: 13990-000 | BC86: SPS | BD86: Approved | BE86: Carvalho, Eliane R | BF86: 44970.103 | BG86: 0 | BI86: 4868482496 | BK86: Transportation | BM86: Personal Estimate | BN86: Personal Estimate | BQ86: 3 Days 0 Hr 10 Min | BR86: 250 | BS86: Approved - ;; Approved - ; | BT86: 32233 | BU86: 32233 | BV86: ; | BW86: ; | BX86: ; | BY86: BR | CA86: USD | CE86: 15509260/35031567/35410019 | CF86: 1 | CG86: 1 | CJ86: 0
A87: 44958 | B87: Stock discrepancy | C87: 48409 | D87: Stock Discrepancy | E87: GM | F87: 44967 | G87: Paraisopolis | H87: Inbound Premium | I87: 137.27 | J87: 137.27 | K87: =I87/$I$1 -> 0.00033599411 | L87: S1I-Inventory loss/adjustments | M87: Normal | N87: APTIV MANUFATURA E SERVICOS DE-104120 | O87: Tecnoprint São Paulo-Dummy | P87: Stock Discrepancy | Q87: TRANSPORTADORA PITUTA | R87: PTA-00093148 | S87: 15368456; | T87: ; | U87: ; | V87: Aptiv | W87: Premium - Productive | X87: adriane.barbosa.silva@aptiv.com | Y87: 44967.137 | Z87: 44967.137 | AA87: SA | AB87: Closed Not Recovered | AC87: 0 | AE87: 0 | AG87: 10012 | AH87: Q11 | AK87: Non-Recoverable | AM87: 700 | AO87: São Paulo | AP87: Sao Paulo | AQ87: Dummy | AR87: BR | AS87: SA | AT87: Sao Paulo | AU87: 0000 | AV87: AVENIDA AVELINO RIBEIRO, 900 | AW87: PARAISOPOLIS | AX87: 104120 | AY87: BR | AZ87: SA | BA87: MG | BB87: 37660-000 | BC87: SPS | BD87: Approved | BE87: Carvalho, Eliane R | BF87: 44969.487 | BG87: 0 | BK87: Aptiv | BM87: Invoice | BQ87: 2 Days 8 Hr 24 Min | BR87: 250 | BS87: Approved - ;; Approved - ; | BT87: 13727 | BU87: 13727 | BV87: ; | BW87: ; | BX87: ; | BY87: BR | CA87: BRL | CF87: 19610535 | CJ87: 0
A88: 44958 | B88: Customer reschedule | C88: 48488 | D88: Customer Reschedule - Fiat Consulta 06 | E88: FIAT | F88: 44970 | G88: Ouros | H88: Inbound Premium | I88: 100 | J88: 100 | K88: =I88/$I$1 -> 0.00024476878 | L88: S2-External Customer driven schedule changes | M88: Cost Recovery Pending | N88: APTIV MANUFATURA E SERVICOS DE-109304 | O88: DELFINGEN DE-HASSFURT GMBH-1085272 | P88: reprograma cliente FIAT - Consulta 06: Incremento fire Fev_2023 | Q88: DHL Express SA | R88: PTA-00093170 | S88: 10763307 ; | T88: ; | U88: ; | V88: Customer | W88: Premium - Productive | X88: lua.barbosa.ribeiro@aptiv.com | Y88: 44967.275 | Z88: 44967.275 | AA88: SA | AB88: Open | AC88: 0 | AE88: 0 | AF88: 44974 | AG88: 10023 | AH88: Q11 | AK88: Recoverable | AM88: 100 | AN88: USD | AO88: PHILIPP-REIS-STR. 18 | AP88: HASSFURT | AQ88: 1085272 | AR88: DE | AS88: EMEA | AT88: BY | AU88: 97437 | AV88: TV ANTONIO E FONSECA 250 BAIRRO | AW88: CONCEICAO DOS OUROS | AX88: 109304 | AY88: BR | AZ88: SA | BA88: MG | BB88: 37548-000 | BC88: SPS | BD88: Approved | BE88: Carvalho, Eliane R | BF88: 44970.442 | BG88: 0 | BK88: Customer | BM88: Invoice | BO88: FIAT | BQ88: 2 Days 16 Hr 1 Min | BR88: 250 | BS88: Approved - ;; Approved - ; | BT88: 100 | BU88: 100 | BV88: ; | BW88: ; | BX88: ; | BY88: BR | BZ88: Fiat Fire | CA88: USD | CF88: 1 | CG88: 1 | CJ88: 0
A89: 44958 | B89: Project | C89: 48771 | D89: Projeto | E89: OTHER | F89: 44970 | G89: Paraisopolis | H89: Inbound Premium | I89: 100 | J89: 100 | K89: =I89/$I$1 -> 0.00024476878 | L89: E1D-Aptiv Design/Engineering changes | M89: Cost Recovery Pending | N89: APTIV MANUFATURA E SERVICOS DE-724381 | O89: SEMICON SP Z O O-1052723 | P89: Item ordered outside the supplier's lead time. | Q89: DHL Express SA | R89: PTA-00093273 | S89: 15545256; | T89: 100; | U89: 10.50; | V89: Customer | W89: Premium - Productive | X89: marcia.p.torres@aptiv.com | Y89: 44970.261 | Z89: 44970.261 | AA89: SA | AB89: Open | AC89: 0 | AE89: 0 | AF89: 44970 | AG89: 10012 | AH89: Q11 | AK89: Recoverable | AM89: 100 | AN89: USD | AO89: UL. ZWOLENSKA 43/43A | AP89: WARSZAWA | AQ89: 1052723 | AR89: PL | AS89: EMEA | AT89: MZ | AU89: 04-761 | AV89: AVENIDA AVELINO RIBEIRO, 900 | AW89: PARAISOPOLIS | AX89: 724381 | AY89: BR | AZ89: SA | BA89: MG | BB89: 37660-000 | BC89: SPS | BD89: Approved | BE89: Carvalho, Eliane R | BF89: 44970.353 | BG89: 0 | BH89: DHL Express SA | BK89: Aptiv | BM89: Invoice | BO89: OTHER | BQ89: 0 Days 2 Hr 13 Min | BR89: 250 | BS89: Approved - ;; Approved - ; | BT89: 100 | BU89: 100 | BV89: ; | BW89: 45x33x33; | BX89: ; | BY89: BR | BZ89: CNH | CA89: USD | CD89: Kg | CE89: We have the OK from the CNH platform for the additional costs. | CF89: 1 | CG89: 1 | CJ89: 0
A90: 44958 | B90: Shipment delay | C90: 48961 | D90: Transportation Problem - Atraso ETA - Vessel Hella | E90: GM | F90: 44971 | G90: Pinhal | H90: Inbound Premium | I90: 216.78 | J90: 100 | K90: =I90/$I$1 -> 0.00053060977 | L90: T1-Transportation | M90: Normal | N90: APTIV MANUFATURA E SERVICOS DE-104991 | O90: APTIV SERVICES US, LLC-1001280 | P90: Aéreo necessário devido ao atraso de dois navios. Primeiro atraso no Navio Hella, segundo atraso Navio MSC Alessia. | Q90: DHL Express SA | R90: PTA-00093582 | S90: 15511752; | T90: ; | U90: ; | V90: Aptiv | W90: Premium - Productive | X90: rodrigo.perez@aptiv.com | Y90: 44971.118 | Z90: 44986.252 | AA90: SA | AB90: Closed Not Recovered | AC90: 0 | AE90: 21678 | AF90: 44971 | AG90: 10010 | AH90: Q18 | AJ90: 21678 | AK90: Non-Recoverable | AM90: 100 | AN90: USD | AO90: 1265 N RIVER RD NE | AP90: WARREN | AQ90: 1001280 | AR90: US | AS90: NA | AT90: OH | AU90: 44483-2352 | AV90: RODOVIA SP 342 KM 196 | AW90: ESPIRITO SANTO DO PINHAL | AX90: 104991 | AY90: BR | AZ90: SA | BA90: SP | BB90: 13990-000 | BC90: SPS | BD90: Approved | BE90: Carvalho, Eliane R | BF90: 44971.154 | BG90: 0 | BK90: Transportation | BM90: Personal Estimate | BN90: Personal Estimate | BQ90: 0 Days 0 Hr 51 Min | BR90: 250 | BS90: Approved - ;; Approved - ; | BT90: 21678 | BU90: 21678 | BV90: ; | BW90: ; | BX90: ; | BY90: BR | CA90: USD | CF90: 1 | CG90: 1 | CJ90: 0
A91: 44958 | B91: Shipment delay | C91: 49258 | D91: Transportation Problem - Atraso ETA | E91: GM | F91: 44973 | G91: Pinhal | H91: Inbound Premium | I91: 250 | J91: 250 | K91: =I91/$I$1 -> 0.00061192196 | L91: T1-Transportation | M91: Normal | N91: APTIV MANUFATURA E SERVICOS DE-728338 | O91: SWS CHINA LTD.-7086264 | P91: Aéreo necessário devido ao atraso de ETA do Navio MSC GAYANE. Invoice afetada : 0923010031. | Q91: DHL Express SA | R91: PTA-00094168 | S91: 33103175; | T91: ; | U91: ; | V91: Aptiv | W91: Premium - Productive | X91: rodrigo.perez@aptiv.com | Y91: 44972.477 | Z91: 44972.474 | AA91: SA | AB91: Closed Not Recovered | AC91: 0 | AE91: 0 | AF91: 44972 | AG91: 10010 | AH91: Q18 | AK91: Non-Recoverable | AM91: 250 | AO91: 1501,TOWER B,NO.100 ZUNYI ROAD | AP91: SHANGHAI | AQ91: 7086264 | AR91: CN | AS91: AP | AT91: 31 | AU91: 200051 | AV91: JOSE MONFARDINI N 3 845 LOTEAMENTO | AW91: ESPIRITO SANTO DO PINHAL | AX91: 728338 | AY91: BR | AZ91: SA | BA91: SP | BB91: 13990000 | BC91: SPS | BD91: Approved | BE91: Carvalho, Eliane R | BF91: 44974.054 | BG91: 0 | BK91: Transportation | BM91: Personal Estimate | BQ91: 2 Days 1 Hr 49 Min | BR91: 250 | BS91: Approved - ;; Approved - ; | BT91: 250 | BU91: 250 | BV91: ; | BW91: ; | BX91: ; | BY91: BR | CA91: USD | CE91: 35294642 | CF91: 1 | CJ91: 0
A92: 44958 | B92: Stock discrepancy | C92: 49272 | D92: Stock Discrepancy | E92: JOHN DEERE | F92: 44966 | G92: Paraisopolis | H92: Inbound Premium | I92: 54.72 | J92: 54.72 | K92: =I92/$I$1 -> 0.00013393748 | L92: S1I-Inventory loss/adjustments | M92: Normal | N92: Paraisopolis-10012 | O92: HERMES ENGINEERING OOD-1072462 | P92: Fornecedor padrao (TTI) não tinha peças então conseguimos peças com outro distribuidor - saving no SPOT BUY de 164 Dolares | Q92: DHL Express SA | R92: PTA-00093825 | S92: 13509280; | T92: ; | U92: ; | V92: Aptiv | W92: Premium - Productive | X92: william.de.siqueira@aptiv.com | Y92: 44972.528 | Z92: 44980.219 | AA92: SA | AB92: Closed Recovered | AC92: 0 | AE92: 5472 | AF92: 44966 | AG92: 10012 | AH92: Q11 | AJ92: 5472 | AK92: Recoverable | AM92: 5472 | AN92: USD | AO92: MUR 15 STR. | AP92: SOFIA | AQ92: 1072462 | AR92: BG | AS92: EMEA | AT92: 23 | AU92: 1680 | AV92: Av. Avelino Ribeiro, 900 | AW92: Paraisopolis | AX92: 10012 | AY92: BR | AZ92: SA | BA92: Mina | BB92: 37660-000 | BC92: SPS | BD92: Approved | BE92: Carvalho, Eliane R | BF92: 44972.111 | BG92: 0 | BI92: 3542827761 | BK92: Aptiv | BM92: Invoice | BN92: Invoice | BQ92: 0 Days 1 Hr 59 Min | BR92: 250 | BS92: Approved - ;; Approved - ; | BT92: 5472 | BU92: 5472 | BV92: ; | BW92: ; | BX92: ; | BY92: BR | CA92: USD | CF92: 1 | CG92: 1 | CJ92: 0
A93: 44958 | B93: Supplier delay | C93: 49325 | D93: Supplier Delay Serendipity | E93: JOHN DEERE | F93: 44973 | G93: Paraisopolis | H93: Inbound Premium | I93: 77.82 | J93: 77.82 | K93: =I93/$I$1 -> 0.00019047907 | L93: B3-Behind Schedule-External Supplier | M93: Cost Recovery | N93: Paraisopolis-10012 | O93: SERENDIPITY ELECTRONICS, INC.-1062318 | P93: Atraso do fornecedor - (Cost recovery sim) Fornecedor enviara a nota de credito | Q93: DHL Express SA | R93: PTA-00094025 | S93: 15547891 - 15422718; | T93: ; | U93: ; | V93: Supplier | W93: Premium - Productive | X93: william.de.siqueira@aptiv.com | Y93: 44972.167 | Z93: 44980.219 | AA93: SA | AB93: Closed Recovered | AC93: 0 | AE93: 0 | AF93: 44979 | AG93: 10012 | AH93: Q11 | AJ93: 8257 | AK93: Recoverable | AM93: 7782 | AN93: USD | AO93: 152 E MAIN ST STE D | AP93: HUNTINGTON | AQ93: 1062318 | AR93: US | AS93: NA | AT93: NY | AU93: 11743-2958 | AV93: Av. Avelino Ribeiro, 900 | AW93: Paraisopolis | AX93: 10012 | AY93: BR | AZ93: SA | BA93: Mina | BB93: 37660-000 | BC93: SPS | BD93: Approved | BE93: Carvalho, Eliane R | BF93: 44973.113 | BG93: 0 | BI93: 8266958173 | BK93: Supplier | BM93: Invoice | BN93: Invoice | BP93: SERENDIPITY ELECTRONICS-755571 | BQ93: 0 Days 22 Hr 42 Min | BR93: 250 | BS93: Approved - ;; Approved - ; | BT93: 7782 | BU93: 7782 | BV93: ; | BW93: ; | BX93: ; | BY93: BR | CA93: USD | CB93: Ship From Supplier | CF93: 1 | CG93: 1 | CJ93: 0
A94: 44958 | B94: Customer reschedule | C94: 49562 | D94: Customer Reschedule - VW Alternador | E94: VW | F94: 44974 | G94: Pinhal | H94: Inbound Premium | I94: 150 | J94: 150 | K94: =I94/$I$1 -> 0.00036715317 | L94: PC-Plant PC Resp | M94: Cost Recovery Pending | N94: APTIV MANUFATURA E SERVICOS DE-104991 | O94: LEAR CORPORATION CZECH REPUBLIC S R-765217 | P94: AEREO NECESSARIO DEVIDO AO REPROGRAMA DO ALTERNADOR (CLIENTE AUTORIZOU AÉREO) | Q94: DHL Express SA | R94: PTA-00094026 | S94: 15341575; | T94: ; | U94: ; | V94: Aptiv | W94: Premium - Productive | X94: bruno.g.silva2@aptiv.com | Y94: 44973.43 | Z94: 44973.394 | AA94: SA | AB94: Open | AC94: 0 | AE94: 0 | AF94: 44973 | AG94: 10010 | AH94: Q18 | AK94: Recoverable | AM94: 150 | AO94: TOVARNI 735/10 | AP94: VYSKOV-PREDMESTI | AQ94: 765217 | AR94: CZ | AS94: EMEA | AT94: CZ | AU94: 68201 | AV94: RODOVIA SP 342 KM 196 | AW94: ESPIRITO SANTO DO PINHAL | AX94: 104991 | AY94: BR | AZ94: SA | BA94: SP | BB94: 13990-000 | BC94: SPS | BD94: Approved | BE94: Carvalho, Eliane R | BF94: 44973.119 | BG94: 0 | BH94: DHL Express SA | BK94: Aptiv | BM94: Personal Estimate | BN94: Personal Estimate | BQ94: 0 Days 4 Hr 31 Min | BR94: 250 | BS94: Approved - ;; Approved - ; | BT94: 150 | BU94: 150 | BV94: ; | BW94: ; | BX94: ; | BY94: BR | BZ94: ALTERNADOR | CA94: USD | CF94: 1 | CJ94: 0
A95: 44958 | B95: BOM error | C95: 49633 | D95: BOM Error | E95: VW | F95: 44974 | G95: Pinhal | H95: Inbound Premium | I95: 150 | J95: 150 | K95: =I95/$I$1 -> 0.00036715317 | L95: E1B-BOM Errors | M95: Normal | N95: APTIV MANUFATURA E SERVICOS DE-104991 | O95: APTIV SERVICES DEUTSCHLAND GMBH-765857 | P95: Aereo necessario devido ao erro de BOM, terminal não esta amarrado em parte da estrutura | Q95: DHL Express SA | R95: PTA-00094169 | S95: 10864932; | T95: ; | U95: ; | V95: Aptiv | W95: Premium - Productive | X95: bruno.g.silva2@aptiv.com | Y95: 44973.171 | Z95: 44973.169 | AA95: SA | AB95: Closed Not Recovered | AC95: 0 | AE95: 0 | AF95: 44973 | AG95: 10010 | AH95: Q18 | AK95: Non-Recoverable | AM95: 150 | AO95: RATHSBERGSTRASSE 25 | AP95: NUREMBERG | AQ95: 765857 | AR95: DE | AS95: EMEA | AT95: BY | AU95: 90411 | AV95: RODOVIA SP 342 KM 196 | AW95: ESPIRITO SANTO DO PINHAL | AX95: 104991 | AY95: BR | AZ95: SA | BA95: SP | BB95: 13990-000 | BC95: SPS | BD95: Approved | BE95: Carvalho, Eliane R | BF95: 44974.058 | BG95: 0 | BH95: DHL Express SA | BK95: Aptiv | BM95: Personal Estimate | BN95: Personal Estimate | BQ95: 0 Days 21 Hr 17 Min | BR95: 250 | BS95: Approved - ;; Approved - ; | BT95: 150 | BU95: 150 | BV95: ; | BW95: ; | BX95: ; | BY95: BR | BZ95: MIRGOR | CA95: USD | CF95: 1 | CJ95: 0
A96: 44958 | B96: Customer reschedule | C96: 49706 | D96: Customer Reschedule - John Deere | E96: JOHN DEERE | F96: 44974 | G96: Paraisopolis | H96: Inbound Premium | I96: 1102 | J96: 1102 | K96: =I96/$I$1 -> 0.002697352 | L96: S2-External Customer driven schedule changes | M96: Cost Recovery Pending | N96: APTIV MANUFATURA E SERVICOS DE-724381 | O96: LEONI CABLE S A DE C V-763980 | P96: JD RESCHEDULE, AND THEY WILL PAY THE AIR FREIGHT COST | Q96: DHL Express SA | R96: PTA-00095024 | S96: M7600101; | T96: ; | U96: ; | V96: Customer | W96: Premium - Productive | X96: jorge.luis.almeida@aptiv.com | Y96: 44973.349 | Z96: 44973.349 | AA96: SA | AB96: Open | AC96: 0 | AE96: 0 | AF96: 44985 | AG96: 10012 | AH96: Q11 | AK96: Recoverable | AM96: 1102 | AO96: AVENIDA RIO CONCHOS NO 9700 | AP96: CD CUAUHTEMOC | AQ96: 763980 | AR96: MX | AS96: NA | AT96: CHI | AU96: 31543 | AV96: AVENIDA AVELINO RIBEIRO, 900 | AW96: PARAISOPOLIS | AX96: 724381 | AY96: BR | AZ96: SA | BA96: MG | BB96: 37660-000 | BC96: SPS | BD96: Approved | BE96: Garcia Puente, Jorge | BF96: 44980.147 | BG96: 0 | BK96: Customer | BM96: Invoice | BO96: JOHN DEERE | BQ96: 6 Days 19 Hr 9 Min | BR96: 5000 | BS96: Approved - ;; Approved - ;; Approved - ;; Approved - ;; Approved - ;; Approved - ; | BT96: 1102 | BU96: 1102 | BV96: ; | BW96: ; | BX96: ; | BY96: BR | CA96: USD | CE96: JD RESCHEDULE, AND THEY WILL PAY THE AIR FREIGHT COST | CF96: 1 | CJ96: 0
A97: 44958 | B97: P&A | C97: 50920 | D97: P&A | E97: PSA | F97: 44980 | G97: Paraisopolis | H97: Inbound Premium | I97: 65.57 | J97: 65.57 | K97: =I97/$I$1 -> 0.00016049489 | L97: OOOT-Other/Sales | M97: Normal | N97: APTIV MANUFATURA E SERVICOS DE-724381 | O97: APTIV CONTRACT SERVICES D.O.O.-7094293 | P97: Critical material to meet the P&A program as requested by the customer. PSA | Q97: DHL Express SA | R97: PTA-00095247 | S97: 15327279; | T97: 200; | U97: 0.50; | V97: Aptiv | W97: Premium - Productive | X97: marcia.p.torres@aptiv.com | Y97: 44980.501 | Z97: 44980.501 | AA97: SA | AB97: Closed Not Recovered | AC97: 0 | AE97: 0 | AF97: 44980 | AG97: 10012 | AH97: Q11 | AK97: Non-Recoverable | AL97: 7385444500 | AM97: 6557 | AO97: ZELENA ZONA PRVA 1 | AP97: LESKOVAC | AQ97: 7094293 | AR97: RS | AS97: EMEA | AT97: 23 | AU97: 16000 | AV97: AVENIDA AVELINO RIBEIRO, 900 | AW97: PARAISOPOLIS | AX97: 724381 | AY97: BR | AZ97: SA | BA97: MG | BB97: 37660-000 | BC97: SPS | BD97: Approved | BE97: Carvalho, Eliane R | BF97: 44981.272 | BG97: 0 | BK97: Aptiv | BM97: Invoice | BQ97: 1 Days 6 Hr 31 Min | BR97: 250 | BS97: Approved - ;; Approved - ; | BT97: 6557 | BU97: 6557 | BV97: ; | BW97: 40x30x20; | BX97: ; | BY97: BR | CA97: USD | CD97: Kg | CE97: Critical material to meet the P&A program as requested by the customer. PSA | CF97: 1 | CJ97: 0
A98: 44958 | B98: Customer reschedule | C98: 50921 | D98: Customer Reschedule - VW Alternador | E98: VW | F98: 44974 | G98: Pinhal | H98: Inbound Premium | I98: 150 | J98: 150 | K98: =I98/$I$1 -> 0.00036715317 | L98: PC-Plant PC Resp | M98: Cost Recovery Pending | N98: APTIV MANUFATURA E SERVICOS DE-104991 | O98: LEAR CORPORATION CZECH REPUBLIC S R-765217 | P98: AEREO NECESSARIO DEVIDO AO REPROGRAMA DO ALTERNADOR (CLIENTE AUTORIZOU AÉREO) | Q98: DHL Express SA | R98: PTA-00095012 | S98: 15341575; | T98: ; | U98: ; | V98: Aptiv | W98: Premium - Productive | X98: bruno.g.silva2@aptiv.com | Y98: 44980.505 | Z98: 44980.503 | AA98: SA | AB98: Open | AC98: 0 | AE98: 0 | AF98: 44973 | AG98: 10010 | AH98: Q18 | AK98: Recoverable | AM98: 150 | AO98: TOVARNI 735/10 | AP98: VYSKOV-PREDMESTI | AQ98: 765217 | AR98: CZ | AS98: EMEA | AT98: CZ | AU98: 68201 | AV98: RODOVIA SP 342 KM 196 | AW98: ESPIRITO SANTO DO PINHAL | AX98: 104991 | AY98: BR | AZ98: SA | BA98: SP | BB98: 13990-000 | BC98: SPS | BD98: Approved | BE98: Carvalho, Eliane R | BF98: 44980.519 | BG98: 0 | BH98: DHL Express SA | BK98: Aptiv | BM98: Personal Estimate | BN98: Personal Estimate | BQ98: 0 Days 0 Hr 19 Min | BR98: 250 | BS98: Approved - ;; Approved - ; | BT98: 150 | BU98: 150 | BV98: ; | BW98: ; | BX98: ; | BY98: BR | BZ98: ALTERNADOR | CA98: USD | CF98: 1 | CJ98: 0
A99: 44958 | B99: Shipment delay | C99: 50930 | D99: Transportation Problem - Atraso ETA | E99: GM | F99: 44981 | G99: Pinhal | H99: Inbound Premium | I99: 410 | J99: 410.71 | K99: =I99/$I$1 -> 0.001003552 | L99: PC-Plant PC Resp | M99: Normal | N99: APTIV MANUFATURA E SERVICOS DE DIST-1039282 | O99: Empresa de Transportes Covre-Dummy | P99: Entrega Emergencial da Pasta M0091/23, para evitar parada de linha GM. | Q99: EMPRESA DE TRANSPORTES COVRE | R99: PTA-00095028 | S99: 15511752; | T99: ; | U99: ; | V99: Aptiv | W99: Premium - Productive | X99: rodrigo.perez@aptiv.com | Y99: 44980.055 | Z99: 44980.054 | AA99: SA | AB99: Closed Not Recovered | AC99: 0 | AE99: 410 | AF99: 44980 | AG99: 10010 | AH99: Q18 | AJ99: 410 | AK99: Non-Recoverable | AM99: 41071 | AN99: USD | AO99: R. Hercílio Camargo Barbosa, 207 | AP99: Santos | AQ99: Dummy | AR99: BR | AS99: SA | AT99: Sao Paulo | AU99: 11095-590 | AV99: RUA JOSE MONFARDINI 3845 | AW99: ESPIRITO SANTO DO PINHAL | AX99: 1039282 | AY99: BR | AZ99: SA | BA99: SP | BB99: 13990-000 | BC99: SPS | BD99: Approved | BE99: Edilson, Geraldo | BF99: 44980.155 | BG99: 0 | BH99: EMPRESA DE TRANSPORTES COVRE | BI99: ENTREGA EMERGENCIAL | BK99: Aptiv | BM99: Personal Estimate | BN99: Personal Estimate | BQ99: 0 Days 2 Hr 23 Min | BR99: 500 | BS99: Approved - ;; Approved - ;; Approved - ; | BT99: 410 | BU99: 410 | BV99: ; | BW99: ; | BX99: ; | BY99: BR | CA99: USD | CF99: 1 | CG99: 1 | CJ99: 0
A100: 44958 | B100: Stock discrepancy | C100: 50945 | D100: Stock Discrepancy | E100: JOHN DEERE | F100: 44980 | G100: Paraisopolis | H100: Inbound Premium | I100: 137.27 | J100: 137.27 | K100: =I100/$I$1 -> 0.00033599411 | L100: S1I-Inventory loss/adjustments | M100: Normal | N100: APTIV MANUFATURA E SERVICOS DE-733223 | O100: Heilind São Paulo-Dummy | P100: Stock Discrepancy | Q100: TRANSPORTADORA PITUTA | R100: PTA-00095075 | S100: 12196871; | T100: ; | U100: ; | V100: Aptiv | W100: Premium - Productive | X100: adriane.barbosa.silva@aptiv.com | Y100: 44980.135 | Z100: 44980.135 | AA100: SA | AB100: Closed Not Recovered | AC100: 0 | AE100: 0 | AG100: 10012 | AH100: Q11 | AK100: Non-Recoverable | AM100: 700 | AN100: BRL | AO100: São Paulo | AP100: São Paulo | AQ100: Dummy | AR100: BR | AS100: SA | AT100: São Paulo | AU100: 0000 | AV100: 900 AVENUE AVELINO RIBEIRO | AW100: PARAISOPOLIS | AX100: 733223 | AY100: BR | AZ100: SA | BA100: MG | BB100: 37660-000 | BC100: SPS | BD100: Approved | BE100: Carvalho, Eliane R | BF100: 44980.328 | BG100: 0 | BK100: Aptiv | BM100: Invoice | BQ100: 0 Days 4 Hr 37 Min | BR100: 250 | BS100: Approved - ;; Approved - ; | BT100: 13727 | BU100: 13727 | BV100: ; | BW100: ; | BX100: ; | BY100: BR | CA100: BRL | CE100: Divergencia de 08 semanas de material e sem pedido firme | CF100: 19610535 | CG100: 19610535 | CJ100: 0
...

Sheet Dashboard 2024
A1: DASHBOARD - MAIN REASONS - 2024 (jan - sep)
A2: Reason | B2: Total $ | C2: % | D2: CR | G2: no | K2: Target year 24 | N2: DASHBOARD - MAIN REASONS - 2023
A3: Carrier issue | B3: 18421.75 | C3: 0.025779404 | H3: Faturamento 2024 | K3: 236.48141 | N3: Reason | O3: MOTIVO | P3: Total $ | Q3: % | S3: =(GETPIVOTDATA("Total $",$N$3,"ORIG_PREMIUM_REASON_CODE","Cost Recovery")+GETPIVOTDATA("Total $",$N$3,"ORIG_PREMIUM_REASON_CODE","Cost Recovery Pending"))/1000000 -> 0.19046043
A4: Customer recheduled | B4: 195264.37 | C4: 0.27325303 | N4: Cost Recovery | O4: Freight to be recovery at POV | P4: 45701.32 | Q4: 0.17481593 | S4: =S3/I3 -> #DIV/0!
A5: Internal problem - Manufacturing/ Ordering/ Purchasing/ IT | B5: 15569.96 | C5: 0.021788608 | H5: Premium Total | I5: =GETPIVOTDATA("Total $",#REF!)/1000000 -> #REF! | K5: =K3*K6 -> 0.14188885 | O5: Freight recovered with the client | P5: 33678.99 | Q5: 0.12882832
A6: Internal strategy | B6: 59813.98 | C6: 0.083703707 | H6: % Premium Total/ fat | I6: =I5/I3 -> #REF! | K6: 0.0006 | O6: Customer reschedule | P6: 30968.96 | Q6: 0.11846195
A7: Lead time discrepancy between supplier/ customer | B7: 21493.11 | C7: 0.030077466 | O7: Project | P7: 25095.57 | Q7: 0.095995159
A8: P&A | B8: 11790.79 | C8: 0.016500036 | H8: CR Non recoverable | I8: =SUMIF(#REF!,$G$2,#REF!)/1000000 -> #REF! | O8: Freight recovered by POV | P8: 12690.38 | Q8: 0.048543032
A9: Stock discrepancy | B9: 18345.13 | C9: 0.025672182 | H9: % CR Non recoverable/ fat | I9: =I8/I3 -> #REF! | O9: Freight recovery by ICC | P9: 7980.1 | Q9: 0.030525346
A10: Vessel delay | B10: 75429.401 | C10: 0.10555593 | O10: Cargo lost | P10: 2723.27 | Q10: 0.010417007
A11: Port Strike + Vessel delay | B11: 161987.49 | C11: 0.22668536 | O11: Internal problem - Manufacturing/ Ordering/ Purchasing/ IT | P11: 1786.12 | Q11: 0.0068322367
A12: APTIV Shipment delay | B12: 19734.33 | C12: 0.027616229 | O12: Lead time discrepancy between supplier/ customer | P12: 1622.1 | Q12: 0.0062048301
A13: Total Geral | B13: 597850.31 | C13: 0.83663196 | O13: Stock discrepancy | P13: 1435.53 | Q13: 0.0054911656
O14: Supplier delay | P14: 1035.37 | Q14: 0.0039604802
O15: Freight to be recovered with supplier | P15: 411.18 | Q15: 0.0015728389
O16: P&A | P16: 169.03 | Q16: 0.00064657076
N17: Cost Recovery Total | P17: 165297.92 | Q17: 0.63229487
N19: Cost Recovery Pending | O19: Carrier issue | P19: 6078.36 | Q19: 0.023250842
O20: Freight to be recovered with client | P20: 4647.41 | Q20: 0.017777196
O21: Freight to be recovery at POV | P21: 4381.83 | Q21: 0.016761304
O22: Lead time discrepancy between supplier/ customer | P22: 3707 | Q22: 0.014179955
O23: Freight recovered by POV | P23: 2139.82 | Q23: 0.0081852041
O24: Customer reschedule | P24: 1209.17 | Q24: 0.0046252971
O25: Freight to be recovered with supplier | P25: 849.34 | Q25: 0.0032488813
O26: Shipment delay | P26: 689 | Q26: 0.0026355514
O27: Project | P27: 631.58 | Q27: 0.0024159094
O28: Internal strategy/ discount | P28: 479 | Q28: 0.0018322629
O29: Internal problem - Manufacturing/ Ordering/ Purchasing/ IT | P29: 350 | Q29: 0.0013388142
N30: Cost Recovery Pending Total | P30: 25162.51 | Q30: 0.096251217
N32: Normal | O32: Internal strategy/ discount | P32: 26502.38 | Q32: 0.10137647
O33: Lead time discrepancy between supplier/ customer | P33: 9978.85 | Q33: 0.038170932
O34: Shipment delay | P34: 8185.56 | Q34: 0.031311269 | S34: =GETPIVOTDATA("Total $",$N$3,"ORIG_PREMIUM_REASON_CODE","Normal")/1000000 -> 0.07096494
O35: Stock discrepancy | P35: 6627.43 | Q35: 0.025351136 | S35: =S34/I3 -> #DIV/0!
O36: Internal problem - Manufacturing/ Ordering/ Purchasing/ IT | P36: 5392.55 | Q36: 0.020627493
O37: P&A | P37: 4731.72 | Q37: 0.018099697
O38: Vessel delay | P38: 4570.71 | Q38: 0.017483804
O39: Payment delay - shipment blocked | P39: 1775 | Q39: 0.0067897006
O40: Cargo lost | P40: 1506.97 | Q40: 0.0057644367
O41: Project | P41: 1243.68 | Q41: 0.0047573042
O42: Supplier bankruptcy | P42: 235.83 | Q42: 0.00090209301
O43: Transferência ferramental | P43: 134.26 | Q43: 0.00051356913
O44: Freight to avoid buy high MOQ | P44: 80 | Q44: 0.00030601468
N45: Normal Total | P45: 70964.94 | Q45: 0.27145391
N47: Total Geral | P47: 261425.37 | Q47: 1

Sheet Details 2025
H1: =SUBTOTAL(9,H3:H1048576) -> 93748.62
A2: MÊS REPORTE | B2: PREMIUM_ID | C2: PBU_NAME | D2: CUSTOMER | E2: SHIPMENT_DATE | F2: PLANT_NAME | G2: SHIPMENT_TYPE | H2: ACTUAL_COST_IN_USD | I2: ESTIMATED_COST_IN_USD | J2: Percentual | K2: PREMIUM_REASON_CODE | L2: ORIG_PREMIUM_REASON_CODE | M2: SHIP_TO_NAME | N2: SHIP_FROM_NAME | O2: PROBLEM_DESCRIPTION | P2: CARRIER_NAME | Q2: PTA_NUMBER | R2: PART_NUMBERS_TEXT | S2: QUANTITY(In Pieces) | T2: WEIGHT | U2: COST_RECOVERY | V2: COMMODITY_TYPE | W2: SUBMITTED_BY_NAME | X2: SUBMIT_DATE | Y2: EDIT_DATE | Z2: REGION_NAME | AA2: RECOVERY_STATUS | AB2: RECOVERED_COST_IN_USD | AC2: RECOVERED_DATE | AD2: ORIG_FREIGHT_COST_USD | AE2: LAUNCH_PERIOD | AF2: PLANT_CODE | AG2: SOURCE_SYSTEM | AH2: RECOVERED_LC | AI2: ACTUAL_SHIP_COST_LC | AJ2: COST_RECOVERY_REQUIRED | AK2: COST_RECOVERY_TRACKING | AL2: ESTIM_SHIP_COST_LC | AM2: INVOICE_CURRENCY | AN2: SHIP_FROM_ADDRESS | AO2: SHIP_FROM_CITY | AP2: SHIP_FROM_CODE | AQ2: SHIP_FROM_COUNTRY | AR2: SHIP_FROM_REGION | AS2: SHIP_FROM_STATE | AT2: SHIP_FROM_ZIP | AU2: SHIP_TO_ADDRESS | AV2: SHIP_TO_CITY | AW2: SHIP_TO_CODE | AX2: SHIP_TO_COUNTRY | AY2: SHIP_TO_REGION | AZ2: SHIP_TO_STATE | BA2: SHIP_TO_ZIP | BB2: SEGMENT | BC2: APPROVAL_STATUS | BD2: APPROVED_BY_NAME | BE2: APPROVED_DATE | BF2: TMS_LOAD_ID | BG2: ACTUAL_CARRIER | BH2: ACTUAL_CARRIER_TRACKING_NUMBER | BI2: PREMIUM_REASON_CODE_ACTUAL | BJ2: DRIVER | BK2: ACTUAL_DRIVER | BL2: ESTIMATED_COST_SOURCE | BM2: ACTUAL_COST_SOURCE | BN2: ACTUAL_CUSTOMER | BO2: ACTUAL_SUPPLIER | BP2: TOTAL_APPROVAL_TIME | BQ2: APPROVED_LEVEL_AMOUNT(USD) | BR2: APPROVER_COMMENTS | BS2: TOTAL_COST | BT2: TOTAL_COST_LESS_RECOVERIES | BU2: NO_OF_CONTAINER | BV2: DIMENSION_OF_BOX(HxWxL) | BW2: UOM | BX2: COUNTRY | BY2: FAMILY_NAME/PROGRAM | BZ2: ESTIMATED_NAME_OF_INVOICE_CURRENCY | CA2: TOP_100_SUPPLIER | CB2: NAME_OF_RECOVERED_CURRENCY | CC2: UNIT_WEIGHTS | CD2: ADDITIONAL_COMMENTARY | CE2: ESTIMATE_INVOICE_EXCHANGE_RATE | CF2: ACTUAL_INVOICE_EXCHANGE_RATE | CG2: ACTUAL_RECOVERED_INVOICE_EXCHANGE_RATE | CH2: NORMAL_SHIPMENT_COST_IN_INVOICE_CURRENCY | CI2: NORMAL_SHIPMENT_COST_(USD) | CJ2: NAME_OF_NORMAL_SHIPMENT_INVOICE_CURRENCY | CK2: NORMAL_INVOICE_EXCHANGE_RATE | CL2: PROBLEM_REASON_CODE_ACTUAL | CM2: CANCELLATION_REMARK | CN2: SHIP_FROM_DUNS | CO2: SHIP_TO_DUNS | CP2: ACTUAL_SUPPLIER_DUNS
A3: 45658 | B3: 177109 | C3: Port Strike + Vessel delay | D3: FIAT | E3: 45659 | F3: Paraisopolis | G3: Inbound Premium | H3: 281.65 | I3: 92 | J3: =H3/$H$1 -> 0.0030043109 | K3: PORT-PORT DELAYS / STRIKE | L3: APTIV MANUFATURA E SERVICOS DE-724381 | M3: KOSTAL KONTAKT SYSTEME GMBH & CO. K-7077965 | N3: Atraso atracação Maritimo - Navio MSCRAYSHMI - Processo M1031/24 | O3: DHL Express SA | P3: PTA-00204798 | Q3: 13924340; | R3: ; | S3: ; | T3: Aptiv | U3: Premium - Productive | V3: lua.barbosa.ribeiro@aptiv.com | W3: 2025-01-06T01:14:49.55 | X3: 2025-01-14T06:25:56.55 | Y3: SA | Z3: Closed Not Recovered | AA3: 0 | AC3: 281.65 | AD3: 2025-01-08T00:00:00 | AE3: 10012 | AF3: Q11 | AH3: 281.65 | AI3: Non-Recoverable | AK3: 92 | AL3: USD | AM3: ZUM TIMBERG 2 | AN3: LUEDENSCHEID | AO3: 7077965 | AP3: DE | AQ3: EMEA | AR3: NW | AS3: 58513 | AT3: AVENIDA AVELINO RIBEIRO, 900 | AU3: PARAISOPOLIS | AV3: 724381 | AW3: BR | AX3: SA | AY3: MG | AZ3: 37660-000 | BA3: SPS | BB3: Approved | BC3: Carvalho, Eliane R | BD3: 2025-01-06T01:57:44.00 | BE3: 0 | BG3: 7417002143 | BI3: Significant_event | BK3: Invoice | BL3: Invoice | BO3: 0 Days 0 Hr 42 Min | BP3: 250 | BQ3: Approved - ;; Approved - ; | BR3: 281.65 | BS3: 281.65 | BT3: ; | BU3: ; | BV3: ; | BW3: BR | BX3: Turbo T3 | BY3: USD | CD3: 1 | CE3: 1 | CH3: 0 | CM3: 340852585 | CQ3: No | CS3: No | CT3: $ 0 - 500 | CU3: $ 0 - 500 | CV3: PORT-PORT DELAYS / STRIKE | CW3: Inbound Premium | CX3: Significant_event | CY3: Approved After Shipment | DA3: william.de.siqueira@aptiv.com | DB3: FIAT | DC3: 1 | DD3: 2 | DF3: KOSTAL INDUSTRIE GMBH & CO. KG
A4: 45658 | B4: 177107 | C4: Port Strike + Vessel delay - Consulta CC22 | D4: FIAT | E4: 45660 | F4: Ouros | G4: Inbound Premium | H4: 801.3 | I4: 1340 | J4: =H4/$H$1 -> 0.0085473258 | K4: PORT-PORT DELAYS / STRIKE | L4: APTIV MANUFATURA E SERVICOS DE-743893 | M4: APTIV HOLDINGS (AUSTRIA) GMBH-1037261 | N4: DELAY ATTRACTION PORT IN SANTOS | O4: DHL Express SA | P4: PTA-00205338 | Q4: 10740372; | R4: ; | S4: ; | T4: Aptiv | U4: Premium - Productive | V4: lua.barbosa.ribeiro@aptiv.com | W4: 2025-01-06T01:12:54.92 | X4: 2025-01-14T06:24:38.58 | Y4: SA | Z4: Closed Recovered | AA4: 0 | AC4: 801.3 | AD4: 2025-01-08T00:00:00 | AE4: 10023 | AF4: Q11 | AH4: 801.3 | AI4: Non-Recoverable | AK4: 1340 | AL4: USD | AM4: INDUSTRIESTRASSE 1 | AN4: GROSSPETERSDORF | AO4: 1037261 | AP4: AT | AQ4: EMEA | AR4: 1 | AS4: 7503 | AT4: TV ANTONIO E FONSECA 250 BAIRRO | AU4: CONCEICAO DOS OUROS | AV4: 743893 | AW4: BR | AX4: SA | AY4: MG | AZ4: 37548-000 | BA4: SPS | BB4: Approved | BC4: Flores, Lorena | BD4: 2025-01-09T07:04:05.00 | BE4: 0 | BG4: 4478753790 | BI4: Significant_event | BK4: Invoice | BL4: Invoice | BO4: 3 Days 5 Hr 51 Min | BQ4: Approved - ;; Approved - ;; Approved - ;; Approved - ;; Approved - Approved by e-mail 1/9. ; | BR4: 801.3 | BS4: 801.3 | BT4: ; | BU4: ; | BV4: ; | BW4: BR | BX4: GSE | BY4: USD | CD4: 1 | CE4: 1 | CH4: 0 | CM4: 219757144 | CQ4: No | CS4: No | CT4: $ 500- 2500 | CU4: $ 500- 2500 | CV4: PORT-PORT DELAYS / STRIKE | CW4: Inbound Premium | CX4: Significant_event | CY4: Approved After Shipment | CZ4: RECUPERADO SMART CC22 | DA4: william.de.siqueira@aptiv.com | DB4: FIAT | DC4: 1 | DD4: 3 | DF4: APTIV GLOBAL INVESTMENTS UK LLP
A5: 45658 | B5: 177110 | C5: Port Strike + Vessel delay - Consulta CC22 | D5: PSA | E5: 45660 | F5: Paraisopolis | G5: Inbound Premium | H5: 480 | I5: 480 | J5: =H5/$H$1 -> 0.0051200754 | K5: PORT-PORT DELAYS / STRIKE | L5: APTIV MANUFATURA E SERVICOS DE-724381 | M5: SANTOS-Dummy | N5: Atraso atracação Navio CISNES - processo M0979/24 | O5: EMPRESA DE TRANSPORTES COVRE | P5: PTA-00204804 | Q5: 35072837; | R5: ; | S5: ; | T5: Aptiv | U5: Premium - Productive | V5: lua.barbosa.ribeiro@aptiv.com | W5: 2025-01-06T01:16:14.34 | X5: 2025-01-14T06:26:44.30 | Y5: SA | Z5: Closed Recovered | AA5: 0 | AC5: 480 | AD5: 2025-01-06T00:00:00 | AE5: 10012 | AF5: Q11 | AH5: 480 | AI5: Non-Recoverable | AK5: 480 | AL5: USD | AM5: Porto Santos | AN5: Santos | AO5: Dummy | AP5: BR | AQ5: SA | AR5: São Paulo | AS5: 1 | AT5: AVENIDA AVELINO RIBEIRO, 900 | AU5: PARAISOPOLIS | AV5: 724381 | AW5: BR | AX5: SA | AY5: MG | AZ5: 37660-000 | BA5: SPS | BB5: Approved | BC5: Edilson, Geraldo | BD5: 2025-01-06T02:09:38.00 | BE5: 0 | BG5: N/A | BI5: Significant_event | BK5: Invoice | BL5: Invoice | BO5: 0 Days 0 Hr 53 Min | BP5: 500 | BQ5: Approved - ;; Approved - ;; Approved - ; | BR5: 480 | BS5: 480 | BT5: ; | BU5: ; | BV5: ; | BW5: BR | BX5: BODY CC24 | BY5: USD | CD5: 1 | CE5: 1 | CH5: 0 | CQ5: No | CS5: No | CT5: $ 0 - 500 | CU5: $ 0 - 500 | CV5: PORT-PORT DELAYS / STRIKE | CW5: Inbound Premium | CX5: Significant_event | CY5: Approved After Shipment | CZ5: CONSULTA CC22 SMART | DA5: william.de.siqueira@aptiv.com | DB5: PSA | DC5: 1 | DD5: 3
A6: 45658 | B6: 177111 | C6: Port Strike + Vessel delay | D6: FIAT | E6: 45660 | F6: Paraisopolis | G6: Inbound Premium | H6: 480 | I6: 480 | J6: =H6/$H$1 -> 0.0051200754 | K6: PORT-PORT DELAYS / STRIKE | L6: APTIV MANUFATURA E SERVICOS DE-724381 | M6: SANTOS-Dummy | N6: Atraso atracação Navio Cisnes - Processo M1004/24 | O6: EMPRESA DE TRANSPORTES COVRE | P6: PTA-00204803 | Q6: M5057051; | R6: ; | S6: ; | T6: Aptiv | U6: Premium - Productive | V6: lua.barbosa.ribeiro@aptiv.com | W6: 2025-01-06T01:17:02.99 | X6: 2025-01-14T06:27:31.53 | Y6: SA | Z6: Closed Not Recovered | AA6: 0 | AC6: 480 | AD6: 2025-01-06T00:00:00 | AE6: 10012 | AF6: Q11 | AH6: 480 | AI6: Non-Recoverable | AK6: 480 | AL6: USD | AM6: Porto Santos | AN6: Santos | AO6: Dummy | AP6: BR | AQ6: SA | AR6: São Paulo | AS6: 1 | AT6: AVENIDA AVELINO RIBEIRO, 900 | AU6: PARAISOPOLIS | AV6: 724381 | AW6: BR | AX6: SA | AY6: MG | AZ6: 37660-000 | BA6: SPS | BB6: Approved | BC6: Edilson, Geraldo | BD6: 2025-01-06T02:09:29.00 | BE6: 0 | BG6: N/A | BI6: Significant_event | BK6: Invoice | BL6: Invoice | BO6: 0 Days 0 Hr 52 Min | BP6: 500 | BQ6: Approved - ;; Approved - ;; Approved - ; | BR6: 480 | BS6: 480 | BT6: ; | BU6: ; | BV6: ; | BW6: BR | BX6: PROJETO P | BY6: USD | CD6: 1 | CE6: 1 | CH6: 0 | CQ6: No | CS6: No | CT6: $ 0 - 500 | CU6: $ 0 - 500 | CV6: PORT-PORT DELAYS / STRIKE | CW6: Inbound Premium | CX6: Significant_event | CY6: Approved After Shipment | DA6: william.de.siqueira@aptiv.com | DB6: FIAT | DC6: 1 | DD6: 3
A7: 45658 | B7: 176665 | C7: Customer reschedule - Consulta 43 | D7: JOHN DEERE | E7: 45663 | F7: Paraisopolis | G7: Inbound Premium | H7: 536.55 | I7: 633 | J7: =H7/$H$1 -> 0.0057232842 | K7: S2-External Customer driven schedule changes | L7: APTIV MANUFATURA E SERVICOS DE-724381 | M7: JUDD WIRE-726536 | N7: INCREASE OF CUSTOMER | O7: DHL Express SA | P7: PTA-00204614 | Q7: M3154279; | R7: ; | S7: ; | T7: Customer | U7: Premium - Productive | V7: Moraes.Arnaldo@aptiv.com | W7: 2024-12-31T01:12:40.35 | X7: 2025-01-21T11:52:08.77 | Y7: SA | Z7: Closed Recovered | AA7: 0 | AC7: 536.55 | AE7: 10012 | AF7: Q11 | AH7: 536.55 | AI7: Recoverable | AK7: 633 | AL7: USD | AM7: 124 TURNPIKE RD | AN7: TURNERS FALLS | AO7: 726536 | AP7: US | AQ7: NA | AR7: MA | AS7: 01376-2699 | AT7: AVENIDA AVELINO RIBEIRO, 900 | AU7: PARAISOPOLIS | AV7: 724381 | AW7: BR | AX7: SA | AY7: MG | AZ7: 37660-000 | BA7: SPS | BB7: Approved | BC7: Naus, Angelica | BD7: 2025-01-02T07:08:50.00 | BE7: 0 | BG7: DTW0380701 | BI7: Customer | BK7: Invoice | BL7: Invoice | BM7: JOHN DEERE | BO7: 2 Days 5 Hr 56 Min | BP7: 800 | BQ7: Approved - ;; Approved - ;; Approved - ;; Approved - ; | BR7: 536.55 | BS7: 536.55 | BT7: ; | BU7: ; | BV7: ; | BW7: BR | BX7: 8R | BY7: USD | CC7: Reprograma JD,CONSULTA 43 | CD7: 1 | CE7: 1 | CH7: 0 | CQ7: No | CS7: No | CT7: $ 500- 2500 | CU7: $ 500- 2500 | CV7: S2-External Customer driven schedule changes | CW7: Inbound Premium | CX7: Customer | CY7: Approved Prior To Shipment | CZ7: Recuperado consulta Horizontina | DB7: JOHN DEERE | DC7: 1 | DD7: 6
A8: 45658 | B8: 176666 | C8: Customer reschedule - Consulta 43 | D8: JOHN DEERE | E8: 45663 | F8: Paraisopolis | G8: Inbound Premium | H8: 450.08 | I8: 803 | J8: =H8/$H$1 -> 0.004800924 | K8: S2-External Customer driven schedule changes | L8: APTIV MANUFATURA E SERVICOS DE-724381 | M8: LEONI CABLE, INC.-1089906 | N8: INCREASE OF CUSTOMER | O8: DHL Express SA | P8: PTA-00204666 | Q8: M7600106; | R8: ; | S8: ; | T8: Customer | U8: Premium - Productive | V8: Moraes.Arnaldo@aptiv.com | W8: 2024-12-31T01:22:09.94 | X8: 2025-01-17T12:04:16.64 | Y8: SA | Z8: Closed Recovered | AA8: 0 | AC8: 450.08 | AE8: 10012 | AF8: Q11 | AH8: 450.08 | AI8: Recoverable | AK8: 803 | AL8: USD | AM8: 1100 BURGUNDY DRIVE | AN8: EL PASO | AO8: 1089906 | AP8: US | AQ8: NA | AR8: TX | AS8: 79907 | AT8: AVENIDA AVELINO RIBEIRO, 900 | AU8: PARAISOPOLIS | AV8: 724381 | AW8: BR | AX8: SA | AY8: MG | AZ8: 37660-000 | BA8: SPS | BB8: Approved | BC8: Laporte, Greg | BD8: 2025-01-03T01:06:44.00 | BE8: 0 | BG8: DTW0380846 | BI8: Customer | BK8: Invoice | BL8: Invoice | BM8: JOHN DEERE | BO8: 2 Days 23 Hr 44 Min | BP8: 5000 | BQ8: Approved - ;; Approved - ;; Approved - ;; Approved - ;; Approved - ; | BR8: 450.08 | BS8: 450.08 | BT8: ; | BU8: ; | BV8: ; | BW8: BR | BX8: CARDIAL | BY8: USD | CC8: Reprograma JD,CONSULTA 43 | CD8: 1 | CE8: 1 | CH8: 0 | CM8: 300881192 | CQ8: No | CS8: No | CT8: $ 500- 2500 | CU8: $ 0 - 500 | CV8: S2-External Customer driven schedule changes | CW8: Inbound Premium | CX8: Customer | CY8: Approved Prior To Shipment | DB8: JOHN DEERE | DC8: 1 | DD8: 6 | DF8: PIERER INVEST GMBH
A9: 45658 | B9: 177331 | C9: Customer reschedule - Consulta 44 | D9: JOHN DEERE | E9: 45663 | F9: Paraisopolis | G9: Inbound Premium | H9: 1004.17 | I9: 1004.17 | J9: =H9/$H$1 -> 0.010711304 | K9: C4-Capacity-External Customer Resp | L9: Paraisopolis-10012 | M9: COMERCIALIZADORA CORDAFLEX, S.A. DE-1069092 | N9: INCREASE OF CUSTOMER | O9: DSV UTI Air & Sea Agenciamento de Transportes | P9: PTA-00205342 | Q9: M3075501; | R9: ; | S9: ; | T9: Customer | U9: Premium - Productive | V9: rodrigo.fernandes@aptiv.com | W9: 2025-01-07T04:20:44.07 | X9: 2025-01-09T07:05:26.00 | Y9: SA | Z9: Open | AA9: 0 | AC9: 0 | AE9: 10012 | AF9: Q11 | AI9: Recoverable | AK9: 1004.17 | AM9: CARRETERA PANAMERICANA KM. 230.6 | AN9: CORREGIDORA | AO9: 1069092 | AP9: MX | AQ9: NA | AR9: BCN | AS9: 76900 | AT9: Av. Avelino Ribeiro, 900 | AU9: Paraisopolis | AV9: 10012 | AW9: BR | AX9: SA | AY9: Minas Gerais | AZ9: 37660-000 | BA9: SPS | BB9: Approved | BC9: Flores, Lorena | BD9: 2025-01-09T07:05:26.00 | BE9: 0 | BI9: Customer | BK9: Invoice | BM9: JOHN DEERE | BO9: 2 Days 2 Hr 44 Min | BQ9: Approved - ;; Approved - ;; Approved - ;; Approved - Approved by e-mail 1/9. ; | BR9: 1004.17 | BS9: 1004.17 | BT9: ; | BU9: ; | BV9: ; | BW9: BR | BX9: EINSTEIN | BY9: USD | CC9: Reprograma JD,CONSULTA 44 | CD9: 1 | CH9: 0 | CM9: 812798196 | CQ9: No | CS9: No | CT9: $ 500- 2500 | CV9: C4-Capacity-External Customer Resp | CW9: Inbound Premium | CX9: Customer | CY9: Approved After Shipment | DA9: rodrigo.fernandes@aptiv.com | DB9: JOHN DEERE | DC9: 1 | DD9: 6 | DF9: COMERCIALIZADORA CORDAFLEX, S.A. DE C.V.
A10: 45658 | B10: 177142 | C10: Customer rescheduled - Consulta CC22 | D10: PSA | E10: 45664 | F10: Paraisopolis | G10: Inbound Premium | H10: 421.87 | I10: 315 | J10: =H10/$H$1 -> 0.0045000129 | K10: B2-Behind Schedule-Aptiv | L10: APTIV MANUFATURA E SERVICOS DE-733223 | M10: APTIV HOLDINGS FRANCE SAS-7079149 | N10: Reprograma dentro do acordo logistico. | O10: DHL Express SA | P10: PTA-00204919 | Q10: 13737770; | R10: ; | S10: ; | T10: Aptiv | U10: Premium - Productive | V10: lua.barbosa.ribeiro@aptiv.com | W10: 2025-01-06T02:50:38.59 | X10: 2025-01-14T06:33:08.76 | Y10: SA | Z10: Closed Recovered | AA10: 0 | AC10: 421.87 | AD10: 2025-01-14T00:00:00 | AE10: 10012 | AF10: Q11 | AH10: 421.87 | AI10: Non-Recoverable | AK10: 315 | AL10: USD | AM10: ZONE INDUSTRIELLE | AN10: EPERNON | AO10: 7079149 | AP10: FR | AQ10: EMEA | AR10: 28 | AS10: 28230 | AT10: AVENIDA AVELINO RIBEIRO, 900 | AU10: PARAISOPOLIS | AV10: 733223 | AW10: BR | AX10: SA | AY10: MG | AZ10: 37660-000 | BA10: SPS | BB10: Approved | BC10: Edilson, Geraldo | BD10: 2025-01-07T11:46:38.00 | BE10: 0 | BG10: 8316409706 | BI10: Aptiv | BK10: Invoice | BL10: Invoice | BO10: 0 Days 20 Hr 56 Min | BP10: 500 | BQ10: Approved - ;; Approved - ;; Approved - ; | BR10: 421.87 | BS10: 421.87 | BT10: ; | BU10: ; | BV10: ; | BW10: BR | BX10: BODY CC24 | BY10: USD | CC10: 10738188 | CD10: 1 | CE10: 1 | CH10: 0 | CM10: 219757144 | CQ10: No | CS10: No | CT10: $ 0 - 500 | CU10: $ 0 - 500 | CV10: B2-Behind Schedule-Aptiv | CW10: Inbound Premium | CX10: Aptiv | CY10: Approved Day Of Shipment | CZ10: CONSULTA CC22 SMART | DA10: william.de.siqueira@aptiv.com | DB10: PSA | DC10: 1 | DD10: 7 | DF10: APTIV GLOBAL INVESTMENTS UK LLP
A11: 45658 | B11: 177173 | C11: Port Strike + Vessel delay | D11: PSA | E11: 45664 | F11: Paraisopolis | G11: Inbound Premium | H11: 480 | I11: 480 | J11: =H11/$H$1 -> 0.0051200754 | K11: PORT-PORT DELAYS / STRIKE | L11: APTIV MANUFATURA E SERVICOS DE-724381 | M11: SANTOS-Dummy | N11: Atraso atracação Navio Cisnes - Processo M0977/24 | O11: EMPRESA DE TRANSPORTES COVRE | P11: PTA-00204920 | Q11: 13893671; | R11: ; | S11: ; | T11: Aptiv | U11: Premium - Productive | V11: lua.barbosa.ribeiro@aptiv.com | W11: 2025-01-06T05:19:06.62 | X11: 2025-01-14T06:28:09.38 | Y11: SA | Z11: Closed Not Recovered | AA11: 0 | AC11: 480 | AD11: 2025-01-07T00:00:00 | AE11: 10012 | AF11: Q11 | AH11: 480 | AI11: Non-Recoverable | AK11: 480 | AL11: USD | AM11: Porto Santos | AN11: Santos | AO11: Dummy | AP11: BR | AQ11: SA | AR11: São Paulo | AS11: 1 | AT11: AVENIDA AVELINO RIBEIRO, 900 | AU11: PARAISOPOLIS | AV11: 724381 | AW11: BR | AX11: SA | AY11: MG | AZ11: 37660-000 | BA11: SPS | BB11: Approved | BC11: Edilson, Geraldo | BD11: 2025-01-07T11:46:49.00 | BE11: 0 | BG11: N/A | BI11: Significant_event | BK11: Invoice | BL11: Invoice | BO11: 0 Days 18 Hr 27 Min | BP11: 500 | BQ11: Approved - ;; Approved - ;; Approved - ; | BR11: 480 | BS11: 480 | BT11: ; | BU11: ; | BV11: ; | BW11: BR | BX11: BODY CC24 | BY11: USD | CD11: 1 | CE11: 1 | CH11: 0 | CQ11: No | CS11: No | CT11: $ 0 - 500 | CU11: $ 0 - 500 | CV11: PORT-PORT DELAYS / STRIKE | CW11: Inbound Premium | CX11: Significant_event | CY11: Approved Day Of Shipment | DA11: william.de.siqueira@aptiv.com | DB11: PSA | DC11: 1 | DD11: 7
A12: 45658 | B12: 177332 | C12: Port Strike + Vessel delay- Consulta CC22 | D12: FIAT | E12: 45664 | F12: Paraisopolis | G12: Inbound Premium | H12: 1115.47 | I12: 1115.47 | J12: =H12/$H$1 -> 0.011898522 | K12: PORT-PORT DELAYS / STRIKE | L12: Paraisopolis-10012 | M12: MTA ANTENNE SRL-7107642 | N12: Port Delays | O12: DSV UTI Air & Sea Agenciamento de Transportes | P12: PTA-00205339 | Q12: 15363920; | R12: ; | S12: ; | T12: Aptiv | U12: Premium - Productive | V12: rodrigo.fernandes@aptiv.com | W12: 2025-01-07T04:21:41.54 | X12: 2025-01-14T01:30:54.95 | Y12: SA | Z12: Closed Recovered | AA12: 0 | AC12: 0 | AE12: 10012 | AF12: Q11 | AI12: Non-Recoverable | AK12: 1115.47 | AM12: VIALE DELLINDUSTRIA 12 | AN12: CODOGNO | AO12: 7107642 | AP12: IT | AQ12: EMEA | AR12: LO | AS12: 26845 | AT12: Av. Avelino Ribeiro, 900 | AU12: Paraisopolis | AV12: 10012 | AW12: BR | AX12: SA | AY12: Minas Gerais | AZ12: 37660-000 | BA12: SPS | BB12: Approved | BC12: Flores, Lorena | BD12: 2025-01-09T07:04:23.00 | BE12: 0 | BI12: Significant_event | BK12: Invoice | BO12: 2 Days 2 Hr 42 Min | BQ12: Approved - ;; Approved - ;; Approved - ;; Approved - Approved by e-mail 1/9. ; | BR12: 1115.47 | BS12: 1115.47 | BT12: ; | BU12: ; | BV12: ; | BW12: BR | BX12: Projeto P | BY12: USD | CC12: Port Delays: 15363920, 35381256, 13788476 | CD12: 1 | CH12: 0 | CM12: 428456263 | CQ12: No | CS12: No | CT12: $ 500- 2500 | CV12: PORT-PORT DELAYS / STRIKE | CW12: Inbound Premium | CX12: Significant_event | CY12: Approved After Shipment | CZ12: CONSULTA SMART CC22 | DA12: rodrigo.fernandes@aptiv.com | DB12: FIAT | DC12: 1 | DD12: 7 | DF12: MTA SPA
A13: 45658 | B13: 176940 | C13: Stock Divergence | D13: Mercedes-Benz | E13: 45665 | F13: Paraisopolis | G13: Inbound Premium | H13: 92.28 | I13: 93 | J13: =H13/$H$1 -> 0.00098433449 | K13: S1I-Inventory loss/adjustments | L13: APTIV MANUFATURA E SERVICOS DE-724381 | M13: HIRSCHMANN AUTOMOTIVE GMBH-7010627 | N13: Divergencia de estoque/recebimento. | O13: DHL Express SA | P13: PTA-00205106 | Q13: 13741709; | R13: ; | S13: ; | T13: Aptiv | U13: Premium - Productive | V13: lua.barbosa.ribeiro@aptiv.com | W13: 2025-01-08T01:49:05.96 | X13: 2025-01-14T06:40:50.32 | Y13: SA | Z13: Closed Not Recovered | AA13: 0 | AC13: 92.28 | AD13: 2025-01-15T00:00:00 | AE13: 10012 | AF13: Q11 | AH13: 92.28 | AI13: Non-Recoverable | AK13: 93 | AL13: USD | AM13: OBERER PASPELSWEG 6-8 | AN13: RANKWEIL | AO13: 7010627 | AP13: AT | AQ13: EMEA | AR13: 8 | AS13: 6830 | AT13: AVENIDA AVELINO RIBEIRO, 900 | AU13: PARAISOPOLIS | AV13: 724381 | AW13: BR | AX13: SA | AY13: MG | AZ13: 37660-000 | BA13: SPS | BB13: Approved | BC13: Edilson, Geraldo | BD13: 2025-01-08T02:41:12.00 | BE13: 0 | BG13: 6775746246 | BI13: Aptiv | BK13: Invoice | BL13: Invoice | BO13: 0 Days 0 Hr 52 Min | BP13: 500 | BQ13: Approved - ;; Approved - ; | BR13: 92.28 | BS13: 92.28 | BT13: ; | BU13: ; | BV13: ; | BW13: BR | BX13: MOTOR MBB | BY13: USD | CD13: 1 | CE13: 1 | CH13: 0 | CM13: 300733438 | CQ13: No | CS13: No | CT13: $ 0 - 500 | CU13: $ 0 - 500 | CV13: S1I-Inventory loss/adjustments | CW13: Inbound Premium | CX13: Aptiv | CY13: Approved Day Of Shipment | DA13: william.de.siqueira@aptiv.com | DB13: Mercedes-Benz | DC13: 1 | DD13: 8 | DF13: F & R INDUSTRIEBETEILIGUNGEN GMBH
A14: 45658 | B14: 177633 | C14: Customer rescheduled - Consulta 40 | D14: CNH COMBINE | E14: 45666 | F14: Paraisopolis | G14: Inbound Premium | H14: 101.19 | I14: 84.78 | J14: =H14/$H$1 -> 0.0010793759 | K14: S2-External Customer driven schedule changes | L14: APTIV MANUFATURA E SERVICOS DE-724381 | M14: APTIV WARREN (FR09)-725458 | N14: REPROGRAMA DO CLIENTE | O14: DHL Express SA | P14: PTA-00205273 | Q14: 13783293; | R14: ; | S14: ; | T14: Customer | U14: Premium - Productive | V14: Moraes.Arnaldo@aptiv.com | W14: 2025-01-08T04:48:59.41 | X14: 2025-01-14T05:18:00.83 | Y14: SA | Z14: Closed Recovered | AA14: 0 | AC14: 101.19 | AE14: 10012 | AF14: Q11 | AH14: 101.19 | AI14: Recoverable | AK14: 84.78 | AL14: USD | AM14: 1265 N RIVER RD | AN14: WARREN | AO14: 725458 | AP14: US | AQ14: NA | AR14: OH | AS14: 44483 | AT14: AVENIDA AVELINO RIBEIRO, 900 | AU14: PARAISOPOLIS | AV14: 724381 | AW14: BR | AX14: SA | AY14: MG | AZ14: 37660-000 | BA14: SPS | BB14: Approved | BC14: Edilson, Geraldo | BD14: 2025-01-09T01:35:09.00 | BE14: 0 | BG14: 99299618551 | BI14: Customer | BK14: Invoice | BL14: Invoice | BM14: CNH COMBINE | BO14: 0 Days 20 Hr 46 Min | BP14: 500 | BQ14: Approved - ;; Approved - ; | BR14: 101.19 | BS14: 101.19 | BT14: ; | BU14: ; | BV14: ; | BW14: BR | BX14: SUGAR CANE | BY14: USD | CC14: CONSULTA 40-CNH Sugar cane | CD14: 1 | CE14: 1 | CH14: 0 | CQ14: No | CS14: No | CT14: $ 0 - 500 | CU14: $ 0 - 500 | CV14: S2-External Customer driven schedule changes | CW14: Inbound Premium | CX14: Customer | CY14: Approved Day Of Shipment | CZ14: CONSULTA 40 - CLIENTE CNH | DB14: CNH COMBINE | DC14: 1 | DD14: 9
A15: 45658 | B15: 177638 | C15: Customer reschedule - Consulta 43 | D15: JOHN DEERE | E15: 45666 | F15: Paraisopolis | G15: Inbound Premium | H15: 115.44 | I15: 123.06 | J15: =H15/$H$1 -> 0.0012313781 | K15: S4S-External Customer driven systems issues | L15: APTIV MANUFATURA E SERVICOS DE-724381 | M15: APTIV CENTEC III (FW84)-725455 | N15: REPROGRAMA DO CLIENTE | O15: DHL Express SA | P15: PTA-00205274 | Q15: 12103504; | R15: ; | S15: ; | T15: Customer | U15: Premium - Productive | V15: Moraes.Arnaldo@aptiv.com | W15: 2025-01-08T04:58:45.59 | X15: 2025-01-17T12:06:43.90 | Y15: SA | Z15: Closed Recovered | AA15: 0 | AC15: 115.44 | AE15: 10012 | AF15: Q11 | AH15: 115.44 | AI15: Recoverable | AK15: 123.06 | AL15: USD | AM15: BOULEVARD ALPHA #955 | AN15: RAMOS ARIZPE | AO15: 725455 | AP15: MX | AQ15: NA | AR15: COA | AS15: 25903 | AT15: AVENIDA AVELINO RIBEIRO, 900 | AU15: PARAISOPOLIS | AV15: 724381 | AW15: BR | AX15: SA | AY15: MG | AZ15: 37660-000 | BA15: SPS | BB15: Approved | BC15: Edilson, Geraldo | BD15: 2025-01-09T01:35:16.00 | BE15: 0 | BG15: 1622038655 | BI15: Customer | BK15: Invoice | BL15: Invoice | BM15: JOHN DEERE | BO15: 0 Days 20 Hr 36 Min | BP15: 500 | BQ15: Approved - ;; Approved - ; | BR15: 115.44 | BS15: 115.44 | BT15: ; | BU15: ; | BV15: ; | BW15: BR | BX15: EINSTEN | BY15: USD | CC15: CONSULTA 43 - Reprograma JD | CD15: 1 | CE15: 1 | CH15: 0 | CQ15: No | CS15: No | CT15: $ 0 - 500 | CU15: $ 0 - 500 | CV15: S4S-External Customer driven systems issues | CW15: Inbound Premium | CX15: Customer | CY15: Approved Day Of Shipment | CZ15: CONSULTA 43 - JD HORIZONTINA | DB15: JOHN DEERE | DC15: 1 | DD15: 9
A16: 45658 | B16: 177810 | C16: Return of Material | D16: FIAT | E16: 45666 | F16: Ouros | G16: Outbound Premium | H16: 330 | I16: 330 | J16: =H16/$H$1 -> 0.0035200518 | K16: OOOT-Other/Sales | L16: FCA FIAT CHRYSLER AUTOMOTIVES-766873 | M16: Paraisopolis-10012 | N16: Devolução de materia prima para a FIAT de Jaboatão | O16: Brix | P16: PTA-00205271 | Q16: *; | R16: ; | S16: ; | T16: Aptiv | U16: Premium - Returnable Containers | V16: rodrigo.fernandes@aptiv.com | W16: 2025-01-09T10:34:26.82 | X16: 2025-01-09T01:34:50.00 | Y16: SA | Z16: Closed Not Recovered | AA16: 0 | AC16: 0 | AE16: 10023 | AF16: Q11 | AI16: Non-Recoverable | AK16: 330 | AM16: Av. Avelino Ribeiro, 900 | AN16: Paraisopolis | AO16: 10012 | AP16: BR | AQ16: SA | AR16: Minas Gerais | AS16: 37660-000 | AT16: RODOVIA BR101 SUL KM86.2 S/N | AU16: JABOATAO GUARARAPES | AV16: 766873 | AW16: BR | AX16: SA | AY16: BR | AZ16: 54335-000 | BA16: SPS | BB16: Approved | BC16: Edilson, Geraldo | BD16: 2025-01-09T01:34:50.00 | BE16: 0 | BI16: Aptiv | BK16: Invoice | BO16: 0 Days 3 Hr 0 Min | BP16: 500 | BQ16: Approved - ;; Approved - ; | BR16: 330 | BS16: 330 | BT16: ; | BU16: ; | BV16: ; | BW16: BR | BX16: Jaboatão | BY16: USD | CC16: Devolução de materia prima para a FIAT de Jaboatão | CD16: 1 | CH16: 0 | CQ16: No | CS16: No | CT16: $ 0 - 500 | CV16: OOOT-Other/Sales | CW16: Outbound Premium | CX16: Aptiv | CY16: Approved Day Of Shipment | DA16: william.de.siqueira@aptiv.com | DB16: FIAT | DC16: 1 | DD16: 9
A17: 45658 | B17: 177822 | C17: Customer reschedule | D17: PSA | E17: 45666 | F17: Paraisopolis | G17: Inbound Premium | H17: 242.31 | I17: 220 | J17: =H17/$H$1 -> 0.002584678 | K17: S2-External Customer driven schedule changes | L17: APTIV MANUFATURA E SERVICOS DE-724381 | M17: APTIV HOLDINGS (AUSTRIA) GMBH-1037261 | N17: Reprograma PSA - Custo já recuperado do cliente. | O17: DHL Express SA | P17: PTA-00205272 | Q17: 15458151; | R17: ; | S17: ; | T17: Customer | U17: Premium - Productive | V17: lua.barbosa.ribeiro@aptiv.com | W17: 2025-01-09T11:09:44.95 | X17: 2025-01-14T06:38:41.98 | Y17: SA | Z17: Closed Recovered | AA17: 0 | AC17: 242.31 | AD17: 2025-01-15T00:00:00 | AE17: 10012 | AF17: Q11 | AH17: 242.31 | AI17: Recoverable | AK17: 220 | AL17: USD | AM17: INDUSTRIESTRASSE 1 | AN17: GROSSPETERSDORF | AO17: 1037261 | AP17: AT | AQ17: EMEA | AR17: 1 | AS17: 7503 | AT17: AVENIDA AVELINO RIBEIRO, 900 | AU17: PARAISOPOLIS | AV17: 724381 | AW17: BR | AX17: SA | AY17: MG | AZ17: 37660-000 | BA17: SPS | BB17: Approved | BC17: Edilson, Geraldo | BD17: 2025-01-09T01:34:59.00 | BE17: 0 | BG17: 3896114725 | BI17: Customer | BK17: Invoice | BL17: Invoice | BM17: PSA | BO17: 0 Days 2 Hr 25 Min | BP17: 500 | BQ17: Approved - ;; Approved - ; | BR17: 242.31 | BS17: 242.31 | BT17: ; | BU17: ; | BV17: ; | BW17: BR | BX17: BODY CC22 | BY17: USD | CD17: 1 | CE17: 1 | CH17: 0 | CM17: 219757144 | CQ17: No | CS17: No | CT17: $ 0 - 500 | CU17: $ 0 - 500 | CV17: S2-External Customer driven schedule changes | CW17: Inbound Premium | CX17: Customer | CY17: Approved Day Of Shipment | DA17: william.de.siqueira@aptiv.com | DB17: PSA | DC17: 1 | DD17: 9 | DF17: APTIV GLOBAL INVESTMENTS UK LLP
A18: 45658 | B18: 177828 | C18: Supplier Delay | D18: PSA | E18: 45666 | F18: Paraisopolis | G18: Inbound Premium | H18: 1113 | I18: 1113 | J18: =H18/$H$1 -> 0.011872175 | K18: B3-Behind Schedule-External Supplier | L18: APTIV MANUFATURA E SERVICOS DE-724381 | M18: OPTIMAS OE SOLUTIONS-7082485 | N18: Delay from supplier due to lack of material. | O18: DHL Express SA | Q18: 13567904; | R18: ; | S18: ; | T18: Supplier | U18: Premium - Productive | V18: lua.barbosa.ribeiro@aptiv.com | W18: 2025-01-09T11:36:48.16 | X18: 2025-01-09T11:36:12.41 | Y18: SA | Z18: Open | AA18: 0 | AC18: 0 | AD18: 2025-01-15T00:00:00 | AE18: 10012 | AF18: Q11 | AI18: Recoverable | AK18: 1113 | AM18: 9 RUE GUTENBERG | AN18: SARREGUEMINES | AO18: 7082485 | AP18: FR | AQ18: EMEA | AR18: 57 | AS18: 57200 | AT18: AVENIDA AVELINO RIBEIRO, 900 | AU18: PARAISOPOLIS | AV18: 724381 | AW18: BR | AX18: SA | AY18: MG | AZ18: 37660-000 | BA18: SPS | BB18: Pending | BE18: 0 | BI18: Supplier | BK18: Invoice | BN18: OPTIMAS OE SOLUTIONS-1068927 | BP18: 0 | BQ18: Approved - ;; Approved - ;; Pending - | BR18: 1113 | BS18: 1113 | BT18: ; | BU18: ; | BV18: ; | BW18: BR | BX18: BODY CC22 | BY18: USD | BZ18: 762735 | CC18: 13724539 | CD18: 1 | CH18: 0 | CM18: 079793017 | CO18: 079793017 | CQ18: No | CS18: No | CT18: $ 500- 2500 | CV18: B3-Behind Schedule-External Supplier | CW18: Inbound Premium | CX18: Supplier | CY18: Not Yet Approved | DA18: william.de.siqueira@aptiv.com | DB18: PSA | DC18: 1 | DD18: 9 | DE18: OPTIMAS OE SOLUTIONS INTERMEDIATE, LLC | DF18: OPTIMAS OE SOLUTIONS INTERMEDIATE, LLC
A19: 45658 | B19: 177851 | C19: Customer reschedule | D19: PSA | E19: 45666 | F19: Paraisopolis | G19: Inbound Premium | H19: 1332.34 | I19: 1332.34 | J19: =H19/$H$1 -> 0.014211836 | K19: S4S-External Customer driven systems issues | L19: Paraisopolis-10012 | M19: MECATRACTION-7009627 | N19: Increase of Customer | O19: DSV UTI Air & Sea Agenciamento de Transportes | Q19: 33130556; | R19: ; | S19: ; | T19: Customer | U19: Premium - Productive | V19: rodrigo.fernandes@aptiv.com | W19: 2025-01-17T06:13:02.63 | X19: 2025-01-17T06:12:38.91 | Y19: SA | Z19: Closed Recovered | AA19: 0 | AC19: 0 | AE19: 10012 | AF19: Q11 | AI19: Recoverable | AK19: 1230 | AM19: ZA DE CHIG ZONE INDUSTRIELLE LES | AN19: ARNAC POMPADOUR | AO19: 7009627 | AP19: FR | AQ19: EMEA | AR19: 19 | AS19: 19230 | AT19: Av. Avelino Ribeiro, 900 | AU19: Paraisopolis | AV19: 10012 | AW19: BR | AX19: SA | AY19: Minas Gerais | AZ19: 37660-000 | BA19: SPS | BB19: Pending | BE19: 0 | BI19: Customer | BK19: Invoice | BM19: PSA | BP19: 0 | BQ19: Approved - ;; Approved - ;; Pending - | BR19: 1332.34 | BS19: 1332.34 | BT19: ; | BU19: ; | BV19: ; | BW19: BR | BX19: Bateria Positivo Smart | BY19: EUR | CC19: REPROGRAMA CC22 SMART | CD19: 1.0832 | CH19: 0 | CM19: 217018821 | CQ19: No | CS19: No | CT19: $ 500- 2500 | CV19: S4S-External Customer driven systems issues | CW19: Inbound Premium | CX19: Customer | CY19: Not Yet Approved | DA19: rodrigo.fernandes@aptiv.com | DB19: PSA | DC19: 1 | DD19: 9 | DF19: EQUISTONE LLP
A20: 45658 | B20: 177871 | C20: Customer rescheduled - Consulta CC22 | D20: PSA | E20: 45666 | F20: Paraisopolis | G20: Inbound Premium | H20: 61.73 | I20: 61.73 | J20: =H20/$H$1 -> 0.00065846303 | K20: S2-External Customer driven schedule changes | L20: APTIV MANUFATURA E SERVICOS DE-733223 | M20: SERENDIPITY ELECTRONICS-749804 | N20: REPROGRAMA DENTRO DO ACORDO LOGISTICO E FORA DO LEAD TIME DO FORNECEDOR, OS CUSTOS SERÃO ASSUMIDOS PELA APTIV | O20: DHL Express SA | P20: PTA-00206029 | Q20: 15386012; | R20: 6000; | S20: 4.54; | T20: Aptiv | U20: Premium - Productive | V20: marcia.p.torres@aptiv.com | W20: 2025-01-09T03:08:32.84 | X20: 2025-01-17T05:08:34.03 | Y20: SA | Z20: Closed Recovered | AA20: 0 | AC20: 61.73 | AE20: 10012 | AF20: Q11 | AH20: 61.73 | AI20: Non-Recoverable | AK20: 61.73 | AL20: USD | AM20: 152 E MAIN ST | AN20: HUNTINGTON | AO20: 749804 | AP20: US | AQ20: NA | AR20: NY | AS20: 11743-2958 | AT20: AVENIDA AVELINO RIBEIRO, 900 | AU20: PARAISOPOLIS | AV20: 733223 | AW20: BR | AX20: SA | AY20: MG | AZ20: 37660-000 | BA20: SPS | BB20: Approved | BC20: Edilson, Geraldo | BD20: 2025-01-14T11:24:05.00 | BE20: 0 | BG20: 63 9408 5552 | BI20: Customer | BK20: Invoice | BL20: Invoice | BO20: 4 Days 20 Hr 15 Min | BP20: 500 | BQ20: Approved - ;; Approved - ; | BR20: 61.73 | BS20: 61.73 | BT20: ; | BU20: 16x12x13; | BV20: ; | BW20: BR | BX20: SMART | BY20: USD | CB20: Kg | CC20: REPROGRAMA DENTRO DO ACORDO LOGISTICO E FORA DO LEAD TIME DO FORNECEDOR, OS CUSTOS SERÃO ASSUMIDOS PELA APTIV | CD20: 1 | CE20: 1 | CH20: 0 | CQ20: No | CS20: No | CT20: $ 0 - 500 | CU20: $ 0 - 500 | CV20: S2-External Customer driven schedule changes | CW20: Inbound Premium | CX20: Customer | CY20: Approved After Shipment | CZ20: CONSULTA CC22 SMART | DB20: PSA | DC20: 1 | DD20: 9
A21: 45658 | B21: 178122 | C21: Port Strike + Vessel delay- Consulta CC22 | D21: FIAT | E21: 45667 | F21: Ouros | G21: Inbound Premium | H21: 1902 | I21: 1902 | J21: =H21/$H$1 -> 0.020288299 | K21: PORT-PORT DELAYS / STRIKE | L21: Paraisopolis-10012 | M21: A.E.C. SRL-7028240 | N21: Port Delays | O21: DSV UTI Air & Sea Agenciamento de Transportes | Q21: 35017235; | R21: ; | S21: ; | T21: Aptiv | U21: Premium - Productive | V21: rodrigo.fernandes@aptiv.com | W21: 2025-01-17T06:14:13.83 | X21: 2025-01-17T06:13:39.90 | Y21: SA | Z21: Closed Recovered | AA21: 0 | AC21: 0 | AE21: 10023 | AF21: Q11 | AI21: Recoverable | AK21: 1902 | AM21: STRADA DEL FRANCESE 99 | AN21: TORINO | AO21: 7028240 | AP21: IT | AQ21: EMEA | AR21: TO | AS21: 10156 | AT21: Av. Avelino Ribeiro, 900 | AU21: Paraisopolis | AV21: 10012 | AW21: BR | AX21: SA | AY21: Minas Gerais | AZ21: 37660-000 | BA21: SPS | BB21: Pending | BE21: 0 | BI21: Significant_event | BK21: Invoice | BP21: 0 | BQ21: Approved - ;; Approved - ;; Pending - | BR21: 1902 | BS21: 1902 | BT21: ; | BU21: ; | BV21: ; | BW21: BR | BX21: Posterior X6H | BY21: USD | CC21: REPROGRAMA CC22 SMART - Port Delays: 35017235, 13971766 | CD21: 1 | CH21: 0 | CM21: 447580440 | CQ21: No | CS21: No | CT21: $ 500- 2500 | CV21: PORT-PORT DELAYS / STRIKE | CW21: Inbound Premium | CX21: Significant_event | CY21: Not Yet Approved | DA21: rodrigo.fernandes@aptiv.com | DB21: FIAT | DC21: 1 | DD21: 10 | DF21: A.E.C. SRL
A22: 45658 | B22: 178127 | C22: Stock Divergence | D22: FIAT | E22: 45667 | F22: Ouros | G22: Inbound Premium | H22: 375 | I22: 375 | J22: =H22/$H$1 -> 0.0040000589 | K22: S1I-Inventory loss/adjustments | L22: APTIV MANUFATURA E SERVICOS DE-743893 | M22: DELFINGEN IT-VERONA SRL-1056586 | N22: Divergencia estoque - Inventario Ouros | O22: DHL Express SA | P22: PTA-00206060 | Q22: 10763307; | R22: ; | S22: ; | T22: Aptiv | U22: Premium - Productive | V22: lua.barbosa.ribeiro@aptiv.com | W22: 2025-01-10T12:01:45.61 | X22: 2025-01-17T02:30:23.07 | Y22: SA | Z22: Closed Not Recovered | AA22: 0 | AC22: 0 | AD22: 2025-01-15T00:00:00 | AE22: 10023 | AF22: Q11 | AH22: 368.01 | AI22: Non-Recoverable | AK22: 375 | AL22: USD | AM22: LOCALITA VANZELLE 3 | AN22: RIVOLI VERONESE | AO22: 1056586 | AP22: IT | AQ22: EMEA | AR22: VR | AS22: 37010 | AT22: TV ANTONIO E FONSECA 250 BAIRRO | AU22: CONCEICAO DOS OUROS | AV22: 743893 | AW22: BR | AX22: SA | AY22: MG | AZ22: 37548-000 | BA22: SPS | BB22: Approved | BC22: Edilson, Geraldo | BD22: 2025-01-14T02:21:33.00 | BE22: 0 | BG22: 1622065896 | BI22: Aptiv | BK22: Invoice | BL22: Invoice | BO22: 4 Days 2 Hr 19 Min | BP22: 500 | BQ22: Approved - ;; Approved - ; | BR22: 375 | BS22: 375 | BT22: ; | BU22: ; | BV22: ; | BW22: BR | BX22: FIRE | BY22: USD | CC22: 13893739 | CD22: 1 | CE22: 1 | CH22: 0 | CM22: 505882451 | CQ22: No | CS22: No | CT22: $ 0 - 500 | CV22: S1I-Inventory loss/adjustments | CW22: Inbound Premium | CX22: Aptiv | CY22: Approved After Shipment | DA22: william.de.siqueira@aptiv.com | DB22: FIAT | DC22: 1 | DD22: 10 | DF22: DELFINGEN GROUP
A23: 45658 | B23: 178131 | C23: Port Strike + Vessel delay | D23: FIAT | E23: 45667 | F23: Paraisopolis | G23: Inbound Premium | H23: 1197 | I23: 1197 | J23: =H23/$H$1 -> 0.012768188 | K23: PORT-PORT DELAYS / STRIKE | L23: APTIV MANUFATURA E SERVICOS DE-724381 | M23: CABLENA S A-728252 | N23: Delay attraction Port in Santos - Vessel MSC RAYSHMI. | O23: DHL Express SA | Q23: M4754297; | R23: ; | S23: ; | T23: Aptiv | U23: Premium - Productive | V23: lua.barbosa.ribeiro@aptiv.com | W23: 2025-01-10T12:32:13.87 | X23: 2025-01-10T12:29:00.52 | Y23: SA | Z23: Closed Not Recovered | AA23: 0 | AC23: 0 | AD23: 2025-01-15T00:00:00 | AE23: 10012 | AF23: Q11 | AI23: Non-Recoverable | AK23: 1197 | AM23: CALLE E, PARCELLAS 43-44 | AN23: ZARAGOZA | AO23: 728252 | AP23: ES | AQ23: EMEA | AR23: Z | AS23: 50016 | AT23: AVENIDA AVELINO RIBEIRO, 900 | AU23: PARAISOPOLIS | AV23: 724381 | AW23: BR | AX23: SA | AY23: MG | AZ23: 37660-000 | BA23: SPS | BB23: Pending | BE23: 0 | BI23: Significant_event | BK23: Invoice | BP23: 0 | BQ23: Approved - ;; Approved - ;; Pending - | BR23: 1197 | BS23: 1197 | BT23: ; | BU23: ; | BV23: ; | BW23: BR | BX23: PROJETO P | BY23: USD | CD23: 1 | CH23: 0 | CQ23: No | CS23: No | CT23: $ 500- 2500 | CV23: PORT-PORT DELAYS / STRIKE | CW23: Inbound Premium | CX23: Significant_event | CY23: Not Yet Approved | DA23: william.de.siqueira@aptiv.com | DB23: FIAT | DC23: 1 | DD23: 10
A24: 45658 | B24: 178138 | C24: Customer rescheduled - Consulta CC22 | D24: PSA | E24: 45667 | F24: Paraisopolis | G24: Inbound Premium | H24: 98.78 | I24: 98 | J24: =H24/$H$1 -> 0.0010536688 | K24: B2-Behind Schedule-Aptiv | L24: APTIV MANUFATURA E SERVICOS DE-724381 | M24: APTIV HOLDINGS FRANCE SAS-768624 | N24: Reprograma Cliente dentro do protocolo logistico. | O24: DHL Express SA | P24: PTA-00206058 | Q24: 33512190; | R24: ; | S24: ; | T24: Aptiv | U24: Premium - Productive | V24: lua.barbosa.ribeiro@aptiv.com | W24: 2025-01-10T01:39:34.86 | X24: 2025-01-17T05:36:03.04 | Y24: SA | Z24: Closed Recovered | AA24: 0 | AC24: 98.78 | AD24: 2025-01-16T00:00:00 | AE24: 10012 | AF24: Q11 | AH24: 98.78 | AI24: Non-Recoverable | AK24: 98 | AL24: USD | AM24: ZI DES LONGS REAGES | AN24: EPERNON | AO24: 768624 | AP24: FR | AQ24: EMEA | AR24: 28 | AS24: 28230 | AT24: AVENIDA AVELINO RIBEIRO, 900 | AU24: PARAISOPOLIS | AV24: 724381 | AW24: BR | AX24: SA | AY24: MG | AZ24: 37660-000 | BA24: SPS | BB24: Approved | BC24: Edilson, Geraldo | BD24: 2025-01-14T02:20:38.00 | BE24: 0 | BG24: 1290920982 | BI24: Aptiv | BK24: Invoice | BL24: Invoice | BO24: 4 Days 0 Hr 41 Min | BP24: 500 | BQ24: Approved - ;; Approved - ; | BR24: 98.78 | BS24: 98.78 | BT24: ; | BU24: ; | BV24: ; | BW24: BR | BX24: Bateria Positivo PSA | BY24: USD | CD24: 1 | CE24: 1 | CH24: 0 | CQ24: No | CS24: No | CT24: $ 0 - 500 | CU24: $ 0 - 500 | CV24: B2-Behind Schedule-Aptiv | CW24: Inbound Premium | CX24: Aptiv | CY24: Approved After Shipment | CZ24: REPROGRAMA CC22 SMART | DA24: william.de.siqueira@aptiv.com | DB24: PSA | DC24: 1 | DD24: 10
A25: 45658 | B25: 178176 | C25: Project - prototypes/ samples | D25: VW | E25: 45667 | F25: Paraisopolis | G25: Inbound Premium | H25: 280.21 | I25: 280.21 | J25: =H25/$H$1 -> 0.0029889507 | K25: E1P-Prototypes/Samples | L25: TE CONNECTIVITY BRASIL INDUSTRIA DE-7065022 | M25: APTIV MANUFATURA E SERVICOS DE-724381 | N25: Cutso incluso na cotação 090-24 | O25: TRANSPORTADORA PITUTA | P25: PTA-00206057 | Q25: M5748001; | R25: ; | S25: ; | T25: Aptiv | U25: Premium - Productive | V25: Stefany.Tressoldi@aptiv.com | W25: 2025-01-10T04:53:28.75 | X25: 2025-01-14T02:20:26.00 | Y25: SA | Z25: Closed Recovered | AA25: 0 | AC25: 280.21 | AE25: 10012 | AF25: Q11 | AH25: 1400 | AI25: Recoverable | AK25: 1400 | AL25: BRL | AM25: AVENIDA AVELINO RIBEIRO, 900 | AN25: PARAISOPOLIS | AO25: 724381 | AP25: BR | AQ25: SA | AR25: MG | AS25: 37660-000 | AT25: RUA SAMARITA 1117 | AU25: SAO PAULO | AV25: 7065022 | AW25: BR | AX25: SA | AY25: SP | AZ25: 02518-080 | BA25: SPS | BB25: Approved | BC25: Edilson, Geraldo | BD25: 2025-01-14T02:20:26.00 | BE25: 0 | BI25: Aptiv | BK25: Invoice | BL25: Invoice | BO25: 3 Days 21 Hr 26 Min | BP25: 500 | BQ25: Approved - ;; Approved - ; | BR25: 280.21 | BS25: 280.21 | BT25: ; | BU25: ; | BV25: ; | BW25: BR | BX25: 246 A0 SUV | BY25: BRL | CD25: 0.20015212 | CE25: 0.20015212 | CH25: 0 | CN25: 485203835 | CQ25: No | CS25: No | CT25: $ 0 - 500 | CU25: $ 0 - 500 | CV25: E1P-Prototypes/Samples | CW25: Inbound Premium | CX25: Aptiv | CY25: Approved After Shipment | DB25: VW | DC25: 1 | DD25: 10 | DG25: TE CONNECTIVITY LTD.
A26: 45658 | B26: 178275 | C26: Customer reschedule | D26: PSA | E26: 45667 | F26: Paraisopolis | G26: Inbound Premium | H26: 139.06 | I26: 139.06 | J26: =H26/$H$1 -> 0.0014833285 | K26: C4-Capacity-External Customer Resp | L26: Paraisopolis-10012 | M26: PACIFIC FOCUS INC-1061901 | N26: increase of customer | O26: DHL Express SA | P26: PTA-00206056 | Q26: 15337975; | R26: ; | S26: ; | T26: Customer | U26: Premium - Productive | V26: rodrigo.fernandes@aptiv.com | W26: 2025-01-10T07:28:49.17 | X26: 2025-01-17T05:38:47.01 | Y26: SA | Z26: Closed Recovered | AA26: 0 | AC26: 0 | AE26: 10012 | AF26: Q11 | AH26: 139.63 | AI26: Recoverable | AK26: 139.06 | AL26: USD | AM26: 13904 EQUITABLE RD | AN26: CERRITOS | AO26: 1061901 | AP26: US | AQ26: NA | AR26: CA | AS26: 90703-1013 | AT26: Av. Avelino Ribeiro, 900 | AU26: Paraisopolis | AV26: 10012 | AW26: BR | AX26: SA | AY26: Minas Gerais | AZ26: 37660-000 | BA26: SPS | BB26: Approved | BC26: Edilson, Geraldo | BD26: 2025-01-14T02:20:19.00 | BE26: 0 | BI26: Customer | BK26: Invoice | BL26: Invoice | BM26: PSA | BO26: 3 Days 18 Hr 51 Min | BP26: 500 | BQ26: Approved - ;; Approved - ; | BR26: 139.06 | BS26: 139.06 | BT26: ; | BU26: ; | BV26: ; | BW26: BR | BX26: CC22 | BY26: USD | CC26: Consulta CC22 | CD26: 1 | CE26: 1 | CH26: 0 | CM26: 999103825 | CQ26: No | CS26: No | CT26: $ 0 - 500 | CV26: C4-Capacity-External Customer Resp | CW26: Inbound Premium | CX26: Customer | CY26: Approved After Shipment | CZ26: REPROGRAMA C22 SMART | DA26: rodrigo.fernandes@aptiv.com | DB26: PSA | DC26: 1 | DD26: 10 | DF26: PACIFIC FOCUS INC
A27: 45658 | B27: 178389 | C27: Project - prototypes/ samples | D27: GM | E27: 45670 | F27: Pinhal | G27: Inbound Premium | H27: 123 | I27: 123 | J27: =H27/$H$1 -> 0.0013120193 | K27: E1P-Prototypes/Samples | L27: APTIV MANUFATURA E SERVICOS DE-734227 | M27: SERENDIPITY ELECTRONICS-749804 | N27: Parts for sales from prototype pieces. Freight is included in the piece price. | O27: DHL Express SA | P27: PTA-00206030 | Q27: 35104248; | R27: ; | S27: ; | T27: Aptiv | U27: Premium - Productive | V27: rayzza.peres@aptiv.com | W27: 2025-01-13T11:56:16.66 | X27: 2025-01-14T11:24:17.00 | Y27: SA | Z27: Closed Recovered | AA27: 0 | AC27: 123 | AE27: 10010 | AF27: Q18 | AH27: 123 | AI27: Recoverable | AK27: 123 | AL27: USD | AM27: 152 E MAIN ST | AN27: HUNTINGTON | AO27: 749804 | AP27: US | AQ27: NA | AR27: NY | AS27: 11743-2958 | AT27: AVENIDA AVELINO RIBEIRO, 900 | AU27: PARAISOPOLIS | AV27: 734227 | AW27: BR | AX27: SA | AY27: MG | AZ27: 37660-000 | BA27: SPS | BB27: Approved | BC27: Edilson, Geraldo | BD27: 2025-01-14T11:24:17.00 | BE27: 0 | BG27: 4169584716 | BI27: Aptiv | BK27: Invoice | BL27: Invoice | BO27: 0 Days 23 Hr 28 Min | BP27: 500 | BQ27: Approved - ;; Approved - ; | BR27: 123 | BS27: 123 | BT27: ; | BU27: ; | BV27: ; | BW27: BR | BX27: GEM MY27,5 HIBRIDO | BY27: USD | CC27: DPE48934 | CD27: 1 | CE27: 1 | CH27: 0 | CQ27: No | CS27: No | CT27: $ 0 - 500 | CU27: $ 0 - 500 | CV27: E1P-Prototypes/Samples | CW27: Inbound Premium | CX27: Aptiv | CY27: Approved After Shipment | DB27: GM | DC27: 1 | DD27: 13
A28: 45658 | B28: 176417 | C28: Customer reschedule | D28: PSA | E28: 45670 | F28: Paraisopolis | G28: Inbound Premium | H28: 932.3 | I28: 852.66 | J28: =H28/$H$1 -> 0.0099446797 | K28: S2-External Customer driven schedule changes | L28: APTIV MANUFATURA E SERVICOS DE-724381 | M28: KUM LLC-1082372 | N28: INCREASE FROM CUSTOMER | O28: DHL Express SA | P28: PTA-00204595 | Q28: 13947042; | R28: ; | S28: ; | T28: Customer | U28: Premium - Productive | V28: Moraes.Arnaldo@aptiv.com | W28: 2024-12-26T02:06:41.66 | X28: 2025-01-14T05:14:38.91 | Y28: SA | Z28: Closed Recovered | AA28: 0 | AC28: 932.3 | AE28: 10012 | AF28: Q11 | AH28: 932.3 | AI28: Recoverable | AK28: 852.66 | AL28: USD | AM28: 53 JEONEUMNONGGONG-GIL, DUSEO-MYEON | AN28: ULSAN | AO28: 1082372 | AP28: KR | AQ28: AP | AR28: 31 | AS28: 44911 | AT28: AVENIDA AVELINO RIBEIRO, 900 | AU28: PARAISOPOLIS | AV28: 724381 | AW28: BR | AX28: SA | AY28: MG | AZ28: 37660-000 | BA28: SPS | BB28: Approved | BC28: Flores, Lorena | BD28: 2025-01-02T03:40:42.00 | BE28: 0 | BG28: 99299618540 | BI28: Customer | BK28: Invoice | BL28: Invoice | BM28: PSA | BO28: 7 Days 1 Hr 34 Min | BQ28: Approved - ;; Approved - ;; Approved - ;; Approved - ;; Approved - Approved by teams 1/2/25. ; | BR28: 932.3 | BS28: 932.3 | BT28: ; | BU28: ; | BV28: ; | BW28: BR | BX28: CC22 | BY28: USD | CC28: RECUPERAÇÃO DO CUSTO SENDO NEGOCIANDO COM O CLIENTE | CD28: 1 | CE28: 1 | CH28: 0 | CM28: 217616996 | CQ28: No | CS28: No | CT28: $ 500- 2500 | CU28: $ 500- 2500 | CV28: S2-External Customer driven schedule changes | CW28: Inbound Premium | CX28: Customer | CY28: Approved Prior To Shipment | CZ28: CONSULTA CC22 SMART | DB28: PSA | DC28: 1 | DD28: 13 | DF28: APTIV PLC
A29: 45658 | B29: 178359 | C29: End of Project- Consulta CC22 | D29: PSA | E29: 45671 | F29: Paraisopolis | G29: Inbound Premium | H29: 570 | I29: 570 | J29: =H29/$H$1 -> 0.0060800895 | K29: PC-Plant PC Resp | L29: APTIV MANUFATURA E SERVICOS DE-733223 | M29: ROBERT BOSCH SRL-755720 | N29: End of project | O29: DSV UTI Air & Sea Agenciamento de Transportes | Q29: 35511515; | R29: ; | S29: ; | T29: Aptiv | U29: Premium - Productive | V29: gislene.de.fatima.clemente@aptiv.com | W29: 2025-01-13T09:29:18.53 | X29: 2025-01-13T09:27:19.37 | Y29: SA | Z29: Closed Recovered | AA29: 0 | AC29: 0 | AE29: 10012 | AF29: Q11 | AI29: Non-Recoverable | AK29: 570 | AM29: ROBERT BOSCH 1 PARC INDUSTRIAL TETR | AN29: JUCU | AO29: 755720 | AP29: RO | AQ29: EMEA | AR29: CJ | AS29: 407350 | AT29: AVENIDA AVELINO RIBEIRO, 900 | AU29: PARAISOPOLIS | AV29: 733223 | AW29: BR | AX29: SA | AY29: MG | AZ29: 37660-000 | BA29: SPS | BB29: Pending | BE29: 0 | BI29: Aptiv | BK29: Invoice | BP29: 0 | BQ29: Approved - ;; Approved - ;; Pending - | BR29: 570 | BS29: 570 | BT29: ; | BU29: ; | BV29: ; | BW29: BR | BX29: K0 negative battery | BY29: USD | CC29: End of project | CD29: 1 | CH29: 0 | CQ29: No | CS29: No | CT29: $ 500- 2500 | CV29: PC-Plant PC Resp | CW29: Inbound Premium | CX29: Aptiv | CY29: Not Yet Approved | DB29: PSA | DC29: 1 | DD29: 14
A30: 45658 | B30: 178363 | C30: Customer reschedule | D30: PSA | E30: 45671 | F30: Paraisopolis | G30: Inbound Premium | H30: 1000 | I30: 1000 | J30: =H30/$H$1 -> 0.010666824 | K30: PC-Plant PC Resp | L30: APTIV MANUFATURA E SERVICOS DE-733223 | M30: MOLEX ELEKTRONIK GMBH-7081868 | N30: The costs will be recovered under Consulta CC22 | O30: DSV UTI Air & Sea Agenciamento de Transportes | Q30: 35361315; | R30: ; | S30: ; | T30: Aptiv | U30: Premium - Productive | V30: gislene.de.fatima.clemente@aptiv.com | W30: 2025-01-13T09:41:13.75 | X30: 2025-01-13T09:31:04.68 | Y30: SA | Z30: Open | AA30: 0 | AC30: 0 | AE30: 10012 | AF30: Q11 | AI30: Recoverable | AJ30: The costs will be recovered under Consulta CC22 | AK30: 1000 | AM30: GRASHOFSTR. 17 | AN30: ETTLINGEN | AO30: 7081868 | AP30: DE | AQ30: EMEA | AR30: BW | AS30: 76275 | AT30: AVENIDA AVELINO RIBEIRO, 900 | AU30: PARAISOPOLIS | AV30: 733223 | AW30: BR | AX30: SA | AY30: MG | AZ30: 37660-000 | BA30: SPS | BB30: Pending | BE30: 0 | BI30: Aptiv | BK30: Invoice | BP30: 0 | BQ30: Approved - ;; Approved - ;; Pending - | BR30: 1000 | BS30: 1000 | BT30: ; | BU30: ; | BV30: ; | BW30: BR | BX30: Body CC22 | BY30: USD | CC30: The costs will be recovered under Consulta CC22 | CD30: 1 | CH30: 0 | CM30: 726761322 | CQ30: No | CS30: No | CT30: $ 500- 2500 | CV30: PC-Plant PC Resp | CW30: Inbound Premium | CX30: Aptiv | CY30: Not Yet Approved | DB30: PSA | DC30: 1 | DD30: 14 | DF30: MOLEX FOREIGN HOLDINGS, L.P.
A31: 45658 | B31: 178702 | C31: Customer rescheduled - Consulta 44 | D31: JOHN DEERE | E31: 45671 | F31: Paraisopolis | G31: Inbound Premium | H31: 56.45 | I31: 56.45 | J31: =H31/$H$1 -> 0.0006021422 | K31: S2-External Customer driven schedule changes | L31: APTIV MANUFATURA E SERVICOS DE-733223 | M31: SERENDIPITY ELECTRONICS, INC.-1062318 | N31: REPROGRAMA DO CLIENTE | O31: DHL Express SA | P31: PTA-00206059 | Q31: 02965401; | R31: ; | S31: ; | T31: Customer | U31: Premium - Productive | V31: Moraes.Arnaldo@aptiv.com | W31: 2025-01-14T11:07:04.48 | X31: 2025-01-20T06:30:16.73 | Y31: SA | Z31: Closed Recovered | AA31: 0 | AC31: 56.45 | AE31: 10012 | AF31: Q11 | AH31: 56.45 | AI31: Recoverable | AK31: 56.45 | AL31: USD | AM31: 152 E MAIN ST STE D | AN31: HUNTINGTON | AO31: 1062318 | AP31: US | AQ31: NA | AR31: NY | AS31: 11743-2958 | AT31: AVENIDA AVELINO RIBEIRO, 900 | AU31: PARAISOPOLIS | AV31: 733223 | AW31: BR | AX31: SA | AY31: MG | AZ31: 37660-000 | BA31: SPS | BB31: Approved | BC31: Edilson, Geraldo | BD31: 2025-01-14T02:21:01.00 | BE31: 0 | BG31: 3392023935 | BI31: Customer | BK31: Invoice | BL31: Invoice | BM31: JOHN DEERE | BO31: 0 Days 3 Hr 13 Min | BP31: 500 | BQ31: Approved - ;; Approved - ; | BR31: 56.45 | BS31: 56.45 | BT31: ; | BU31: ; | BV31: ; | BW31: BR | BX31: CARDIAL | BY31: USD | CC31: CONSULTA 44 - Reprograma JD JANEIRO FEVEREIRO | CD31: 1 | CE31: 1 | CH31: 0 | CM31: 800114696 | CQ31: No | CS31: No | CT31: $ 0 - 500 | CU31: $ 0 - 500 | CV31: S2-External Customer driven schedule changes | CW31: Inbound Premium | CX31: Customer | CY31: Approved Day Of Shipment | CZ31: Consulta 44 JD horizontina | DB31: JOHN DEERE | DC31: 1 | DD31: 14 | DF31: SERENDIPITY ELECTRONICS, INC.
A32: 45658 | B32: 178740 | C32: Port Strick + Vessel Delay | D32: GM | E32: 45671 | F32: Pinhal | G32: Inbound Premium | H32: 25.83 | I32: 110.71 | J32: =H32/$H$1 -> 0.00027552406 | K32: C2-Capacity-Aptiv Resp | L32: APTIV MANUFATURA E SERVICOS DE-727173 | M32: TRANSPORTADORA PITUTA LTDA-Dummy | N32: Carro especial para coleta do terminal 33136798, que se tornou critico devido a inspeção de madeira do processo M1026/24. Coleta na HEILIND SP. | O32: TRANSPORTADORA PITUTA | P32: PTA-00206298 | Q32: 33136798; | R32: ; | S32: ; | T32: Aptiv | U32: Premium - Productive | V32: Guilherme.Lucio@aptiv.com | W32: 2025-01-14T01:35:39.49 | X32: 2025-01-17T06:46:06.64 | Y32: SA | Z32: Closed Not Recovered | AA32: 0 | AC32: 25.83 | AD32: 2025-01-14T00:00:00 | AE32: 10010 | AF32: Q18 | AH32: 129.03 | AI32: Non-Recoverable | AK32: 553.13 | AL32: BRL | AM32: RUA ENGENHEIRO ALBERT LEIMER, 1174 | AN32: Guarulhos | AO32: Dummy | AP32: BR | AQ32: SA | AR32: Sao Paulo | AS32: 07140020 | AT32: JOSE MONFARDINI N 3 845 LOTEAMENTO | AU32: ESPIRITO SANTO DO PINHAL | AV32: 727173 | AW32: BR | AX32: SA | AY32: SP | AZ32: 13990000 | BA32: SPS | BB32: Approved | BC32: Edilson, Geraldo | BD32: 2025-01-15T12:36:44.00 | BE32: 0 | BF32: TRANSPORTADORA PITUTA | BG32: COLETA ESPECIAL | BI32: Aptiv | BK32: Personal Estimate | BL32: Invoice | BO32: 0 Days 23 Hr 1 Min | BP32: 500 | BQ32: Approved - ;; Approved - ; | BR32: 25.83 | BS32: 25.83 | BT32: ; | BU32: ; | BV32: ; | BW32: BR | BX32: BODY | BY32: BRL | CD32: 0.20015212 | CE32: 0.20015212 | CH32: 0 | CQ32: No | CS32: No | CT32: $ 0 - 500 | CU32: $ 0 - 500 | CV32: C2-Capacity-Aptiv Resp | CW32: Inbound Premium | CX32: Aptiv | CY32: Approved After Shipment | DA32: Guilherme.Lucio@aptiv.com | DB32: GM | DC32: 1 | DD32: 14
A33: 45658 | B33: 178884 | C33: Project - prototypes/ samples | D33: JOHN DEERE | E33: 45671 | F33: Paraisopolis | G33: Inbound Premium | H33: 154 | I33: 154 | J33: =H33/$H$1 -> 0.0016426908 | K33: E1P-Prototypes/Samples | L33: APTIV MANUFATURA E SERVICOS DE-724381 | M33: APTIV CENTEC I (FW98)-725544 | N33: Parts for project development. Freight approved by email by the Project Manager. | O33: DHL Express SA | P33: PTA-00206295 | Q33: 13767803; | R33: ; | S33: ; | T33: Aptiv | U33: Premium - Productive | V33: rayzza.peres@aptiv.com | W33: 2025-01-14T07:40:53.32 | X33: 2025-01-15T12:35:33.00 | Y33: SA | Z33: Open | AA33: 0 | AC33: 0 | AE33: 10012 | AF33: Q11 | AI33: Recoverable | AK33: 154 | AL33: USD | AM33: CARRETERA SALTILLO PIEDRAS NEGRAS K | AN33: RAMOS ARIZPE | AO33: 725544 | AP33: MX | AQ33: NA | AR33: COA | AS33: 25900 | AT33: AVENIDA AVELINO RIBEIRO, 900 | AU33: PARAISOPOLIS | AV33: 724381 | AW33: BR | AX33: SA | AY33: MG | AZ33: 37660-000 | BA33: SPS | BB33: Approved | BC33: Edilson, Geraldo | BD33: 2025-01-15T12:35:33.00 | BE33: 0 | BF33: DHL Express SA | BI33: Aptiv | BK33: Invoice | BL33: Invoice | BO33: 0 Days 16 Hr 54 Min | BP33: 500 | BQ33: Approved - ;; Approved - ; | BR33: 154 | BS33: 154 | BT33: ; | BU33: ; | BV33: ; | BW33: BR | BX33: MERCURY | BY33: USD | CC33: 13767803 | CD33: 1 | CE33: 1 | CH33: 0 | CQ33: No | CS33: No | CT33: $ 0 - 500 | CV33: E1P-Prototypes/Samples | CW33: Inbound Premium | CX33: Aptiv | CY33: Approved After Shipment | DB33: JOHN DEERE | DC33: 1 | DD33: 14
A34: 45658 | B34: 178885 | C34: Project - prototypes/ samples | D34: JOHN DEERE | E34: 45671 | F34: Paraisopolis | G34: Inbound Premium | H34: 220 | I34: 220 | J34: =H34/$H$1 -> 0.0023467012 | K34: E1P-Prototypes/Samples | L34: APTIV MANUFATURA E SERVICOS DE-724381 | M34: APTIV CENTEC I (FW98)-725544 | N34: Parts for project development. Freight approved by email by the Project Manager. | O34: DHL Express SA | P34: PTA-00206294 | Q34: 13710085; | R34: ; | S34: ; | T34: Aptiv | U34: Premium - Productive | V34: rayzza.peres@aptiv.com | W34: 2025-01-14T07:42:18.02 | X34: 2025-01-15T12:35:22.00 | Y34: SA | Z34: Open | AA34: 0 | AC34: 0 | AE34: 10012 | AF34: Q11 | AI34: Recoverable | AK34: 220 | AM34: CARRETERA SALTILLO PIEDRAS NEGRAS K | AN34: RAMOS ARIZPE | AO34: 725544 | AP34: MX | AQ34: NA | AR34: COA | AS34: 25900 | AT34: AVENIDA AVELINO RIBEIRO, 900 | AU34: PARAISOPOLIS | AV34: 724381 | AW34: BR | AX34: SA | AY34: MG | AZ34: 37660-000 | BA34: SPS | BB34: Approved | BC34: Edilson, Geraldo | BD34: 2025-01-15T12:35:22.00 | BE34: 0 | BF34: DHL Express SA | BI34: Aptiv | BK34: Invoice | BL34: Invoice | BO34: 0 Days 16 Hr 53 Min | BP34: 500 | BQ34: Approved - ;; Approved - ; | BR34: 220 | BS34: 220 | BT34: ; | BU34: ; | BV34: ; | BW34: BR | BX34: MERCURY | BY34: USD | CC34: 13510085 e 15429045 | CD34: 1 | CH34: 0 | CQ34: No | CS34: No | CT34: $ 0 - 500 | CV34: E1P-Prototypes/Samples | CW34: Inbound Premium | CX34: Aptiv | CY34: Approved After Shipment | DB34: JOHN DEERE | DC34: 1 | DD34: 14
A35: 45658 | B35: 178886 | C35: Project - prototypes/ samples | D35: GM | E35: 45671 | F35: Pinhal | G35: Inbound Premium | H35: 800 | I35: 800 | J35: =H35/$H$1 -> 0.0085334589 | K35: E1P-Prototypes/Samples | L35: APTIV MANUFATURA E SERVICOS DE DIST-7048271 | M35: APTIV CONNECTION SYSTEMS (NANTONG)-761233 | N35: Parts for project development. Freight approved by email by the Project Manager. | O35: DSV UTI Air & Sea Agenciamento de Transportes | P35: PTA-00208202 | Q35: 35935955; | R35: ; | S35: ; | T35: Aptiv | U35: Premium - Productive | V35: rayzza.peres@aptiv.com | W35: 2025-01-14T07:55:16.21 | X35: 2025-01-27T05:32:44.00 | Y35: SA | Z35: Open | AA35: 0 | AC35: 800 | AE35: 10010 | AF35: Q18 | AH35: 800 | AI35: Recoverable | AK35: 800 | AL35: USD | AM35: NO 9 HEBIN ROAD TONGZHOU ECONOMIC | AN35: TONGZHOU | AO35: 761233 | AP35: CN | AQ35: AP | AR35: 100 | AS35: 226300 | AT35: RUA JOSE MONFARDINI 3845 | AU35: ESPIRITO SANTO DO PINHAL | AV35: 7048271 | AW35: BR | AX35: SA | AY35: SP | AZ35: 13990-000 | BA35: SPS | BB35: Approved | BC35: Edilson, Geraldo | BD35: 2025-01-27T05:32:44.00 | BE35: 0 | BI35: Aptiv | BK35: Personal Estimate | BL35: Personal Estimate | BO35: 12 Days 21 Hr 37 Min | BP35: 500 | BQ35: Approved - ;; Approved - ;; Approved - ;; Approved - ; | BR35: 800 | BS35: 800 | BT35: ; | BU35: ; | BV35: ; | BW35: BR | BX35: GEM MY26 | BY35: USD | CC35: DPE48798 | CD35: 1 | CE35: 1 | CH35: 0 | CN35: 217616996 | CQ35: No | CS35: No | CT35: $ 500- 2500 | CU35: $ 500- 2500 | CV35: E1P-Prototypes/Samples | CW35: Inbound Premium | CX35: Aptiv | CY35: Approved After Shipment | DB35: GM | DC35: 1 | DD35: 14 | DG35: APTIV PLC
